import in.krosbits.musicolet.MusicActivity;

public final class al extends dv0 {
  public final int a;
  
  public static void p() {
    try {
      MusicActivity.R0.d0.b1();
    } finally {
      Exception exception;
    } 
  }
  
  public void a(iv0 paramiv0) {
    switch (this.a) {
      default:
        return;
      case 1:
        break;
    } 
    p();
  }
  
  public void b(iv0 paramiv0) {
    switch (this.a) {
      default:
        return;
      case 1:
        break;
    } 
    p();
  }
  
  public void c(iv0 paramiv0) {
    switch (this.a) {
      default:
        return;
      case 1:
        break;
    } 
    p();
  }
  
  public void d(iv0 paramiv0, hv0 paramhv0) {
    switch (this.a) {
      default:
        return;
      case 1:
        break;
    } 
    p();
  }
  
  public void h(iv0 paramiv0) {
    switch (this.a) {
      default:
        return;
      case 1:
        break;
    } 
    p();
  }
  
  public void i(iv0 paramiv0, hv0 paramhv0) {
    switch (this.a) {
      default:
        return;
      case 1:
        break;
    } 
    p();
  }
  
  public final void o(hv0 paramhv0) {
    // Byte code:
    //   0: aload_0
    //   1: getfield a : I
    //   4: tableswitch default -> 24, 0 -> 36
    //   24: getstatic in/krosbits/musicolet/MusicActivity.R0 : Lin/krosbits/musicolet/MusicActivity;
    //   27: getfield d0 : Lz71;
    //   30: iconst_0
    //   31: invokevirtual h1 : (I)Z
    //   34: pop
    //   35: return
    //   36: getstatic in/krosbits/musicolet/MusicService.P0 : Lin/krosbits/musicolet/MusicService;
    //   39: invokevirtual U : ()V
    //   42: goto -> 50
    //   45: astore_1
    //   46: aload_1
    //   47: invokevirtual printStackTrace : ()V
    //   50: return
    //   51: astore_1
    //   52: goto -> 35
    // Exception table:
    //   from	to	target	type
    //   24	35	51	finally
    //   36	42	45	finally
  }
}


/* Location:              C:\Users\Kevin\Downloads\dex-tools-v2.4\dex-tools-v2.4\musicolet-dex2jar.jar!\al.class
 * Java compiler version: 6 (50.0)
 * JD-Core Version:       1.1.3
 */