import java.util.concurrent.atomic.AtomicReference;
import java.util.concurrent.atomic.AtomicReferenceFieldUpdater;

public final class ip1 extends g0 implements w80, gp1, kd0, x80 {
  public static final AtomicReferenceFieldUpdater g = AtomicReferenceFieldUpdater.newUpdater(ip1.class, Object.class, "_state$volatile");
  
  public static final long h = oi.a.objectFieldOffset(ip1.class.getDeclaredField("_state$volatile"));
  
  public volatile Object _state$volatile;
  
  public int f;
  
  public ip1(Object paramObject) {
    this._state$volatile = paramObject;
  }
  
  public final Object a(x80 paramx80, cs paramcs) {
    // Byte code:
    //   0: aload_0
    //   1: astore #9
    //   3: getstatic ys.b : Lys;
    //   6: astore #21
    //   8: aload_2
    //   9: instanceof hp1
    //   12: ifeq -> 49
    //   15: aload_2
    //   16: checkcast hp1
    //   19: astore #8
    //   21: aload #8
    //   23: getfield m : I
    //   26: istore_3
    //   27: iload_3
    //   28: ldc -2147483648
    //   30: iand
    //   31: ifeq -> 49
    //   34: aload #8
    //   36: iload_3
    //   37: ldc -2147483648
    //   39: iadd
    //   40: putfield m : I
    //   43: aload #8
    //   45: astore_2
    //   46: goto -> 60
    //   49: new hp1
    //   52: dup
    //   53: aload #9
    //   55: aload_2
    //   56: invokespecial <init> : (Lip1;Lcs;)V
    //   59: astore_2
    //   60: aload_2
    //   61: getfield k : Ljava/lang/Object;
    //   64: astore #12
    //   66: aload_2
    //   67: getfield m : I
    //   70: istore_3
    //   71: iconst_0
    //   72: istore #7
    //   74: iconst_3
    //   75: istore #4
    //   77: iload_3
    //   78: ifeq -> 245
    //   81: iload_3
    //   82: iconst_1
    //   83: if_icmpeq -> 212
    //   86: iload_3
    //   87: iconst_2
    //   88: if_icmpeq -> 158
    //   91: iload_3
    //   92: iconst_3
    //   93: if_icmpne -> 151
    //   96: aload_2
    //   97: getfield j : Ljava/lang/Object;
    //   100: astore #18
    //   102: aload_2
    //   103: getfield i : Lvj0;
    //   106: astore #14
    //   108: aload_2
    //   109: getfield h : Ljp1;
    //   112: astore #10
    //   114: aload_2
    //   115: getfield g : Lx80;
    //   118: astore #13
    //   120: aload_2
    //   121: getfield f : Lip1;
    //   124: astore #9
    //   126: aload #10
    //   128: astore #8
    //   130: aload #9
    //   132: astore_1
    //   133: aload #12
    //   135: invokestatic r0 : (Ljava/lang/Object;)V
    //   138: aload_2
    //   139: astore #12
    //   141: aload #9
    //   143: astore_2
    //   144: goto -> 1099
    //   147: astore_2
    //   148: goto -> 1119
    //   151: ldc 'call to 'resume' before 'invoke' with coroutine'
    //   153: invokestatic f : (Ljava/lang/String;)V
    //   156: aconst_null
    //   157: areturn
    //   158: aload_2
    //   159: getfield j : Ljava/lang/Object;
    //   162: astore #11
    //   164: aload_2
    //   165: getfield i : Lvj0;
    //   168: astore #14
    //   170: aload_2
    //   171: getfield h : Ljp1;
    //   174: astore #10
    //   176: aload_2
    //   177: getfield g : Lx80;
    //   180: astore #15
    //   182: aload_2
    //   183: getfield f : Lip1;
    //   186: astore #9
    //   188: aload #10
    //   190: astore #8
    //   192: aload #9
    //   194: astore_1
    //   195: aload #12
    //   197: invokestatic r0 : (Ljava/lang/Object;)V
    //   200: aload_2
    //   201: astore #17
    //   203: iload #4
    //   205: istore_3
    //   206: aload #9
    //   208: astore_2
    //   209: goto -> 749
    //   212: aload_2
    //   213: getfield h : Ljp1;
    //   216: astore #10
    //   218: aload_2
    //   219: getfield g : Lx80;
    //   222: astore #8
    //   224: aload_2
    //   225: getfield f : Lip1;
    //   228: astore_1
    //   229: aload #12
    //   231: invokestatic r0 : (Ljava/lang/Object;)V
    //   234: goto -> 451
    //   237: astore_2
    //   238: aload #10
    //   240: astore #8
    //   242: goto -> 1119
    //   245: aload #12
    //   247: invokestatic r0 : (Ljava/lang/Object;)V
    //   250: aload_0
    //   251: monitorenter
    //   252: aload #9
    //   254: getfield b : [Ljp1;
    //   257: astore #10
    //   259: aload #10
    //   261: ifnonnull -> 285
    //   264: aload #9
    //   266: invokevirtual d : ()[Ljp1;
    //   269: astore #8
    //   271: aload #9
    //   273: aload #8
    //   275: putfield b : [Ljp1;
    //   278: goto -> 329
    //   281: astore_1
    //   282: goto -> 1215
    //   285: aload #10
    //   287: astore #8
    //   289: aload #9
    //   291: getfield c : I
    //   294: aload #10
    //   296: arraylength
    //   297: if_icmplt -> 329
    //   300: aload #10
    //   302: aload #10
    //   304: arraylength
    //   305: iconst_2
    //   306: imul
    //   307: invokestatic copyOf : ([Ljava/lang/Object;I)[Ljava/lang/Object;
    //   310: astore #8
    //   312: aload #9
    //   314: aload #8
    //   316: checkcast [Ljp1;
    //   319: putfield b : [Ljp1;
    //   322: aload #8
    //   324: checkcast [Ljp1;
    //   327: astore #8
    //   329: aload #9
    //   331: getfield e : I
    //   334: istore #6
    //   336: aload #8
    //   338: iload #6
    //   340: aaload
    //   341: astore #11
    //   343: aload #11
    //   345: astore #10
    //   347: aload #11
    //   349: ifnonnull -> 366
    //   352: aload #9
    //   354: invokevirtual c : ()Ljp1;
    //   357: astore #10
    //   359: aload #8
    //   361: iload #6
    //   363: aload #10
    //   365: aastore
    //   366: iload #6
    //   368: iconst_1
    //   369: iadd
    //   370: istore #5
    //   372: iload #5
    //   374: istore_3
    //   375: iload #5
    //   377: aload #8
    //   379: arraylength
    //   380: if_icmplt -> 385
    //   383: iconst_0
    //   384: istore_3
    //   385: aload #10
    //   387: getfield a : Ljava/util/concurrent/atomic/AtomicReference;
    //   390: astore #11
    //   392: aload #11
    //   394: invokevirtual get : ()Ljava/lang/Object;
    //   397: ifnull -> 406
    //   400: iconst_0
    //   401: istore #5
    //   403: goto -> 417
    //   406: aload #11
    //   408: getstatic qz1.f : Lf1;
    //   411: invokevirtual set : (Ljava/lang/Object;)V
    //   414: iconst_1
    //   415: istore #5
    //   417: iload_3
    //   418: istore #6
    //   420: iload #5
    //   422: ifeq -> 336
    //   425: aload #9
    //   427: iload_3
    //   428: putfield e : I
    //   431: aload #9
    //   433: aload #9
    //   435: getfield c : I
    //   438: iconst_1
    //   439: iadd
    //   440: putfield c : I
    //   443: aload_0
    //   444: monitorexit
    //   445: aload_1
    //   446: astore #8
    //   448: aload #9
    //   450: astore_1
    //   451: aload_2
    //   452: getfield c : Los;
    //   455: astore #9
    //   457: aload #9
    //   459: invokevirtual getClass : ()Ljava/lang/Class;
    //   462: pop
    //   463: aload #9
    //   465: getstatic vs2.g : Lvs2;
    //   468: invokeinterface l : (Lns;)Lms;
    //   473: checkcast vj0
    //   476: astore #14
    //   478: aconst_null
    //   479: astore #19
    //   481: aload_1
    //   482: astore #9
    //   484: aload #8
    //   486: astore #13
    //   488: iload #4
    //   490: istore_3
    //   491: aload_2
    //   492: astore #12
    //   494: aload #10
    //   496: astore #8
    //   498: aload #9
    //   500: astore_1
    //   501: getstatic ip1.g : Ljava/util/concurrent/atomic/AtomicReferenceFieldUpdater;
    //   504: aload #9
    //   506: invokevirtual get : (Ljava/lang/Object;)Ljava/lang/Object;
    //   509: astore #20
    //   511: aload #14
    //   513: ifnull -> 552
    //   516: aload #10
    //   518: astore #8
    //   520: aload #9
    //   522: astore_1
    //   523: aload #14
    //   525: invokeinterface a : ()Z
    //   530: ifeq -> 536
    //   533: goto -> 552
    //   536: aload #10
    //   538: astore #8
    //   540: aload #9
    //   542: astore_1
    //   543: aload #14
    //   545: checkcast dk0
    //   548: invokevirtual C : ()Ljava/util/concurrent/CancellationException;
    //   551: athrow
    //   552: aload #19
    //   554: ifnull -> 600
    //   557: aload #10
    //   559: astore #8
    //   561: aload #9
    //   563: astore_1
    //   564: aload #19
    //   566: astore #18
    //   568: aload #12
    //   570: astore #17
    //   572: aload #14
    //   574: astore #16
    //   576: iload_3
    //   577: istore #4
    //   579: aload #10
    //   581: astore #11
    //   583: aload #13
    //   585: astore #15
    //   587: aload #9
    //   589: astore_2
    //   590: aload #19
    //   592: aload #20
    //   594: invokevirtual equals : (Ljava/lang/Object;)Z
    //   597: ifne -> 764
    //   600: aload #10
    //   602: astore #8
    //   604: aload #9
    //   606: astore_1
    //   607: aload #20
    //   609: getstatic dd1.f : Lf1;
    //   612: if_acmpne -> 621
    //   615: aconst_null
    //   616: astore #16
    //   618: goto -> 625
    //   621: aload #20
    //   623: astore #16
    //   625: aload #10
    //   627: astore #8
    //   629: aload #9
    //   631: astore_1
    //   632: aload #12
    //   634: aload #9
    //   636: putfield f : Lip1;
    //   639: aload #10
    //   641: astore #8
    //   643: aload #9
    //   645: astore_1
    //   646: aload #12
    //   648: aload #13
    //   650: putfield g : Lx80;
    //   653: aload #10
    //   655: astore #8
    //   657: aload #9
    //   659: astore_1
    //   660: aload #12
    //   662: aload #10
    //   664: putfield h : Ljp1;
    //   667: aload #10
    //   669: astore #8
    //   671: aload #9
    //   673: astore_1
    //   674: aload #12
    //   676: aload #14
    //   678: putfield i : Lvj0;
    //   681: aload #10
    //   683: astore #8
    //   685: aload #9
    //   687: astore_1
    //   688: aload #12
    //   690: aload #20
    //   692: putfield j : Ljava/lang/Object;
    //   695: aload #10
    //   697: astore #8
    //   699: aload #9
    //   701: astore_1
    //   702: aload #12
    //   704: iconst_2
    //   705: putfield m : I
    //   708: aload #10
    //   710: astore #8
    //   712: aload #9
    //   714: astore_1
    //   715: aload #20
    //   717: astore #11
    //   719: aload #12
    //   721: astore #17
    //   723: aload #13
    //   725: astore #15
    //   727: aload #9
    //   729: astore_2
    //   730: aload #13
    //   732: aload #16
    //   734: aload #12
    //   736: invokeinterface k : (Ljava/lang/Object;Lcs;)Ljava/lang/Object;
    //   741: aload #21
    //   743: if_acmpne -> 749
    //   746: goto -> 1096
    //   749: aload #11
    //   751: astore #18
    //   753: aload #10
    //   755: astore #11
    //   757: iload_3
    //   758: istore #4
    //   760: aload #14
    //   762: astore #16
    //   764: aload #11
    //   766: astore #8
    //   768: aload_2
    //   769: astore_1
    //   770: aload #11
    //   772: getfield a : Ljava/util/concurrent/atomic/AtomicReference;
    //   775: astore #9
    //   777: aload #11
    //   779: astore #8
    //   781: aload_2
    //   782: astore_1
    //   783: getstatic qz1.f : Lf1;
    //   786: astore #10
    //   788: aload #11
    //   790: astore #8
    //   792: aload_2
    //   793: astore_1
    //   794: aload #9
    //   796: aload #10
    //   798: invokevirtual getAndSet : (Ljava/lang/Object;)Ljava/lang/Object;
    //   801: astore #9
    //   803: aload #11
    //   805: astore #8
    //   807: aload_2
    //   808: astore_1
    //   809: aload #9
    //   811: invokevirtual getClass : ()Ljava/lang/Class;
    //   814: pop
    //   815: aload #11
    //   817: astore #8
    //   819: aload_2
    //   820: astore_1
    //   821: aload #9
    //   823: getstatic qz1.g : Lf1;
    //   826: if_acmpne -> 858
    //   829: aload #18
    //   831: astore #19
    //   833: aload #17
    //   835: astore #12
    //   837: aload #16
    //   839: astore #14
    //   841: iload #4
    //   843: istore_3
    //   844: aload #11
    //   846: astore #10
    //   848: aload #15
    //   850: astore #13
    //   852: aload_2
    //   853: astore #9
    //   855: goto -> 494
    //   858: aload #11
    //   860: astore #8
    //   862: aload_2
    //   863: astore_1
    //   864: aload #17
    //   866: aload_2
    //   867: putfield f : Lip1;
    //   870: aload #11
    //   872: astore #8
    //   874: aload_2
    //   875: astore_1
    //   876: aload #17
    //   878: aload #15
    //   880: putfield g : Lx80;
    //   883: aload #11
    //   885: astore #8
    //   887: aload_2
    //   888: astore_1
    //   889: aload #17
    //   891: aload #11
    //   893: putfield h : Ljp1;
    //   896: aload #11
    //   898: astore #8
    //   900: aload_2
    //   901: astore_1
    //   902: aload #17
    //   904: aload #16
    //   906: putfield i : Lvj0;
    //   909: aload #11
    //   911: astore #8
    //   913: aload_2
    //   914: astore_1
    //   915: aload #17
    //   917: aload #18
    //   919: putfield j : Ljava/lang/Object;
    //   922: aload #11
    //   924: astore #8
    //   926: aload_2
    //   927: astore_1
    //   928: aload #17
    //   930: iload #4
    //   932: putfield m : I
    //   935: aload #11
    //   937: astore #8
    //   939: aload_2
    //   940: astore_1
    //   941: getstatic l02.a : Ll02;
    //   944: astore #9
    //   946: aload #11
    //   948: astore #8
    //   950: aload_2
    //   951: astore_1
    //   952: new ni
    //   955: astore #13
    //   957: aload #11
    //   959: astore #8
    //   961: aload_2
    //   962: astore_1
    //   963: aload #13
    //   965: iconst_1
    //   966: aload #17
    //   968: invokestatic N : (Lcs;)Lcs;
    //   971: invokespecial <init> : (ILcs;)V
    //   974: aload #11
    //   976: astore #8
    //   978: aload_2
    //   979: astore_1
    //   980: aload #13
    //   982: invokevirtual x : ()V
    //   985: aload #11
    //   987: astore #8
    //   989: aload_2
    //   990: astore_1
    //   991: aload #11
    //   993: getfield a : Ljava/util/concurrent/atomic/AtomicReference;
    //   996: astore #12
    //   998: aload #11
    //   1000: astore #8
    //   1002: aload_2
    //   1003: astore_1
    //   1004: aload #12
    //   1006: aload #10
    //   1008: aload #13
    //   1010: invokevirtual compareAndSet : (Ljava/lang/Object;Ljava/lang/Object;)Z
    //   1013: ifeq -> 1019
    //   1016: goto -> 1048
    //   1019: aload #11
    //   1021: astore #8
    //   1023: aload_2
    //   1024: astore_1
    //   1025: aload #12
    //   1027: invokevirtual get : ()Ljava/lang/Object;
    //   1030: aload #10
    //   1032: if_acmpeq -> 1111
    //   1035: aload #11
    //   1037: astore #8
    //   1039: aload_2
    //   1040: astore_1
    //   1041: aload #13
    //   1043: aload #9
    //   1045: invokevirtual f : (Ljava/lang/Object;)V
    //   1048: aload #11
    //   1050: astore #8
    //   1052: aload_2
    //   1053: astore_1
    //   1054: aload #13
    //   1056: invokevirtual v : ()Ljava/lang/Object;
    //   1059: astore #10
    //   1061: aload #9
    //   1063: astore_1
    //   1064: aload #10
    //   1066: aload #21
    //   1068: if_acmpne -> 1074
    //   1071: aload #10
    //   1073: astore_1
    //   1074: aload #17
    //   1076: astore #12
    //   1078: aload #16
    //   1080: astore #14
    //   1082: aload #11
    //   1084: astore #10
    //   1086: aload #15
    //   1088: astore #13
    //   1090: aload_1
    //   1091: aload #21
    //   1093: if_acmpne -> 1099
    //   1096: aload #21
    //   1098: areturn
    //   1099: iconst_3
    //   1100: istore_3
    //   1101: aload #18
    //   1103: astore #19
    //   1105: aload_2
    //   1106: astore #9
    //   1108: goto -> 494
    //   1111: goto -> 998
    //   1114: astore_2
    //   1115: aload #10
    //   1117: astore #8
    //   1119: aload_1
    //   1120: monitorenter
    //   1121: aload_1
    //   1122: getfield c : I
    //   1125: iconst_1
    //   1126: isub
    //   1127: istore_3
    //   1128: aload_1
    //   1129: iload_3
    //   1130: putfield c : I
    //   1133: iload_3
    //   1134: ifne -> 1149
    //   1137: aload_1
    //   1138: iconst_0
    //   1139: putfield e : I
    //   1142: goto -> 1149
    //   1145: astore_2
    //   1146: goto -> 1211
    //   1149: aload #8
    //   1151: invokevirtual getClass : ()Ljava/lang/Class;
    //   1154: pop
    //   1155: aload #8
    //   1157: getfield a : Ljava/util/concurrent/atomic/AtomicReference;
    //   1160: aconst_null
    //   1161: invokevirtual set : (Ljava/lang/Object;)V
    //   1164: getstatic qv.a : [Lcs;
    //   1167: astore #8
    //   1169: aload_1
    //   1170: monitorexit
    //   1171: aload #8
    //   1173: arraylength
    //   1174: istore #4
    //   1176: iload #7
    //   1178: istore_3
    //   1179: iload_3
    //   1180: iload #4
    //   1182: if_icmpge -> 1209
    //   1185: aload #8
    //   1187: iload_3
    //   1188: aaload
    //   1189: astore_1
    //   1190: aload_1
    //   1191: ifnull -> 1203
    //   1194: aload_1
    //   1195: getstatic l02.a : Ll02;
    //   1198: invokeinterface f : (Ljava/lang/Object;)V
    //   1203: iinc #3, 1
    //   1206: goto -> 1179
    //   1209: aload_2
    //   1210: athrow
    //   1211: aload_1
    //   1212: monitorexit
    //   1213: aload_2
    //   1214: athrow
    //   1215: aload_0
    //   1216: monitorexit
    //   1217: aload_1
    //   1218: athrow
    // Exception table:
    //   from	to	target	type
    //   133	138	147	finally
    //   195	200	147	finally
    //   229	234	237	finally
    //   252	259	281	finally
    //   264	278	281	finally
    //   289	329	281	finally
    //   329	336	281	finally
    //   352	359	281	finally
    //   375	383	281	finally
    //   385	400	281	finally
    //   406	414	281	finally
    //   425	443	281	finally
    //   451	478	1114	finally
    //   501	511	147	finally
    //   523	533	147	finally
    //   543	552	147	finally
    //   590	600	147	finally
    //   607	615	147	finally
    //   632	639	147	finally
    //   646	653	147	finally
    //   660	667	147	finally
    //   674	681	147	finally
    //   688	695	147	finally
    //   702	708	147	finally
    //   730	746	147	finally
    //   770	777	147	finally
    //   783	788	147	finally
    //   794	803	147	finally
    //   809	815	147	finally
    //   821	829	147	finally
    //   864	870	147	finally
    //   876	883	147	finally
    //   889	896	147	finally
    //   902	909	147	finally
    //   915	922	147	finally
    //   928	935	147	finally
    //   941	946	147	finally
    //   952	957	147	finally
    //   963	974	147	finally
    //   980	985	147	finally
    //   991	998	147	finally
    //   1004	1016	147	finally
    //   1025	1035	147	finally
    //   1041	1048	147	finally
    //   1054	1061	147	finally
    //   1121	1133	1145	finally
    //   1137	1142	1145	finally
    //   1149	1169	1145	finally
  }
  
  public final w80 b(os paramos, int paramInt, hh paramhh) {
    return (w80)(((((paramInt >= 0 && paramInt < 2) || paramInt == -2) && paramhh == hh.c) || ((paramInt == 0 || paramInt == -3) && paramhh == hh.b)) ? this : new gk(this, paramos, paramInt, paramhh));
  }
  
  public final jp1 c() {
    return new jp1();
  }
  
  public final jp1[] d() {
    return new jp1[2];
  }
  
  public final boolean e(Object paramObject1, Object paramObject2) {
    f1 f1 = dd1.f;
    Object object = paramObject1;
    if (paramObject1 == null)
      object = f1; 
    paramObject1 = paramObject2;
    if (paramObject2 == null)
      paramObject1 = f1; 
    return g(object, paramObject1);
  }
  
  public final Object f() {
    f1 f1 = dd1.f;
    g.getClass();
    Object object2 = oi.a.getObjectVolatile(this, h);
    Object object1 = object2;
    if (object2 == f1)
      object1 = null; 
    return object1;
  }
  
  public final boolean g(Object paramObject1, Object paramObject2) {
    f1 f1;
    AtomicReferenceFieldUpdater<ip1, Object> atomicReferenceFieldUpdater;
    /* monitor enter ThisExpression{ObjectType{ip1}} */
    try {
      atomicReferenceFieldUpdater = g;
      f1 = (f1)atomicReferenceFieldUpdater.get(this);
      if (paramObject1 != null) {
        boolean bool1 = ui0.c(f1, paramObject1);
        if (!bool1) {
          /* monitor exit ThisExpression{ObjectType{ip1}} */
          return false;
        } 
      } 
    } finally {}
    boolean bool = ui0.c(f1, paramObject2);
    if (bool) {
      /* monitor exit ThisExpression{ObjectType{ip1}} */
      return true;
    } 
    atomicReferenceFieldUpdater.set(this, paramObject2);
    int i = this.f;
    if ((i & 0x1) == 0) {
      this.f = ++i;
      paramObject1 = this.b;
      /* monitor exit ThisExpression{ObjectType{ip1}} */
      while (true) {
        int j;
        paramObject1 = paramObject1;
        if (paramObject1 != null) {
          int k = paramObject1.length;
          for (j = 0; j < k; j++) {
            paramObject2 = paramObject1[j];
            if (paramObject2 != null) {
              AtomicReference<AtomicReferenceFieldUpdater<ip1, Object>> atomicReference = ((jp1)paramObject2).a;
              label59: while (true) {
                atomicReferenceFieldUpdater = atomicReference.get();
                if (atomicReferenceFieldUpdater == null)
                  break; 
                f1 = qz1.g;
                if (atomicReferenceFieldUpdater == f1)
                  break; 
                paramObject2 = qz1.f;
                if (atomicReferenceFieldUpdater == paramObject2) {
                  while (!atomicReference.compareAndSet(atomicReferenceFieldUpdater, f1)) {
                    if (atomicReference.get() != atomicReferenceFieldUpdater)
                      continue label59; 
                  } 
                  break;
                } 
                while (true) {
                  if (atomicReference.compareAndSet(atomicReferenceFieldUpdater, paramObject2)) {
                    ((ni)atomicReferenceFieldUpdater).f(l02.a);
                    break;
                  } 
                  if (atomicReference.get() != atomicReferenceFieldUpdater)
                    continue label59; 
                } 
                break;
              } 
            } 
          } 
        } 
        /* monitor enter ThisExpression{ObjectType{ip1}} */
        try {
          j = this.f;
          if (j == i) {
            this.f = i + 1;
            /* monitor exit ThisExpression{ObjectType{ip1}} */
            return true;
          } 
        } finally {}
        paramObject1 = this.b;
        /* monitor exit ThisExpression{ObjectType{ip1}} */
        i = j;
      } 
    } 
    this.f = i + 2;
    /* monitor exit ThisExpression{ObjectType{ip1}} */
    return true;
  }
  
  public final Object k(Object paramObject, cs paramcs) {
    Object object = paramObject;
    if (paramObject == null)
      object = dd1.f; 
    g(null, object);
    return l02.a;
  }
}


/* Location:              C:\Users\Kevin\Downloads\dex-tools-v2.4\dex-tools-v2.4\musicolet-dex2jar.jar!\ip1.class
 * Java compiler version: 6 (50.0)
 * JD-Core Version:       1.1.3
 */