import android.animation.Animator;
import android.animation.TimeInterpolator;
import android.util.SparseArray;
import android.util.SparseIntArray;
import android.view.View;
import android.view.ViewGroup;
import android.view.WindowId;
import android.widget.ListView;
import android.widget.TextView;
import java.util.ArrayList;
import java.util.Iterator;
import java.util.WeakHashMap;

public abstract class kw1 implements Cloneable {
  public static final Animator[] B = new Animator[0];
  
  public static final int[] C = new int[] { 2, 1, 3, 4 };
  
  public static final fb0 D = (fb0)new Object();
  
  public static final ThreadLocal E = new ThreadLocal();
  
  public long A;
  
  public final String b = getClass().getName();
  
  public long c = -1L;
  
  public long e = -1L;
  
  public TimeInterpolator f = null;
  
  public final ArrayList g = new ArrayList();
  
  public final ArrayList h = new ArrayList();
  
  public ArrayList i = null;
  
  public n2 j = new n2(14);
  
  public n2 k = new n2(14);
  
  public qw1 l = null;
  
  public final int[] m = C;
  
  public ArrayList n;
  
  public ArrayList o;
  
  public jw1[] p;
  
  public final ArrayList q = new ArrayList();
  
  public Animator[] r = B;
  
  public int s = 0;
  
  public boolean t = false;
  
  public boolean u = false;
  
  public kw1 v = null;
  
  public ArrayList w = null;
  
  public ArrayList x = new ArrayList();
  
  public fb0 y = D;
  
  public long z;
  
  public static void b(n2 paramn2, View paramView, tw1 paramtw1) {
    b9 b92 = (b9)paramn2.c;
    b9 b91 = (b9)paramn2.g;
    SparseArray sparseArray = (SparseArray)paramn2.e;
    sp0 sp0 = (sp0)paramn2.f;
    b92.put(paramView, paramtw1);
    int i = paramView.getId();
    if (i >= 0)
      if (sparseArray.indexOfKey(i) >= 0) {
        sparseArray.put(i, null);
      } else {
        sparseArray.put(i, paramView);
      }  
    WeakHashMap weakHashMap = v22.a;
    String str = paramView.getTransitionName();
    if (str != null)
      if (b91.containsKey(str)) {
        b91.put(str, null);
      } else {
        b91.put(str, paramView);
      }  
    if (paramView.getParent() instanceof ListView) {
      ListView listView = (ListView)paramView.getParent();
      if (listView.getAdapter().hasStableIds()) {
        long l = listView.getItemIdAtPosition(listView.getPositionForView(paramView));
        if (sp0.b) {
          int k = sp0.f;
          long[] arrayOfLong = sp0.c;
          Object[] arrayOfObject = sp0.e;
          i = 0;
          int j;
          for (j = 0; i < k; j = m) {
            Object object = arrayOfObject[i];
            int m = j;
            if (object != ws2.g) {
              if (i != j) {
                arrayOfLong[j] = arrayOfLong[i];
                arrayOfObject[j] = object;
                arrayOfObject[i] = null;
              } 
              m = j + 1;
            } 
            i++;
          } 
          sp0.b = false;
          sp0.f = j;
        } 
        if (ws2.g(sp0.c, sp0.f, l) >= 0) {
          paramView = (View)sp0.b(l);
          if (paramView != null) {
            paramView.setHasTransientState(false);
            sp0.d(l, null);
            return;
          } 
        } else {
          paramView.setHasTransientState(true);
          sp0.d(l, paramView);
        } 
      } 
    } 
  }
  
  public static b9 q() {
    ThreadLocal<b9> threadLocal = E;
    b9 b9 = threadLocal.get();
    zm1 zm1 = b9;
    if (b9 == null) {
      zm1 = new zm1(0);
      threadLocal.set(zm1);
    } 
    return (b9)zm1;
  }
  
  public static boolean w(tw1 paramtw11, tw1 paramtw12, String paramString) {
    paramtw11 = (tw1)paramtw11.a.get(paramString);
    paramtw12 = (tw1)paramtw12.a.get(paramString);
    return (paramtw11 == null && paramtw12 == null) ? false : ((paramtw11 == null || paramtw12 == null) ? true : (paramtw11.equals(paramtw12) ^ true));
  }
  
  public kw1 A(jw1 paramjw1) {
    ArrayList arrayList = this.w;
    if (arrayList != null) {
      if (!arrayList.remove(paramjw1)) {
        kw1 kw11 = this.v;
        if (kw11 != null)
          kw11.A(paramjw1); 
      } 
      if (this.w.size() == 0)
        this.w = null; 
    } 
    return this;
  }
  
  public void B(View paramView) {
    if (this.t) {
      if (!this.u) {
        ArrayList arrayList = this.q;
        int i = arrayList.size();
        Animator[] arrayOfAnimator = (Animator[])arrayList.toArray((Object[])this.r);
        this.r = B;
        while (--i >= 0) {
          Animator animator = arrayOfAnimator[i];
          arrayOfAnimator[i] = null;
          animator.resume();
          i--;
        } 
        this.r = arrayOfAnimator;
        x(this, k91.h, false);
      } 
      this.t = false;
    } 
  }
  
  public void C() {
    K();
    b9 b9 = q();
    ArrayList<Object> arrayList = this.x;
    int j = arrayList.size();
    int i = 0;
    while (i < j) {
      Animator animator1 = (Animator)arrayList.get(i);
      int k = i + 1;
      Animator animator2 = animator1;
      i = k;
      if (b9.containsKey(animator2)) {
        K();
        i = k;
        if (animator2 != null) {
          animator2.addListener((Animator.AnimatorListener)new ew1(this, b9));
          long l = this.e;
          if (l >= 0L)
            animator2.setDuration(l); 
          l = this.c;
          if (l >= 0L)
            animator2.setStartDelay(animator2.getStartDelay() + l); 
          TimeInterpolator timeInterpolator = this.f;
          if (timeInterpolator != null)
            animator2.setInterpolator(timeInterpolator); 
          animator2.addListener((Animator.AnimatorListener)new j1(12, this));
          animator2.start();
          i = k;
        } 
      } 
    } 
    this.x.clear();
    m();
  }
  
  public void D(long paramLong1, long paramLong2) {
    boolean bool;
    long l = this.z;
    int i = 0;
    if (paramLong1 < paramLong2) {
      bool = true;
    } else {
      bool = false;
    } 
    int j = paramLong2 cmp 0L;
    if ((j < 0 && paramLong1 >= 0L) || (paramLong2 > l && paramLong1 <= l)) {
      this.u = false;
      x(this, k91.c, bool);
    } 
    ArrayList arrayList = this.q;
    int k = arrayList.size();
    Animator[] arrayOfAnimator = (Animator[])arrayList.toArray((Object[])this.r);
    this.r = B;
    while (i < k) {
      Animator animator = arrayOfAnimator[i];
      arrayOfAnimator[i] = null;
      long l1 = gw1.a(animator);
      gw1.b(animator, Math.min(Math.max(0L, paramLong1), l1));
      i++;
    } 
    this.r = arrayOfAnimator;
    i = paramLong1 cmp l;
    if ((i > 0 && paramLong2 <= l) || (paramLong1 < 0L && j >= 0)) {
      if (i > 0)
        this.u = true; 
      x(this, k91.e, bool);
    } 
  }
  
  public void E(long paramLong) {
    this.e = paramLong;
  }
  
  public void F(z51 paramz51) {}
  
  public void G(TimeInterpolator paramTimeInterpolator) {
    this.f = paramTimeInterpolator;
  }
  
  public void H(fb0 paramfb0) {
    if (paramfb0 == null) {
      this.y = D;
      return;
    } 
    this.y = paramfb0;
  }
  
  public void I() {}
  
  public void J(long paramLong) {
    this.c = paramLong;
  }
  
  public final void K() {
    if (this.s == 0) {
      x(this, k91.c, false);
      this.u = false;
    } 
    this.s++;
  }
  
  public String L(String paramString) {
    StringBuilder stringBuilder = new StringBuilder(paramString);
    stringBuilder.append(getClass().getSimpleName());
    stringBuilder.append("@");
    stringBuilder.append(Integer.toHexString(hashCode()));
    stringBuilder.append(": ");
    if (this.e != -1L) {
      stringBuilder.append("dur(");
      stringBuilder.append(this.e);
      stringBuilder.append(") ");
    } 
    if (this.c != -1L) {
      stringBuilder.append("dly(");
      stringBuilder.append(this.c);
      stringBuilder.append(") ");
    } 
    if (this.f != null) {
      stringBuilder.append("interp(");
      stringBuilder.append(this.f);
      stringBuilder.append(") ");
    } 
    ArrayList arrayList1 = this.g;
    int i = arrayList1.size();
    ArrayList arrayList2 = this.h;
    if (i > 0 || arrayList2.size() > 0) {
      stringBuilder.append("tgts(");
      i = arrayList1.size();
      boolean bool = false;
      if (i > 0)
        for (i = 0; i < arrayList1.size(); i++) {
          if (i > 0)
            stringBuilder.append(", "); 
          stringBuilder.append(arrayList1.get(i));
        }  
      if (arrayList2.size() > 0)
        for (i = bool; i < arrayList2.size(); i++) {
          if (i > 0)
            stringBuilder.append(", "); 
          stringBuilder.append(arrayList2.get(i));
        }  
      stringBuilder.append(")");
    } 
    return stringBuilder.toString();
  }
  
  public void a(jw1 paramjw1) {
    if (this.w == null)
      this.w = new ArrayList(); 
    this.w.add(paramjw1);
  }
  
  public void c() {
    ArrayList arrayList = this.q;
    int i = arrayList.size();
    Animator[] arrayOfAnimator = (Animator[])arrayList.toArray((Object[])this.r);
    this.r = B;
    while (--i >= 0) {
      Animator animator = arrayOfAnimator[i];
      arrayOfAnimator[i] = null;
      animator.cancel();
      i--;
    } 
    this.r = arrayOfAnimator;
    x(this, k91.f, false);
  }
  
  public abstract void d(tw1 paramtw1);
  
  public final void e(View paramView, boolean paramBoolean) {
    if (paramView != null) {
      paramView.getId();
      ArrayList arrayList = this.i;
      byte b = 0;
      if (arrayList != null) {
        int i = arrayList.size();
        for (byte b1 = 0; b1 < i; b1++) {
          if (((Class)this.i.get(b1)).isInstance(paramView))
            // Byte code: goto -> 189 
        } 
      } 
      if (paramView.getParent() instanceof ViewGroup) {
        tw1 tw1 = new tw1(paramView);
        if (paramBoolean) {
          g(tw1);
        } else {
          d(tw1);
        } 
        tw1.c.add(this);
        f(tw1);
        if (paramBoolean) {
          b(this.j, paramView, tw1);
        } else {
          b(this.k, paramView, tw1);
        } 
      } 
      if (paramView instanceof ViewGroup) {
        ViewGroup viewGroup = (ViewGroup)paramView;
        for (byte b1 = b; b1 < viewGroup.getChildCount(); b1++)
          e(viewGroup.getChildAt(b1), paramBoolean); 
      } 
    } 
  }
  
  public void f(tw1 paramtw1) {}
  
  public abstract void g(tw1 paramtw1);
  
  public final void h(ViewGroup paramViewGroup, boolean paramBoolean) {
    tw1 tw1;
    i(paramBoolean);
    ArrayList<Integer> arrayList1 = this.g;
    int i = arrayList1.size();
    ArrayList<View> arrayList = this.h;
    if (i > 0 || arrayList.size() > 0) {
      byte b1;
      byte b2 = 0;
      i = 0;
      while (true) {
        b1 = b2;
        if (i < arrayList1.size()) {
          View view = paramViewGroup.findViewById(((Integer)arrayList1.get(i)).intValue());
          if (view != null) {
            tw1 tw11 = new tw1(view);
            if (paramBoolean) {
              g(tw11);
            } else {
              d(tw11);
            } 
            tw11.c.add(this);
            f(tw11);
            if (paramBoolean) {
              b(this.j, view, tw11);
            } else {
              b(this.k, view, tw11);
            } 
          } 
          i++;
          continue;
        } 
        break;
      } 
      while (b1 < arrayList.size()) {
        View view = arrayList.get(b1);
        tw1 = new tw1(view);
        if (paramBoolean) {
          g(tw1);
        } else {
          d(tw1);
        } 
        tw1.c.add(this);
        f(tw1);
        if (paramBoolean) {
          b(this.j, view, tw1);
        } else {
          b(this.k, view, tw1);
        } 
        b1++;
      } 
      return;
    } 
    e((View)tw1, paramBoolean);
  }
  
  public final void i(boolean paramBoolean) {
    if (paramBoolean) {
      ((b9)this.j.c).clear();
      ((SparseArray)this.j.e).clear();
      ((sp0)this.j.f).a();
      return;
    } 
    ((b9)this.k.c).clear();
    ((SparseArray)this.k.e).clear();
    ((sp0)this.k.f).a();
  }
  
  public kw1 j() {
    try {
      kw1 kw11 = (kw1)super.clone();
      ArrayList arrayList = new ArrayList();
      this();
      kw11.x = arrayList;
      n2 n21 = new n2();
      this(14);
      kw11.j = n21;
      n21 = new n2();
      this(14);
      kw11.k = n21;
      kw11.n = null;
      kw11.o = null;
      kw11.v = this;
      kw11.w = null;
      return kw11;
    } catch (CloneNotSupportedException cloneNotSupportedException) {
      k91.n(cloneNotSupportedException);
      return null;
    } 
  }
  
  public Animator k(ViewGroup paramViewGroup, tw1 paramtw11, tw1 paramtw12) {
    return null;
  }
  
  public void l(ViewGroup paramViewGroup, n2 paramn21, n2 paramn22, ArrayList<tw1> paramArrayList1, ArrayList<tw1> paramArrayList2) {
    b9 b9 = q();
    SparseIntArray sparseIntArray = new SparseIntArray();
    int j = paramArrayList1.size();
    p().getClass();
    int i;
    for (i = 0; i < j; i = SYNTHETIC_LOCAL_VARIABLE_7 + 1) {
      tw1 tw13 = paramArrayList1.get(i);
      tw1 tw11 = paramArrayList2.get(i);
      tw1 tw12 = tw13;
      if (tw13 != null) {
        tw12 = tw13;
        if (!tw13.c.contains(this))
          tw12 = null; 
      } 
      tw13 = tw11;
      if (tw11 != null) {
        tw13 = tw11;
        if (!tw11.c.contains(this))
          tw13 = null; 
      } 
      if ((tw12 != null || tw13 != null) && (tw12 == null || tw13 == null || u(tw12, tw13))) {
        Animator animator = k(paramViewGroup, tw12, tw13);
        if (animator != null) {
          tw1 tw14;
          Animator animator1;
          tw1 tw15;
          View view;
          String str = this.b;
          if (tw13 != null) {
            view = tw13.b;
            String[] arrayOfString = r();
            if (arrayOfString != null && arrayOfString.length > 0) {
              tw1 tw1 = new tw1(view);
              tw12 = (tw1)((b9)paramn22.c).get(view);
              int n = i;
              if (tw12 != null) {
                byte b = 0;
                while (true) {
                  n = i;
                  if (b < arrayOfString.length) {
                    String str1 = arrayOfString[b];
                    Object object = tw12.a.get(str1);
                    tw1.a.put(str1, object);
                    b++;
                    continue;
                  } 
                  break;
                } 
              } 
              i = n;
              int i1 = b9.e;
              n = 0;
              while (true) {
                if (n < i1) {
                  fw1 fw1 = (fw1)b9.get(b9.f(n));
                  if (fw1.c != null && fw1.a == view && fw1.b.equals(str) && fw1.c.equals(tw1)) {
                    animator = null;
                    tw15 = tw1;
                    break;
                  } 
                  n++;
                  continue;
                } 
                tw12 = tw1;
                break;
              } 
            } else {
              tw12 = null;
            } 
            Animator animator2 = animator;
            tw14 = tw12;
            animator1 = animator2;
          } else {
            view = ((tw1)animator1).b;
            tw1 tw1 = null;
            tw15 = tw14;
            tw14 = tw1;
          } 
          int m = i;
          if (tw15 != null) {
            WindowId windowId = paramViewGroup.getWindowId();
            Object object = new Object();
            ((fw1)object).a = view;
            ((fw1)object).b = str;
            ((fw1)object).c = tw14;
            ((fw1)object).d = windowId;
            ((fw1)object).e = this;
            ((fw1)object).f = (Animator)tw15;
            b9.put(tw15, object);
            this.x.add(tw15);
            m = i;
          } 
          continue;
        } 
      } 
      int k = i;
      continue;
    } 
    if (sparseIntArray.size() != 0)
      for (i = 0; i < sparseIntArray.size(); i++) {
        int k = sparseIntArray.keyAt(i);
        fw1 fw1 = (fw1)b9.get(this.x.get(k));
        long l2 = sparseIntArray.valueAt(i);
        long l1 = fw1.f.getStartDelay();
        fw1.f.setStartDelay(l1 + l2 - Long.MAX_VALUE);
      }  
  }
  
  public final void m() {
    int i = this.s - 1;
    this.s = i;
    if (i == 0) {
      x(this, k91.e, false);
      for (i = 0; i < ((sp0)this.j.f).e(); i++) {
        View view = (View)((sp0)this.j.f).f(i);
        if (view != null)
          view.setHasTransientState(false); 
      } 
      for (i = 0; i < ((sp0)this.k.f).e(); i++) {
        View view = (View)((sp0)this.k.f).f(i);
        if (view != null)
          view.setHasTransientState(false); 
      } 
      this.u = true;
    } 
  }
  
  public void n() {
    ArrayList<Class<TextView>> arrayList2 = this.i;
    ArrayList<Class<TextView>> arrayList1 = arrayList2;
    if (arrayList2 == null)
      arrayList1 = new ArrayList(); 
    if (!arrayList1.contains(TextView.class))
      arrayList1.add(TextView.class); 
    this.i = arrayList1;
  }
  
  public final tw1 o(View paramView, boolean paramBoolean) {
    // Byte code:
    //   0: aload_0
    //   1: getfield l : Lqw1;
    //   4: astore #5
    //   6: aload #5
    //   8: ifnull -> 19
    //   11: aload #5
    //   13: aload_1
    //   14: iload_2
    //   15: invokevirtual o : (Landroid/view/View;Z)Ltw1;
    //   18: areturn
    //   19: iload_2
    //   20: ifeq -> 32
    //   23: aload_0
    //   24: getfield n : Ljava/util/ArrayList;
    //   27: astore #5
    //   29: goto -> 38
    //   32: aload_0
    //   33: getfield o : Ljava/util/ArrayList;
    //   36: astore #5
    //   38: aload #5
    //   40: ifnonnull -> 46
    //   43: goto -> 130
    //   46: aload #5
    //   48: invokevirtual size : ()I
    //   51: istore #4
    //   53: iconst_0
    //   54: istore_3
    //   55: iload_3
    //   56: iload #4
    //   58: if_icmpge -> 98
    //   61: aload #5
    //   63: iload_3
    //   64: invokevirtual get : (I)Ljava/lang/Object;
    //   67: checkcast tw1
    //   70: astore #6
    //   72: aload #6
    //   74: ifnonnull -> 80
    //   77: goto -> 130
    //   80: aload #6
    //   82: getfield b : Landroid/view/View;
    //   85: aload_1
    //   86: if_acmpne -> 92
    //   89: goto -> 100
    //   92: iinc #3, 1
    //   95: goto -> 55
    //   98: iconst_m1
    //   99: istore_3
    //   100: iload_3
    //   101: iflt -> 130
    //   104: iload_2
    //   105: ifeq -> 116
    //   108: aload_0
    //   109: getfield o : Ljava/util/ArrayList;
    //   112: astore_1
    //   113: goto -> 121
    //   116: aload_0
    //   117: getfield n : Ljava/util/ArrayList;
    //   120: astore_1
    //   121: aload_1
    //   122: iload_3
    //   123: invokevirtual get : (I)Ljava/lang/Object;
    //   126: checkcast tw1
    //   129: areturn
    //   130: aconst_null
    //   131: areturn
  }
  
  public final kw1 p() {
    qw1 qw11 = this.l;
    kw1 kw11 = this;
    if (qw11 != null)
      kw11 = qw11.p(); 
    return kw11;
  }
  
  public String[] r() {
    return null;
  }
  
  public final tw1 s(View paramView, boolean paramBoolean) {
    n2 n21;
    qw1 qw11 = this.l;
    if (qw11 != null)
      return qw11.s(paramView, paramBoolean); 
    if (paramBoolean) {
      n21 = this.j;
    } else {
      n21 = this.k;
    } 
    return (tw1)((b9)n21.c).get(paramView);
  }
  
  public boolean t() {
    return this.q.isEmpty() ^ true;
  }
  
  public final String toString() {
    return L("");
  }
  
  public boolean u(tw1 paramtw11, tw1 paramtw12) {
    if (paramtw11 != null && paramtw12 != null) {
      String[] arrayOfString = r();
      if (arrayOfString != null) {
        int i = arrayOfString.length;
        byte b = 0;
        while (b < i) {
          if (!w(paramtw11, paramtw12, arrayOfString[b])) {
            b++;
            continue;
          } 
          return true;
        } 
      } else {
        Iterator<String> iterator = paramtw11.a.keySet().iterator();
        while (iterator.hasNext()) {
          if (w(paramtw11, paramtw12, iterator.next()))
            return true; 
        } 
      } 
    } 
    return false;
  }
  
  public final boolean v(View paramView) {
    int j = paramView.getId();
    ArrayList arrayList1 = this.i;
    if (arrayList1 != null) {
      int k = arrayList1.size();
      for (byte b = 0; b < k; b++) {
        if (((Class)this.i.get(b)).isInstance(paramView))
          return false; 
      } 
    } 
    ArrayList arrayList2 = this.g;
    int i = arrayList2.size();
    arrayList1 = this.h;
    return (i == 0 && arrayList1.size() == 0) ? true : ((arrayList2.contains(Integer.valueOf(j)) || arrayList1.contains(paramView)));
  }
  
  public final void x(kw1 paramkw1, k91 paramk91, boolean paramBoolean) {
    kw1 kw11 = this.v;
    if (kw11 != null)
      kw11.x(paramkw1, paramk91, paramBoolean); 
    ArrayList arrayList = this.w;
    if (arrayList != null && !arrayList.isEmpty()) {
      int i = this.w.size();
      jw1[] arrayOfJw12 = this.p;
      jw1[] arrayOfJw11 = arrayOfJw12;
      if (arrayOfJw12 == null)
        arrayOfJw11 = new jw1[i]; 
      this.p = null;
      arrayOfJw12 = (jw1[])this.w.toArray((Object[])arrayOfJw11);
      for (byte b = 0; b < i; b++) {
        jw1 jw11 = arrayOfJw12[b];
        switch (paramk91.b) {
          default:
            jw11.c();
            break;
          case 17:
            jw11.b();
            break;
          case 16:
            jw11.f(paramkw1);
            break;
          case 15:
            jw11.d(paramkw1);
            break;
          case 14:
            jw11.e(paramkw1);
            break;
        } 
        arrayOfJw12[b] = null;
      } 
      this.p = arrayOfJw12;
    } 
  }
  
  public void y(View paramView) {
    if (!this.u) {
      ArrayList arrayList = this.q;
      int i = arrayList.size();
      Animator[] arrayOfAnimator = (Animator[])arrayList.toArray((Object[])this.r);
      this.r = B;
      while (--i >= 0) {
        Animator animator = arrayOfAnimator[i];
        arrayOfAnimator[i] = null;
        animator.pause();
        i--;
      } 
      this.r = arrayOfAnimator;
      x(this, k91.g, false);
      this.t = true;
    } 
  }
  
  public void z() {
    b9 b9 = q();
    this.z = 0L;
    byte b = 0;
    while (true) {
      Animator animator;
      int i = this.x.size();
      ArrayList<Animator> arrayList = this.x;
      if (b < i) {
        animator = arrayList.get(b);
        fw1 fw1 = (fw1)b9.get(animator);
        if (animator != null && fw1 != null) {
          Animator animator1 = fw1.f;
          long l = this.e;
          if (l >= 0L)
            animator1.setDuration(l); 
          l = this.c;
          if (l >= 0L)
            animator1.setStartDelay(animator1.getStartDelay() + l); 
          TimeInterpolator timeInterpolator = this.f;
          if (timeInterpolator != null)
            animator1.setInterpolator(timeInterpolator); 
          this.q.add(animator);
          this.z = Math.max(this.z, gw1.a(animator));
        } 
        b++;
        continue;
      } 
      animator.clear();
      return;
    } 
  }
}


/* Location:              C:\Users\Kevin\Downloads\dex-tools-v2.4\dex-tools-v2.4\musicolet-dex2jar.jar!\kw1.class
 * Java compiler version: 6 (50.0)
 * JD-Core Version:       1.1.3
 */