import java.sql.Date;
import java.text.SimpleDateFormat;

public final class no1 extends jy1 {
  public static final a b = new a();
  
  public final SimpleDateFormat a = new SimpleDateFormat("MMM d, yyyy");
  
  public no1() {}
  
  public final Object b(tk0 paramtk0) {
    // Byte code:
    //   0: aload_1
    //   1: invokevirtual C : ()I
    //   4: bipush #9
    //   6: if_icmpne -> 15
    //   9: aload_1
    //   10: invokevirtual y : ()V
    //   13: aconst_null
    //   14: areturn
    //   15: aload_1
    //   16: invokevirtual A : ()Ljava/lang/String;
    //   19: astore_3
    //   20: aload_0
    //   21: monitorenter
    //   22: aload_0
    //   23: getfield a : Ljava/text/SimpleDateFormat;
    //   26: invokevirtual getTimeZone : ()Ljava/util/TimeZone;
    //   29: astore_2
    //   30: aload_0
    //   31: getfield a : Ljava/text/SimpleDateFormat;
    //   34: aload_3
    //   35: invokevirtual parse : (Ljava/lang/String;)Ljava/util/Date;
    //   38: astore #4
    //   40: new java/sql/Date
    //   43: astore #5
    //   45: aload #5
    //   47: aload #4
    //   49: invokevirtual getTime : ()J
    //   52: invokespecial <init> : (J)V
    //   55: aload_0
    //   56: getfield a : Ljava/text/SimpleDateFormat;
    //   59: aload_2
    //   60: invokevirtual setTimeZone : (Ljava/util/TimeZone;)V
    //   63: aload_0
    //   64: monitorexit
    //   65: aload #5
    //   67: areturn
    //   68: astore_1
    //   69: goto -> 146
    //   72: astore_1
    //   73: goto -> 136
    //   76: astore #6
    //   78: new pk0
    //   81: astore #5
    //   83: new java/lang/StringBuilder
    //   86: astore #4
    //   88: aload #4
    //   90: ldc 'Failed parsing ''
    //   92: invokespecial <init> : (Ljava/lang/String;)V
    //   95: aload #4
    //   97: aload_3
    //   98: invokevirtual append : (Ljava/lang/String;)Ljava/lang/StringBuilder;
    //   101: pop
    //   102: aload #4
    //   104: ldc '' as SQL Date; at path '
    //   106: invokevirtual append : (Ljava/lang/String;)Ljava/lang/StringBuilder;
    //   109: pop
    //   110: aload #4
    //   112: aload_1
    //   113: iconst_1
    //   114: invokevirtual m : (Z)Ljava/lang/String;
    //   117: invokevirtual append : (Ljava/lang/String;)Ljava/lang/StringBuilder;
    //   120: pop
    //   121: aload #5
    //   123: aload #4
    //   125: invokevirtual toString : ()Ljava/lang/String;
    //   128: aload #6
    //   130: invokespecial <init> : (Ljava/lang/String;Ljava/lang/Throwable;)V
    //   133: aload #5
    //   135: athrow
    //   136: aload_0
    //   137: getfield a : Ljava/text/SimpleDateFormat;
    //   140: aload_2
    //   141: invokevirtual setTimeZone : (Ljava/util/TimeZone;)V
    //   144: aload_1
    //   145: athrow
    //   146: aload_0
    //   147: monitorexit
    //   148: aload_1
    //   149: athrow
    // Exception table:
    //   from	to	target	type
    //   22	30	68	finally
    //   30	55	76	java/text/ParseException
    //   30	55	72	finally
    //   55	65	68	finally
    //   78	136	72	finally
    //   136	146	68	finally
    //   146	148	68	finally
  }
  
  public final void c(cl0 paramcl0, Object paramObject) {
    // Byte code:
    //   0: aload_2
    //   1: checkcast java/sql/Date
    //   4: astore_2
    //   5: aload_2
    //   6: ifnonnull -> 15
    //   9: aload_1
    //   10: invokevirtual o : ()Lcl0;
    //   13: pop
    //   14: return
    //   15: aload_0
    //   16: monitorenter
    //   17: aload_0
    //   18: getfield a : Ljava/text/SimpleDateFormat;
    //   21: aload_2
    //   22: invokevirtual format : (Ljava/util/Date;)Ljava/lang/String;
    //   25: astore_2
    //   26: aload_0
    //   27: monitorexit
    //   28: aload_1
    //   29: aload_2
    //   30: invokevirtual w : (Ljava/lang/String;)V
    //   33: return
    //   34: astore_1
    //   35: aload_0
    //   36: monitorexit
    //   37: aload_1
    //   38: athrow
    // Exception table:
    //   from	to	target	type
    //   17	28	34	finally
    //   35	37	34	finally
  }
  
  public class a implements ky1 {
    public final jy1 a(my param1my, rz1 param1rz1) {
      return (param1rz1.a == Date.class) ? new no1(0) : null;
    }
  }
}


/* Location:              C:\Users\Kevin\Downloads\dex-tools-v2.4\dex-tools-v2.4\musicolet-dex2jar.jar!\no1.class
 * Java compiler version: 6 (50.0)
 * JD-Core Version:       1.1.3
 */