public final class ot0 {
  public final nt0 a;
  
  public final Object b;
  
  public final li1[] c;
  
  public boolean d;
  
  public boolean e;
  
  public pt0 f;
  
  public final boolean[] g;
  
  public final lz0[] h;
  
  public final zv0 i;
  
  public final ad j;
  
  public ot0 k;
  
  public vv1 l;
  
  public oz0 m;
  
  public long n;
  
  public ot0(lz0[] paramArrayOflz0, long paramLong, zv0 paramzv0, uv paramuv, ad paramad, pt0 parampt0, oz0 paramoz0) {
    this.h = paramArrayOflz0;
    this.n = paramLong;
    this.i = paramzv0;
    this.j = paramad;
    fw0 fw0 = parampt0.a;
    this.b = fw0.a;
    this.f = parampt0;
    this.l = vv1.f;
    this.m = paramoz0;
    this.c = new li1[paramArrayOflz0.length];
    this.g = new boolean[paramArrayOflz0.length];
    paramLong = parampt0.b;
    long l = parampt0.c;
    nt0 nt02 = paramad.a(fw0, paramuv, paramLong);
    nt0 nt01 = nt02;
    if (l != -9223372036854775807L) {
      nt01 = nt02;
      if (l != Long.MIN_VALUE)
        nt01 = new zl(nt02, l); 
    } 
    this.a = nt01;
  }
  
  public final long a(oz0 paramoz0, long paramLong, boolean paramBoolean, boolean[] paramArrayOfboolean) {
    byte b = 0;
    while (true) {
      int i = paramoz0.b;
      boolean bool = true;
      if (b < i) {
        if (paramBoolean || !paramoz0.a(this.m, b))
          bool = false; 
        this.g[b] = bool;
        b++;
        continue;
      } 
      b = 0;
      while (true) {
        lz0[] arrayOfLz0 = this.h;
        if (b < arrayOfLz0.length) {
          arrayOfLz0[b].getClass();
          b++;
          continue;
        } 
        b();
        this.m = paramoz0;
        c();
        zd[] arrayOfZd1 = ((xv1)paramoz0.e).b;
        zd[] arrayOfZd2 = (zd[])arrayOfZd1.clone();
        boolean[] arrayOfBoolean = this.g;
        li1[] arrayOfLi1 = this.c;
        paramLong = this.a.h(arrayOfZd2, arrayOfBoolean, arrayOfLi1, paramArrayOfboolean, paramLong);
        for (b = 0; b < arrayOfLz0.length; b++)
          arrayOfLz0[b].getClass(); 
        this.e = false;
        b = 0;
        while (true) {
          li1[] arrayOfLi11 = this.c;
          if (b < arrayOfLi11.length) {
            if (arrayOfLi11[b] != null) {
              n21.r(paramoz0.b(b));
              arrayOfLz0[b].getClass();
              this.e = true;
            } else {
              if (arrayOfZd1[b] == null) {
                paramBoolean = true;
              } else {
                paramBoolean = false;
              } 
              n21.r(paramBoolean);
            } 
            b++;
            continue;
          } 
          return paramLong;
        } 
        break;
      } 
      break;
    } 
  }
  
  public final void b() {
    if (this.k == null) {
      byte b = 0;
      while (true) {
        oz0 oz01 = this.m;
        if (b < oz01.b) {
          oz01.b(b);
          zd zd = ((xv1)this.m.e).b[b];
          b++;
          continue;
        } 
        break;
      } 
    } 
  }
  
  public final void c() {
    if (this.k == null) {
      byte b = 0;
      while (true) {
        oz0 oz01 = this.m;
        if (b < oz01.b) {
          oz01.b(b);
          zd zd = ((xv1)this.m.e).b[b];
          b++;
          continue;
        } 
        break;
      } 
    } 
  }
  
  public final long d() {
    long l;
    if (!this.d)
      return this.f.b; 
    if (this.e) {
      l = this.a.j();
    } else {
      l = Long.MIN_VALUE;
    } 
    return (l == Long.MIN_VALUE) ? this.f.d : l;
  }
  
  public final void e() {
    b();
    long l = this.f.c;
    ad ad1 = this.j;
    nt0 nt01 = this.a;
    if (l != -9223372036854775807L && l != Long.MIN_VALUE)
      try {
        ad1.k(((zl)nt01).b);
        return;
      } catch (RuntimeException runtimeException) {
        qv.n("MediaPeriodHolder", "Period release failed.", runtimeException);
        return;
      }  
    runtimeException.k(nt01);
  }
  
  public final oz0 f(float paramFloat) {
    // Byte code:
    //   0: aload_0
    //   1: getfield l : Lvv1;
    //   4: astore #33
    //   6: aload_0
    //   7: getfield h : [Llz0;
    //   10: astore #40
    //   12: aload #40
    //   14: arraylength
    //   15: istore #8
    //   17: iconst_1
    //   18: istore #9
    //   20: iload #8
    //   22: iconst_1
    //   23: iadd
    //   24: newarray int
    //   26: astore #32
    //   28: aload #40
    //   30: arraylength
    //   31: iconst_1
    //   32: iadd
    //   33: istore #10
    //   35: iload #10
    //   37: anewarray [Luv1;
    //   40: astore #39
    //   42: aload #40
    //   44: arraylength
    //   45: iconst_1
    //   46: iadd
    //   47: anewarray [[I
    //   50: astore #36
    //   52: iconst_0
    //   53: istore #8
    //   55: iload #8
    //   57: iload #10
    //   59: if_icmpge -> 95
    //   62: aload #33
    //   64: getfield b : I
    //   67: istore #11
    //   69: aload #39
    //   71: iload #8
    //   73: iload #11
    //   75: anewarray uv1
    //   78: aastore
    //   79: aload #36
    //   81: iload #8
    //   83: iload #11
    //   85: anewarray [I
    //   88: aastore
    //   89: iinc #8, 1
    //   92: goto -> 55
    //   95: aload #40
    //   97: arraylength
    //   98: istore #10
    //   100: iload #10
    //   102: newarray int
    //   104: astore #35
    //   106: iconst_0
    //   107: istore #8
    //   109: iload #8
    //   111: iload #10
    //   113: if_icmpge -> 137
    //   116: aload #40
    //   118: iload #8
    //   120: aaload
    //   121: invokevirtual getClass : ()Ljava/lang/Class;
    //   124: pop
    //   125: aload #35
    //   127: iload #8
    //   129: iconst_0
    //   130: iastore
    //   131: iinc #8, 1
    //   134: goto -> 109
    //   137: iconst_0
    //   138: istore #12
    //   140: iload #9
    //   142: istore #8
    //   144: iload #12
    //   146: aload #33
    //   148: getfield b : I
    //   151: if_icmpge -> 745
    //   154: aload #33
    //   156: getfield c : [Luv1;
    //   159: iload #12
    //   161: aaload
    //   162: astore #37
    //   164: aload #37
    //   166: getfield c : [Lla0;
    //   169: astore #38
    //   171: aload #37
    //   173: getfield b : I
    //   176: istore #20
    //   178: aload #38
    //   180: iconst_0
    //   181: aaload
    //   182: getfield k : Ljava/lang/String;
    //   185: astore #34
    //   187: getstatic tx0.a : Ljava/util/ArrayList;
    //   190: astore #41
    //   192: aload #34
    //   194: invokestatic isEmpty : (Ljava/lang/CharSequence;)Z
    //   197: ifeq -> 203
    //   200: goto -> 445
    //   203: ldc 'audio'
    //   205: aload #34
    //   207: invokestatic a : (Ljava/lang/String;)Ljava/lang/String;
    //   210: invokevirtual equals : (Ljava/lang/Object;)Z
    //   213: ifeq -> 219
    //   216: goto -> 445
    //   219: ldc 'video'
    //   221: aload #34
    //   223: invokestatic a : (Ljava/lang/String;)Ljava/lang/String;
    //   226: invokevirtual equals : (Ljava/lang/Object;)Z
    //   229: ifeq -> 235
    //   232: goto -> 445
    //   235: ldc 'text'
    //   237: aload #34
    //   239: invokestatic a : (Ljava/lang/String;)Ljava/lang/String;
    //   242: invokevirtual equals : (Ljava/lang/Object;)Z
    //   245: ifne -> 445
    //   248: ldc 'application/cea-608'
    //   250: aload #34
    //   252: invokevirtual equals : (Ljava/lang/Object;)Z
    //   255: ifne -> 445
    //   258: ldc 'application/cea-708'
    //   260: aload #34
    //   262: invokevirtual equals : (Ljava/lang/Object;)Z
    //   265: ifne -> 445
    //   268: ldc 'application/x-mp4-cea-608'
    //   270: aload #34
    //   272: invokevirtual equals : (Ljava/lang/Object;)Z
    //   275: ifne -> 445
    //   278: ldc 'application/x-subrip'
    //   280: aload #34
    //   282: invokevirtual equals : (Ljava/lang/Object;)Z
    //   285: ifne -> 445
    //   288: ldc 'application/ttml+xml'
    //   290: aload #34
    //   292: invokevirtual equals : (Ljava/lang/Object;)Z
    //   295: ifne -> 445
    //   298: ldc 'application/x-quicktime-tx3g'
    //   300: aload #34
    //   302: invokevirtual equals : (Ljava/lang/Object;)Z
    //   305: ifne -> 445
    //   308: ldc 'application/x-mp4-vtt'
    //   310: aload #34
    //   312: invokevirtual equals : (Ljava/lang/Object;)Z
    //   315: ifne -> 445
    //   318: ldc 'application/x-rawcc'
    //   320: aload #34
    //   322: invokevirtual equals : (Ljava/lang/Object;)Z
    //   325: ifne -> 445
    //   328: ldc 'application/vobsub'
    //   330: aload #34
    //   332: invokevirtual equals : (Ljava/lang/Object;)Z
    //   335: ifne -> 445
    //   338: ldc 'application/pgs'
    //   340: aload #34
    //   342: invokevirtual equals : (Ljava/lang/Object;)Z
    //   345: ifne -> 445
    //   348: ldc 'application/dvbsubs'
    //   350: aload #34
    //   352: invokevirtual equals : (Ljava/lang/Object;)Z
    //   355: ifeq -> 361
    //   358: goto -> 445
    //   361: ldc 'application/id3'
    //   363: aload #34
    //   365: invokevirtual equals : (Ljava/lang/Object;)Z
    //   368: ifne -> 438
    //   371: ldc 'application/x-emsg'
    //   373: aload #34
    //   375: invokevirtual equals : (Ljava/lang/Object;)Z
    //   378: ifne -> 438
    //   381: ldc 'application/x-scte35'
    //   383: aload #34
    //   385: invokevirtual equals : (Ljava/lang/Object;)Z
    //   388: ifeq -> 394
    //   391: goto -> 438
    //   394: ldc 'application/x-camera-motion'
    //   396: aload #34
    //   398: invokevirtual equals : (Ljava/lang/Object;)Z
    //   401: ifeq -> 407
    //   404: goto -> 445
    //   407: getstatic tx0.a : Ljava/util/ArrayList;
    //   410: astore #34
    //   412: aload #34
    //   414: invokevirtual size : ()I
    //   417: ifgt -> 423
    //   420: goto -> 445
    //   423: aload #34
    //   425: iconst_0
    //   426: invokevirtual get : (I)Ljava/lang/Object;
    //   429: invokevirtual getClass : ()Ljava/lang/Class;
    //   432: pop
    //   433: invokestatic b : ()V
    //   436: aconst_null
    //   437: areturn
    //   438: iload #8
    //   440: istore #13
    //   442: goto -> 448
    //   445: iconst_0
    //   446: istore #13
    //   448: aload #40
    //   450: arraylength
    //   451: istore #14
    //   453: iload #8
    //   455: istore #15
    //   457: iconst_0
    //   458: istore #16
    //   460: iconst_0
    //   461: istore #9
    //   463: iload #9
    //   465: aload #40
    //   467: arraylength
    //   468: if_icmpge -> 642
    //   471: aload #40
    //   473: iload #9
    //   475: aaload
    //   476: astore #34
    //   478: iconst_0
    //   479: istore #11
    //   481: iconst_0
    //   482: istore #10
    //   484: iload #11
    //   486: iload #20
    //   488: if_icmpge -> 517
    //   491: iload #10
    //   493: aload #34
    //   495: aload #38
    //   497: iload #11
    //   499: aaload
    //   500: invokevirtual g : (Lla0;)I
    //   503: bipush #7
    //   505: iand
    //   506: invokestatic max : (II)I
    //   509: istore #10
    //   511: iinc #11, 1
    //   514: goto -> 484
    //   517: aload #32
    //   519: iload #9
    //   521: iaload
    //   522: ifne -> 532
    //   525: iload #8
    //   527: istore #11
    //   529: goto -> 535
    //   532: iconst_0
    //   533: istore #11
    //   535: iload #10
    //   537: iload #16
    //   539: if_icmpgt -> 612
    //   542: iload #16
    //   544: istore #19
    //   546: iload #14
    //   548: istore #18
    //   550: iload #15
    //   552: istore #17
    //   554: iload #10
    //   556: iload #16
    //   558: if_icmpne -> 624
    //   561: iload #16
    //   563: istore #19
    //   565: iload #14
    //   567: istore #18
    //   569: iload #15
    //   571: istore #17
    //   573: iload #13
    //   575: ifeq -> 624
    //   578: iload #16
    //   580: istore #19
    //   582: iload #14
    //   584: istore #18
    //   586: iload #15
    //   588: istore #17
    //   590: iload #15
    //   592: ifne -> 624
    //   595: iload #16
    //   597: istore #19
    //   599: iload #14
    //   601: istore #18
    //   603: iload #15
    //   605: istore #17
    //   607: iload #11
    //   609: ifeq -> 624
    //   612: iload #9
    //   614: istore #18
    //   616: iload #11
    //   618: istore #17
    //   620: iload #10
    //   622: istore #19
    //   624: iinc #9, 1
    //   627: iload #19
    //   629: istore #16
    //   631: iload #18
    //   633: istore #14
    //   635: iload #17
    //   637: istore #15
    //   639: goto -> 463
    //   642: iload #14
    //   644: aload #40
    //   646: arraylength
    //   647: if_icmpne -> 659
    //   650: iload #20
    //   652: newarray int
    //   654: astore #34
    //   656: goto -> 703
    //   659: aload #40
    //   661: iload #14
    //   663: aaload
    //   664: astore #41
    //   666: iload #20
    //   668: newarray int
    //   670: astore #34
    //   672: iconst_0
    //   673: istore #9
    //   675: iload #9
    //   677: iload #20
    //   679: if_icmpge -> 703
    //   682: aload #34
    //   684: iload #9
    //   686: aload #41
    //   688: aload #38
    //   690: iload #9
    //   692: aaload
    //   693: invokevirtual g : (Lla0;)I
    //   696: iastore
    //   697: iinc #9, 1
    //   700: goto -> 675
    //   703: aload #32
    //   705: iload #14
    //   707: iaload
    //   708: istore #9
    //   710: aload #39
    //   712: iload #14
    //   714: aaload
    //   715: iload #9
    //   717: aload #37
    //   719: aastore
    //   720: aload #36
    //   722: iload #14
    //   724: aaload
    //   725: iload #9
    //   727: aload #34
    //   729: aastore
    //   730: aload #32
    //   732: iload #14
    //   734: iload #9
    //   736: iconst_1
    //   737: iadd
    //   738: iastore
    //   739: iinc #12, 1
    //   742: goto -> 144
    //   745: aload #40
    //   747: arraylength
    //   748: anewarray vv1
    //   751: astore #38
    //   753: aload #40
    //   755: arraylength
    //   756: newarray int
    //   758: astore #37
    //   760: iconst_0
    //   761: istore #9
    //   763: iload #9
    //   765: aload #40
    //   767: arraylength
    //   768: if_icmpge -> 902
    //   771: aload #32
    //   773: iload #9
    //   775: iaload
    //   776: istore #11
    //   778: aload #39
    //   780: iload #9
    //   782: aaload
    //   783: astore #33
    //   785: getstatic d12.a : I
    //   788: istore #10
    //   790: iload #11
    //   792: aload #33
    //   794: arraylength
    //   795: if_icmpgt -> 805
    //   798: iload #8
    //   800: istore #10
    //   802: goto -> 808
    //   805: iconst_0
    //   806: istore #10
    //   808: iload #10
    //   810: invokestatic h : (Z)V
    //   813: aload #38
    //   815: iload #9
    //   817: new vv1
    //   820: dup
    //   821: aload #33
    //   823: iload #11
    //   825: invokestatic copyOf : ([Ljava/lang/Object;I)[Ljava/lang/Object;
    //   828: checkcast [Luv1;
    //   831: invokespecial <init> : ([Luv1;)V
    //   834: aastore
    //   835: aload #36
    //   837: iload #9
    //   839: aaload
    //   840: astore #33
    //   842: iload #11
    //   844: aload #33
    //   846: arraylength
    //   847: if_icmpgt -> 857
    //   850: iload #8
    //   852: istore #10
    //   854: goto -> 860
    //   857: iconst_0
    //   858: istore #10
    //   860: iload #10
    //   862: invokestatic h : (Z)V
    //   865: aload #36
    //   867: iload #9
    //   869: aload #33
    //   871: iload #11
    //   873: invokestatic copyOf : ([Ljava/lang/Object;I)[Ljava/lang/Object;
    //   876: checkcast [[I
    //   879: aastore
    //   880: aload #40
    //   882: iload #9
    //   884: aaload
    //   885: invokevirtual getClass : ()Ljava/lang/Class;
    //   888: pop
    //   889: aload #37
    //   891: iload #9
    //   893: iload #8
    //   895: iastore
    //   896: iinc #9, 1
    //   899: goto -> 763
    //   902: aload #32
    //   904: aload #40
    //   906: arraylength
    //   907: iaload
    //   908: istore #10
    //   910: new vv1
    //   913: astore #32
    //   915: aload #39
    //   917: aload #40
    //   919: arraylength
    //   920: aaload
    //   921: astore #32
    //   923: getstatic d12.a : I
    //   926: istore #9
    //   928: iload #10
    //   930: aload #32
    //   932: arraylength
    //   933: if_icmpgt -> 943
    //   936: iload #8
    //   938: istore #9
    //   940: goto -> 946
    //   943: iconst_0
    //   944: istore #9
    //   946: iload #9
    //   948: invokestatic h : (Z)V
    //   951: aload #32
    //   953: iload #10
    //   955: invokestatic copyOf : ([Ljava/lang/Object;I)[Ljava/lang/Object;
    //   958: checkcast [Luv1;
    //   961: astore #32
    //   963: new nr0
    //   966: dup
    //   967: aload #37
    //   969: aload #38
    //   971: invokespecial <init> : ([I[Lvv1;)V
    //   974: astore #46
    //   976: aload_0
    //   977: getfield i : Lzv0;
    //   980: astore #48
    //   982: aload #48
    //   984: getfield f : Ljava/lang/Object;
    //   987: checkcast java/util/concurrent/atomic/AtomicReference
    //   990: invokevirtual get : ()Ljava/lang/Object;
    //   993: checkcast ox
    //   996: astore #47
    //   998: aload #46
    //   1000: getfield a : I
    //   1003: istore #23
    //   1005: iload #23
    //   1007: anewarray wv1
    //   1010: astore #39
    //   1012: iconst_0
    //   1013: istore #9
    //   1015: iconst_0
    //   1016: istore #12
    //   1018: iconst_0
    //   1019: istore #10
    //   1021: aload #35
    //   1023: astore #32
    //   1025: getstatic zv0.h : [I
    //   1028: astore #34
    //   1030: iload #9
    //   1032: iload #23
    //   1034: if_icmpge -> 2367
    //   1037: iconst_2
    //   1038: aload #37
    //   1040: iload #9
    //   1042: iaload
    //   1043: if_icmpne -> 2354
    //   1046: iload #12
    //   1048: ifne -> 2319
    //   1051: aload #38
    //   1053: iload #9
    //   1055: aaload
    //   1056: astore #41
    //   1058: aload #36
    //   1060: iload #9
    //   1062: aaload
    //   1063: astore #43
    //   1065: aload #32
    //   1067: iload #9
    //   1069: iaload
    //   1070: istore #11
    //   1072: aload #47
    //   1074: getfield y : Z
    //   1077: istore #29
    //   1079: aload #47
    //   1081: getfield q : Z
    //   1084: istore #27
    //   1086: aload #47
    //   1088: getfield p : I
    //   1091: istore #19
    //   1093: aload #47
    //   1095: getfield o : I
    //   1098: istore #20
    //   1100: aload #47
    //   1102: getfield x : Z
    //   1105: istore #28
    //   1107: iload #29
    //   1109: ifne -> 1667
    //   1112: iload #28
    //   1114: ifne -> 1667
    //   1117: aload #47
    //   1119: getfield n : Z
    //   1122: ifeq -> 1132
    //   1125: bipush #24
    //   1127: istore #13
    //   1129: goto -> 1139
    //   1132: bipush #16
    //   1134: istore #13
    //   1136: goto -> 1129
    //   1139: aload #47
    //   1141: getfield m : Z
    //   1144: ifeq -> 1162
    //   1147: iload #11
    //   1149: iload #13
    //   1151: iand
    //   1152: ifeq -> 1162
    //   1155: iload #8
    //   1157: istore #11
    //   1159: goto -> 1165
    //   1162: iconst_0
    //   1163: istore #11
    //   1165: iconst_0
    //   1166: istore #15
    //   1168: iload #11
    //   1170: istore #14
    //   1172: iload #9
    //   1174: istore #11
    //   1176: aload #32
    //   1178: astore #33
    //   1180: iload #10
    //   1182: istore #12
    //   1184: iload #15
    //   1186: aload #41
    //   1188: getfield b : I
    //   1191: if_icmpge -> 1656
    //   1194: aload #41
    //   1196: getfield c : [Luv1;
    //   1199: iload #15
    //   1201: aaload
    //   1202: astore #44
    //   1204: aload #43
    //   1206: iload #15
    //   1208: aaload
    //   1209: astore #49
    //   1211: aload #47
    //   1213: getfield h : I
    //   1216: istore #21
    //   1218: aload #47
    //   1220: getfield i : I
    //   1223: istore #24
    //   1225: aload #47
    //   1227: getfield j : I
    //   1230: istore #22
    //   1232: aload #47
    //   1234: getfield k : I
    //   1237: istore #25
    //   1239: aload #44
    //   1241: getfield b : I
    //   1244: istore #11
    //   1246: aload #44
    //   1248: getfield c : [Lla0;
    //   1251: astore #50
    //   1253: iload #11
    //   1255: iconst_2
    //   1256: if_icmpge -> 1266
    //   1259: aload #34
    //   1261: astore #33
    //   1263: goto -> 1624
    //   1266: aload #44
    //   1268: iload #20
    //   1270: iload #19
    //   1272: iload #27
    //   1274: invokestatic s : (Luv1;IIZ)Ljava/util/ArrayList;
    //   1277: astore #45
    //   1279: aload #45
    //   1281: invokevirtual size : ()I
    //   1284: iconst_2
    //   1285: if_icmpge -> 1291
    //   1288: goto -> 1259
    //   1291: iload #14
    //   1293: ifne -> 1482
    //   1296: new java/util/HashSet
    //   1299: dup
    //   1300: invokespecial <init> : ()V
    //   1303: astore #40
    //   1305: aconst_null
    //   1306: astore #33
    //   1308: iconst_0
    //   1309: istore #16
    //   1311: iconst_0
    //   1312: istore #12
    //   1314: iload #16
    //   1316: aload #45
    //   1318: invokevirtual size : ()I
    //   1321: if_icmpge -> 1479
    //   1324: aload #50
    //   1326: aload #45
    //   1328: iload #16
    //   1330: invokevirtual get : (I)Ljava/lang/Object;
    //   1333: checkcast java/lang/Integer
    //   1336: invokevirtual intValue : ()I
    //   1339: aaload
    //   1340: getfield k : Ljava/lang/String;
    //   1343: astore #42
    //   1345: iload #12
    //   1347: istore #17
    //   1349: aload #33
    //   1351: astore #35
    //   1353: aload #40
    //   1355: aload #42
    //   1357: invokevirtual add : (Ljava/lang/Object;)Z
    //   1360: ifeq -> 1465
    //   1363: iconst_0
    //   1364: istore #17
    //   1366: iconst_0
    //   1367: istore #11
    //   1369: iload #17
    //   1371: aload #45
    //   1373: invokevirtual size : ()I
    //   1376: if_icmpge -> 1442
    //   1379: aload #45
    //   1381: iload #17
    //   1383: invokevirtual get : (I)Ljava/lang/Object;
    //   1386: checkcast java/lang/Integer
    //   1389: invokevirtual intValue : ()I
    //   1392: istore #26
    //   1394: iload #11
    //   1396: istore #18
    //   1398: aload #50
    //   1400: iload #26
    //   1402: aaload
    //   1403: aload #42
    //   1405: aload #49
    //   1407: iload #26
    //   1409: iaload
    //   1410: iload #13
    //   1412: iload #21
    //   1414: iload #24
    //   1416: iload #22
    //   1418: iload #25
    //   1420: invokestatic v : (Lla0;Ljava/lang/String;IIIIII)Z
    //   1423: ifeq -> 1432
    //   1426: iload #11
    //   1428: iconst_1
    //   1429: iadd
    //   1430: istore #18
    //   1432: iinc #17, 1
    //   1435: iload #18
    //   1437: istore #11
    //   1439: goto -> 1369
    //   1442: iload #12
    //   1444: istore #17
    //   1446: aload #33
    //   1448: astore #35
    //   1450: iload #11
    //   1452: iload #12
    //   1454: if_icmple -> 1465
    //   1457: aload #42
    //   1459: astore #35
    //   1461: iload #11
    //   1463: istore #17
    //   1465: iinc #16, 1
    //   1468: iload #17
    //   1470: istore #12
    //   1472: aload #35
    //   1474: astore #33
    //   1476: goto -> 1314
    //   1479: goto -> 1485
    //   1482: aconst_null
    //   1483: astore #33
    //   1485: aload #45
    //   1487: invokevirtual size : ()I
    //   1490: iconst_1
    //   1491: isub
    //   1492: istore #11
    //   1494: iload #11
    //   1496: iflt -> 1556
    //   1499: aload #45
    //   1501: iload #11
    //   1503: invokevirtual get : (I)Ljava/lang/Object;
    //   1506: checkcast java/lang/Integer
    //   1509: invokevirtual intValue : ()I
    //   1512: istore #12
    //   1514: aload #50
    //   1516: iload #12
    //   1518: aaload
    //   1519: aload #33
    //   1521: aload #49
    //   1523: iload #12
    //   1525: iaload
    //   1526: iload #13
    //   1528: iload #21
    //   1530: iload #24
    //   1532: iload #22
    //   1534: iload #25
    //   1536: invokestatic v : (Lla0;Ljava/lang/String;IIIIII)Z
    //   1539: ifne -> 1550
    //   1542: aload #45
    //   1544: iload #11
    //   1546: invokevirtual remove : (I)Ljava/lang/Object;
    //   1549: pop
    //   1550: iinc #11, -1
    //   1553: goto -> 1494
    //   1556: aload #45
    //   1558: invokevirtual size : ()I
    //   1561: iconst_2
    //   1562: if_icmpge -> 1568
    //   1565: goto -> 1259
    //   1568: getstatic d12.a : I
    //   1571: istore #11
    //   1573: aload #45
    //   1575: invokevirtual size : ()I
    //   1578: istore #12
    //   1580: iload #12
    //   1582: newarray int
    //   1584: astore #35
    //   1586: iconst_0
    //   1587: istore #11
    //   1589: aload #35
    //   1591: astore #33
    //   1593: iload #11
    //   1595: iload #12
    //   1597: if_icmpge -> 1624
    //   1600: aload #35
    //   1602: iload #11
    //   1604: aload #45
    //   1606: iload #11
    //   1608: invokevirtual get : (I)Ljava/lang/Object;
    //   1611: checkcast java/lang/Integer
    //   1614: invokevirtual intValue : ()I
    //   1617: iastore
    //   1618: iinc #11, 1
    //   1621: goto -> 1589
    //   1624: aload #33
    //   1626: arraylength
    //   1627: ifle -> 1650
    //   1630: new wv1
    //   1633: dup
    //   1634: aload #44
    //   1636: aload #33
    //   1638: invokespecial <init> : (Luv1;[I)V
    //   1641: astore #33
    //   1643: iload #9
    //   1645: istore #11
    //   1647: goto -> 1685
    //   1650: iinc #15, 1
    //   1653: goto -> 1172
    //   1656: aload #33
    //   1658: astore #32
    //   1660: iload #12
    //   1662: istore #10
    //   1664: goto -> 1682
    //   1667: iload #9
    //   1669: istore #11
    //   1671: aload #32
    //   1673: astore #33
    //   1675: iload #10
    //   1677: istore #12
    //   1679: goto -> 1656
    //   1682: aconst_null
    //   1683: astore #33
    //   1685: aload #33
    //   1687: astore #34
    //   1689: aload #33
    //   1691: ifnonnull -> 2290
    //   1694: aconst_null
    //   1695: astore #33
    //   1697: iconst_m1
    //   1698: istore #14
    //   1700: iconst_m1
    //   1701: istore #15
    //   1703: iconst_0
    //   1704: istore #12
    //   1706: iconst_0
    //   1707: istore #9
    //   1709: iconst_0
    //   1710: istore #13
    //   1712: aload #41
    //   1714: astore #35
    //   1716: iload #20
    //   1718: istore #18
    //   1720: iload #12
    //   1722: aload #35
    //   1724: getfield b : I
    //   1727: if_icmpge -> 2260
    //   1730: aload #35
    //   1732: getfield c : [Luv1;
    //   1735: iload #12
    //   1737: aaload
    //   1738: astore #40
    //   1740: aload #40
    //   1742: iload #18
    //   1744: iload #19
    //   1746: iload #27
    //   1748: invokestatic s : (Luv1;IIZ)Ljava/util/ArrayList;
    //   1751: astore #42
    //   1753: aload #43
    //   1755: iload #12
    //   1757: aaload
    //   1758: astore #41
    //   1760: iload #15
    //   1762: istore #16
    //   1764: iload #14
    //   1766: istore #15
    //   1768: iconst_0
    //   1769: istore #17
    //   1771: aload #33
    //   1773: astore #34
    //   1775: aload #40
    //   1777: astore #33
    //   1779: iload #16
    //   1781: istore #14
    //   1783: iload #12
    //   1785: istore #20
    //   1787: iload #17
    //   1789: istore #12
    //   1791: iload #12
    //   1793: aload #33
    //   1795: getfield b : I
    //   1798: if_icmpge -> 2231
    //   1801: aload #33
    //   1803: getfield c : [Lla0;
    //   1806: iload #12
    //   1808: aaload
    //   1809: astore #40
    //   1811: aload #40
    //   1813: getfield f : I
    //   1816: istore #16
    //   1818: aload #40
    //   1820: getfield q : I
    //   1823: istore #25
    //   1825: aload #40
    //   1827: getfield p : I
    //   1830: istore #24
    //   1832: aload #40
    //   1834: getfield g : I
    //   1837: istore #22
    //   1839: iload #16
    //   1841: sipush #16384
    //   1844: iand
    //   1845: ifeq -> 1851
    //   1848: goto -> 2225
    //   1851: aload #41
    //   1853: iload #12
    //   1855: iaload
    //   1856: aload #47
    //   1858: getfield z : Z
    //   1861: invokestatic t : (IZ)Z
    //   1864: ifeq -> 2225
    //   1867: aload #42
    //   1869: iload #12
    //   1871: invokestatic valueOf : (I)Ljava/lang/Integer;
    //   1874: invokevirtual contains : (Ljava/lang/Object;)Z
    //   1877: ifeq -> 1960
    //   1880: iload #24
    //   1882: iconst_m1
    //   1883: if_icmpeq -> 1896
    //   1886: iload #24
    //   1888: aload #47
    //   1890: getfield h : I
    //   1893: if_icmpgt -> 1960
    //   1896: iload #25
    //   1898: iconst_m1
    //   1899: if_icmpeq -> 1912
    //   1902: iload #25
    //   1904: aload #47
    //   1906: getfield i : I
    //   1909: if_icmpgt -> 1960
    //   1912: aload #40
    //   1914: getfield r : F
    //   1917: fstore_1
    //   1918: fload_1
    //   1919: ldc_w -1.0
    //   1922: fcmpl
    //   1923: ifeq -> 1937
    //   1926: fload_1
    //   1927: aload #47
    //   1929: getfield j : I
    //   1932: i2f
    //   1933: fcmpg
    //   1934: ifgt -> 1960
    //   1937: iload #22
    //   1939: iconst_m1
    //   1940: if_icmpeq -> 1953
    //   1943: iload #22
    //   1945: aload #47
    //   1947: getfield k : I
    //   1950: if_icmpgt -> 1960
    //   1953: iload #8
    //   1955: istore #21
    //   1957: goto -> 1963
    //   1960: iconst_0
    //   1961: istore #21
    //   1963: iload #21
    //   1965: ifne -> 1979
    //   1968: aload #47
    //   1970: getfield l : Z
    //   1973: ifne -> 1979
    //   1976: goto -> 2225
    //   1979: iload #21
    //   1981: ifeq -> 1990
    //   1984: iconst_2
    //   1985: istore #17
    //   1987: goto -> 1994
    //   1990: iload #8
    //   1992: istore #17
    //   1994: aload #41
    //   1996: iload #12
    //   1998: iaload
    //   1999: iconst_0
    //   2000: invokestatic t : (IZ)Z
    //   2003: istore #29
    //   2005: iload #17
    //   2007: istore #16
    //   2009: iload #29
    //   2011: ifeq -> 2022
    //   2014: iload #17
    //   2016: sipush #1000
    //   2019: iadd
    //   2020: istore #16
    //   2022: iload #16
    //   2024: iload #13
    //   2026: if_icmple -> 2036
    //   2029: iload #8
    //   2031: istore #17
    //   2033: goto -> 2039
    //   2036: iconst_0
    //   2037: istore #17
    //   2039: iload #16
    //   2041: iload #13
    //   2043: if_icmpne -> 2165
    //   2046: iload #22
    //   2048: iload #15
    //   2050: invokestatic l : (II)I
    //   2053: istore #17
    //   2055: iload #28
    //   2057: ifeq -> 2083
    //   2060: iload #17
    //   2062: ifeq -> 2083
    //   2065: iload #17
    //   2067: ifge -> 2077
    //   2070: iload #8
    //   2072: istore #17
    //   2074: goto -> 2165
    //   2077: iconst_0
    //   2078: istore #17
    //   2080: goto -> 2165
    //   2083: iload #24
    //   2085: iconst_m1
    //   2086: if_icmpeq -> 2108
    //   2089: iload #25
    //   2091: iconst_m1
    //   2092: if_icmpne -> 2098
    //   2095: goto -> 2108
    //   2098: iload #24
    //   2100: iload #25
    //   2102: imul
    //   2103: istore #17
    //   2105: goto -> 2111
    //   2108: iconst_m1
    //   2109: istore #17
    //   2111: iload #17
    //   2113: iload #14
    //   2115: if_icmpeq -> 2130
    //   2118: iload #17
    //   2120: iload #14
    //   2122: invokestatic l : (II)I
    //   2125: istore #17
    //   2127: goto -> 2139
    //   2130: iload #22
    //   2132: iload #15
    //   2134: invokestatic l : (II)I
    //   2137: istore #17
    //   2139: iload #29
    //   2141: ifeq -> 2157
    //   2144: iload #21
    //   2146: ifeq -> 2157
    //   2149: iload #17
    //   2151: ifle -> 2077
    //   2154: goto -> 2070
    //   2157: iload #17
    //   2159: ifge -> 2077
    //   2162: goto -> 2070
    //   2165: iload #17
    //   2167: ifeq -> 2225
    //   2170: iload #24
    //   2172: iconst_m1
    //   2173: if_icmpeq -> 2195
    //   2176: iload #25
    //   2178: iconst_m1
    //   2179: if_icmpne -> 2185
    //   2182: goto -> 2195
    //   2185: iload #24
    //   2187: iload #25
    //   2189: imul
    //   2190: istore #9
    //   2192: goto -> 2198
    //   2195: iconst_m1
    //   2196: istore #9
    //   2198: iload #16
    //   2200: istore #13
    //   2202: iload #22
    //   2204: istore #15
    //   2206: iload #12
    //   2208: istore #16
    //   2210: aload #33
    //   2212: astore #34
    //   2214: iload #9
    //   2216: istore #14
    //   2218: iload #16
    //   2220: istore #9
    //   2222: goto -> 2225
    //   2225: iinc #12, 1
    //   2228: goto -> 1791
    //   2231: iload #20
    //   2233: iconst_1
    //   2234: iadd
    //   2235: istore #16
    //   2237: iload #14
    //   2239: istore #12
    //   2241: aload #34
    //   2243: astore #33
    //   2245: iload #15
    //   2247: istore #14
    //   2249: iload #12
    //   2251: istore #15
    //   2253: iload #16
    //   2255: istore #12
    //   2257: goto -> 1720
    //   2260: aload #33
    //   2262: ifnonnull -> 2271
    //   2265: aconst_null
    //   2266: astore #34
    //   2268: goto -> 2290
    //   2271: new wv1
    //   2274: dup
    //   2275: aload #33
    //   2277: iconst_1
    //   2278: newarray int
    //   2280: dup
    //   2281: iconst_0
    //   2282: iload #9
    //   2284: iastore
    //   2285: invokespecial <init> : (Luv1;[I)V
    //   2288: astore #34
    //   2290: aload #39
    //   2292: iload #11
    //   2294: aload #34
    //   2296: aastore
    //   2297: aload #34
    //   2299: ifnull -> 2309
    //   2302: iload #8
    //   2304: istore #9
    //   2306: goto -> 2312
    //   2309: iconst_0
    //   2310: istore #9
    //   2312: iload #9
    //   2314: istore #12
    //   2316: goto -> 2323
    //   2319: iload #9
    //   2321: istore #11
    //   2323: aload #38
    //   2325: iload #11
    //   2327: aaload
    //   2328: getfield b : I
    //   2331: ifle -> 2341
    //   2334: iload #8
    //   2336: istore #9
    //   2338: goto -> 2344
    //   2341: iconst_0
    //   2342: istore #9
    //   2344: iload #10
    //   2346: iload #9
    //   2348: ior
    //   2349: istore #10
    //   2351: goto -> 2358
    //   2354: iload #9
    //   2356: istore #11
    //   2358: iload #11
    //   2360: iconst_1
    //   2361: iadd
    //   2362: istore #9
    //   2364: goto -> 1025
    //   2367: aconst_null
    //   2368: astore #40
    //   2370: aconst_null
    //   2371: astore #41
    //   2373: iconst_m1
    //   2374: istore #12
    //   2376: iconst_0
    //   2377: istore #11
    //   2379: iload #8
    //   2381: istore #9
    //   2383: aload #34
    //   2385: astore #33
    //   2387: iload #11
    //   2389: istore #8
    //   2391: iload #8
    //   2393: iload #23
    //   2395: if_icmpge -> 3254
    //   2398: iload #9
    //   2400: aload #37
    //   2402: iload #8
    //   2404: iaload
    //   2405: if_icmpne -> 3202
    //   2408: aload #38
    //   2410: iload #8
    //   2412: aaload
    //   2413: astore #35
    //   2415: aload #36
    //   2417: iload #8
    //   2419: aaload
    //   2420: astore #34
    //   2422: aload #32
    //   2424: iload #8
    //   2426: iaload
    //   2427: istore #9
    //   2429: aconst_null
    //   2430: astore #42
    //   2432: iconst_m1
    //   2433: istore #14
    //   2435: iconst_m1
    //   2436: istore #11
    //   2438: iconst_0
    //   2439: istore #9
    //   2441: aload #35
    //   2443: getfield b : I
    //   2446: istore #13
    //   2448: aload #35
    //   2450: getfield c : [Luv1;
    //   2453: astore #43
    //   2455: iload #9
    //   2457: iload #13
    //   2459: if_icmpge -> 2618
    //   2462: aload #43
    //   2464: iload #9
    //   2466: aaload
    //   2467: astore #44
    //   2469: aload #34
    //   2471: iload #9
    //   2473: aaload
    //   2474: astore #49
    //   2476: iconst_0
    //   2477: istore #15
    //   2479: iload #11
    //   2481: istore #13
    //   2483: iload #15
    //   2485: istore #11
    //   2487: iload #11
    //   2489: aload #44
    //   2491: getfield b : I
    //   2494: if_icmpge -> 2608
    //   2497: aload #49
    //   2499: iload #11
    //   2501: iaload
    //   2502: aload #47
    //   2504: getfield z : Z
    //   2507: invokestatic t : (IZ)Z
    //   2510: ifeq -> 2594
    //   2513: new nx
    //   2516: dup
    //   2517: aload #44
    //   2519: getfield c : [Lla0;
    //   2522: iload #11
    //   2524: aaload
    //   2525: aload #47
    //   2527: aload #49
    //   2529: iload #11
    //   2531: iaload
    //   2532: invokespecial <init> : (Lla0;Lox;I)V
    //   2535: astore #45
    //   2537: aload #45
    //   2539: getfield b : Z
    //   2542: ifne -> 2560
    //   2545: aload #47
    //   2547: getfield t : Z
    //   2550: ifne -> 2560
    //   2553: aload #42
    //   2555: astore #43
    //   2557: goto -> 2598
    //   2560: aload #42
    //   2562: ifnull -> 2579
    //   2565: aload #42
    //   2567: astore #43
    //   2569: aload #45
    //   2571: aload #42
    //   2573: invokevirtual a : (Lnx;)I
    //   2576: ifle -> 2598
    //   2579: aload #45
    //   2581: astore #43
    //   2583: iload #9
    //   2585: istore #14
    //   2587: iload #11
    //   2589: istore #13
    //   2591: goto -> 2598
    //   2594: aload #42
    //   2596: astore #43
    //   2598: iinc #11, 1
    //   2601: aload #43
    //   2603: astore #42
    //   2605: goto -> 2487
    //   2608: iinc #9, 1
    //   2611: iload #13
    //   2613: istore #11
    //   2615: goto -> 2441
    //   2618: iload #14
    //   2620: iconst_m1
    //   2621: if_icmpne -> 2630
    //   2624: aconst_null
    //   2625: astore #35
    //   2627: goto -> 3053
    //   2630: aload #43
    //   2632: iload #14
    //   2634: aaload
    //   2635: astore #44
    //   2637: aload #47
    //   2639: getfield y : Z
    //   2642: ifne -> 2995
    //   2645: aload #47
    //   2647: getfield x : Z
    //   2650: ifne -> 2995
    //   2653: iload #10
    //   2655: ifne -> 2995
    //   2658: aload #34
    //   2660: iload #14
    //   2662: aaload
    //   2663: astore #45
    //   2665: aload #47
    //   2667: getfield s : I
    //   2670: istore #17
    //   2672: aload #47
    //   2674: getfield u : Z
    //   2677: istore #29
    //   2679: aload #47
    //   2681: getfield v : Z
    //   2684: istore #28
    //   2686: aload #47
    //   2688: getfield w : Z
    //   2691: istore #27
    //   2693: new java/util/HashSet
    //   2696: dup
    //   2697: invokespecial <init> : ()V
    //   2700: astore #50
    //   2702: aconst_null
    //   2703: astore #34
    //   2705: iconst_0
    //   2706: istore #13
    //   2708: iconst_0
    //   2709: istore #14
    //   2711: aload #44
    //   2713: getfield b : I
    //   2716: istore #18
    //   2718: aload #44
    //   2720: getfield c : [Lla0;
    //   2723: astore #49
    //   2725: iload #13
    //   2727: iload #18
    //   2729: if_icmpge -> 2877
    //   2732: aload #49
    //   2734: iload #13
    //   2736: aaload
    //   2737: astore #35
    //   2739: new mx
    //   2742: dup
    //   2743: aload #35
    //   2745: getfield x : I
    //   2748: aload #35
    //   2750: getfield y : I
    //   2753: aload #35
    //   2755: getfield k : Ljava/lang/String;
    //   2758: invokespecial <init> : (IILjava/lang/String;)V
    //   2761: astore #35
    //   2763: iload #14
    //   2765: istore #15
    //   2767: aload #34
    //   2769: astore #43
    //   2771: aload #50
    //   2773: aload #35
    //   2775: invokevirtual add : (Ljava/lang/Object;)Z
    //   2778: ifeq -> 2863
    //   2781: iconst_0
    //   2782: istore #16
    //   2784: iconst_0
    //   2785: istore #9
    //   2787: iload #16
    //   2789: iload #18
    //   2791: if_icmpge -> 2840
    //   2794: iload #9
    //   2796: istore #15
    //   2798: aload #49
    //   2800: iload #16
    //   2802: aaload
    //   2803: aload #45
    //   2805: iload #16
    //   2807: iaload
    //   2808: aload #35
    //   2810: iload #17
    //   2812: iload #29
    //   2814: iload #28
    //   2816: iload #27
    //   2818: invokestatic u : (Lla0;ILmx;IZZZ)Z
    //   2821: ifeq -> 2830
    //   2824: iload #9
    //   2826: iconst_1
    //   2827: iadd
    //   2828: istore #15
    //   2830: iinc #16, 1
    //   2833: iload #15
    //   2835: istore #9
    //   2837: goto -> 2787
    //   2840: iload #14
    //   2842: istore #15
    //   2844: aload #34
    //   2846: astore #43
    //   2848: iload #9
    //   2850: iload #14
    //   2852: if_icmple -> 2863
    //   2855: aload #35
    //   2857: astore #43
    //   2859: iload #9
    //   2861: istore #15
    //   2863: iinc #13, 1
    //   2866: iload #15
    //   2868: istore #14
    //   2870: aload #43
    //   2872: astore #34
    //   2874: goto -> 2711
    //   2877: iload #14
    //   2879: iconst_1
    //   2880: if_icmple -> 2965
    //   2883: aload #34
    //   2885: invokevirtual getClass : ()Ljava/lang/Class;
    //   2888: pop
    //   2889: iload #14
    //   2891: newarray int
    //   2893: astore #43
    //   2895: iconst_0
    //   2896: istore #13
    //   2898: iconst_0
    //   2899: istore #14
    //   2901: aload #43
    //   2903: astore #35
    //   2905: iload #13
    //   2907: iload #18
    //   2909: if_icmpge -> 2969
    //   2912: iload #14
    //   2914: istore #9
    //   2916: aload #49
    //   2918: iload #13
    //   2920: aaload
    //   2921: aload #45
    //   2923: iload #13
    //   2925: iaload
    //   2926: aload #34
    //   2928: iload #17
    //   2930: iload #29
    //   2932: iload #28
    //   2934: iload #27
    //   2936: invokestatic u : (Lla0;ILmx;IZZZ)Z
    //   2939: ifeq -> 2955
    //   2942: aload #43
    //   2944: iload #14
    //   2946: iload #13
    //   2948: iastore
    //   2949: iload #14
    //   2951: iconst_1
    //   2952: iadd
    //   2953: istore #9
    //   2955: iinc #13, 1
    //   2958: iload #9
    //   2960: istore #14
    //   2962: goto -> 2901
    //   2965: aload #33
    //   2967: astore #35
    //   2969: aload #33
    //   2971: astore #34
    //   2973: aload #35
    //   2975: arraylength
    //   2976: ifle -> 2999
    //   2979: new wv1
    //   2982: dup
    //   2983: aload #44
    //   2985: aload #35
    //   2987: invokespecial <init> : (Luv1;[I)V
    //   2990: astore #34
    //   2992: goto -> 3010
    //   2995: aload #33
    //   2997: astore #34
    //   2999: aconst_null
    //   3000: astore #35
    //   3002: aload #34
    //   3004: astore #33
    //   3006: aload #35
    //   3008: astore #34
    //   3010: aload #34
    //   3012: astore #35
    //   3014: aload #34
    //   3016: ifnonnull -> 3038
    //   3019: new wv1
    //   3022: dup
    //   3023: aload #44
    //   3025: iconst_1
    //   3026: newarray int
    //   3028: dup
    //   3029: iconst_0
    //   3030: iload #11
    //   3032: iastore
    //   3033: invokespecial <init> : (Luv1;[I)V
    //   3036: astore #35
    //   3038: aload #42
    //   3040: invokevirtual getClass : ()Ljava/lang/Class;
    //   3043: pop
    //   3044: aload #35
    //   3046: aload #42
    //   3048: invokestatic create : (Ljava/lang/Object;Ljava/lang/Object;)Landroid/util/Pair;
    //   3051: astore #35
    //   3053: iload #12
    //   3055: istore #9
    //   3057: aload #40
    //   3059: astore #42
    //   3061: aload #41
    //   3063: astore #43
    //   3065: iload #8
    //   3067: istore #11
    //   3069: aload #33
    //   3071: astore #34
    //   3073: aload #35
    //   3075: ifnull -> 3222
    //   3078: aload #41
    //   3080: ifnull -> 3119
    //   3083: iload #12
    //   3085: istore #9
    //   3087: aload #40
    //   3089: astore #42
    //   3091: aload #41
    //   3093: astore #43
    //   3095: iload #8
    //   3097: istore #11
    //   3099: aload #33
    //   3101: astore #34
    //   3103: aload #35
    //   3105: getfield second : Ljava/lang/Object;
    //   3108: checkcast nx
    //   3111: aload #41
    //   3113: invokevirtual a : (Lnx;)I
    //   3116: ifle -> 3222
    //   3119: iload #12
    //   3121: iconst_m1
    //   3122: if_icmpeq -> 3131
    //   3125: aload #39
    //   3127: iload #12
    //   3129: aconst_null
    //   3130: aastore
    //   3131: aload #35
    //   3133: getfield first : Ljava/lang/Object;
    //   3136: checkcast wv1
    //   3139: astore #34
    //   3141: aload #39
    //   3143: iload #8
    //   3145: aload #34
    //   3147: aastore
    //   3148: aload #34
    //   3150: getfield a : Luv1;
    //   3153: astore #40
    //   3155: aload #34
    //   3157: getfield b : [I
    //   3160: iconst_0
    //   3161: iaload
    //   3162: istore #9
    //   3164: aload #40
    //   3166: getfield c : [Lla0;
    //   3169: iload #9
    //   3171: aaload
    //   3172: getfield C : Ljava/lang/String;
    //   3175: astore #42
    //   3177: aload #35
    //   3179: getfield second : Ljava/lang/Object;
    //   3182: checkcast nx
    //   3185: astore #43
    //   3187: iload #8
    //   3189: istore #9
    //   3191: iload #8
    //   3193: istore #11
    //   3195: aload #33
    //   3197: astore #34
    //   3199: goto -> 3222
    //   3202: aload #33
    //   3204: astore #34
    //   3206: iload #8
    //   3208: istore #11
    //   3210: aload #41
    //   3212: astore #43
    //   3214: aload #40
    //   3216: astore #42
    //   3218: iload #12
    //   3220: istore #9
    //   3222: iload #11
    //   3224: iconst_1
    //   3225: iadd
    //   3226: istore #8
    //   3228: aload #34
    //   3230: astore #33
    //   3232: iconst_1
    //   3233: istore #11
    //   3235: iload #9
    //   3237: istore #12
    //   3239: aload #42
    //   3241: astore #40
    //   3243: aload #43
    //   3245: astore #41
    //   3247: iload #11
    //   3249: istore #9
    //   3251: goto -> 2391
    //   3254: aconst_null
    //   3255: astore #32
    //   3257: iconst_m1
    //   3258: istore #12
    //   3260: iconst_0
    //   3261: istore #8
    //   3263: iload #8
    //   3265: iload #23
    //   3267: if_icmpge -> 3884
    //   3270: aload #37
    //   3272: iload #8
    //   3274: iaload
    //   3275: istore #9
    //   3277: iload #9
    //   3279: iconst_1
    //   3280: if_icmpeq -> 3855
    //   3283: iload #9
    //   3285: iconst_2
    //   3286: if_icmpeq -> 3855
    //   3289: iload #9
    //   3291: iconst_3
    //   3292: if_icmpeq -> 3540
    //   3295: aload #38
    //   3297: iload #8
    //   3299: aaload
    //   3300: astore #33
    //   3302: aload #36
    //   3304: iload #8
    //   3306: aaload
    //   3307: astore #41
    //   3309: aconst_null
    //   3310: astore #34
    //   3312: iconst_0
    //   3313: istore #13
    //   3315: iconst_0
    //   3316: istore #15
    //   3318: iconst_0
    //   3319: istore #14
    //   3321: iload #13
    //   3323: aload #33
    //   3325: getfield b : I
    //   3328: if_icmpge -> 3488
    //   3331: aload #33
    //   3333: getfield c : [Luv1;
    //   3336: iload #13
    //   3338: aaload
    //   3339: astore #42
    //   3341: aload #41
    //   3343: iload #13
    //   3345: aaload
    //   3346: astore #43
    //   3348: iconst_0
    //   3349: istore #9
    //   3351: aload #34
    //   3353: astore #35
    //   3355: aload #41
    //   3357: astore #34
    //   3359: iload #9
    //   3361: aload #42
    //   3363: getfield b : I
    //   3366: if_icmpge -> 3474
    //   3369: aload #43
    //   3371: iload #9
    //   3373: iaload
    //   3374: aload #47
    //   3376: getfield z : Z
    //   3379: invokestatic t : (IZ)Z
    //   3382: ifeq -> 3460
    //   3385: aload #42
    //   3387: getfield c : [Lla0;
    //   3390: iload #9
    //   3392: aaload
    //   3393: getfield e : I
    //   3396: iconst_1
    //   3397: iand
    //   3398: ifeq -> 3407
    //   3401: iconst_2
    //   3402: istore #11
    //   3404: goto -> 3410
    //   3407: iconst_1
    //   3408: istore #11
    //   3410: iload #11
    //   3412: istore #10
    //   3414: aload #43
    //   3416: iload #9
    //   3418: iaload
    //   3419: iconst_0
    //   3420: invokestatic t : (IZ)Z
    //   3423: ifeq -> 3434
    //   3426: iload #11
    //   3428: sipush #1000
    //   3431: iadd
    //   3432: istore #10
    //   3434: iload #14
    //   3436: istore #11
    //   3438: iload #10
    //   3440: iload #14
    //   3442: if_icmple -> 3464
    //   3445: aload #42
    //   3447: astore #35
    //   3449: iload #9
    //   3451: istore #15
    //   3453: iload #10
    //   3455: istore #11
    //   3457: goto -> 3464
    //   3460: iload #14
    //   3462: istore #11
    //   3464: iinc #9, 1
    //   3467: iload #11
    //   3469: istore #14
    //   3471: goto -> 3359
    //   3474: iinc #13, 1
    //   3477: aload #34
    //   3479: astore #41
    //   3481: aload #35
    //   3483: astore #34
    //   3485: goto -> 3321
    //   3488: aload #34
    //   3490: ifnonnull -> 3499
    //   3493: aconst_null
    //   3494: astore #33
    //   3496: goto -> 3518
    //   3499: new wv1
    //   3502: dup
    //   3503: aload #34
    //   3505: iconst_1
    //   3506: newarray int
    //   3508: dup
    //   3509: iconst_0
    //   3510: iload #15
    //   3512: iastore
    //   3513: invokespecial <init> : (Luv1;[I)V
    //   3516: astore #33
    //   3518: aload #39
    //   3520: iload #8
    //   3522: aload #33
    //   3524: aastore
    //   3525: iload #12
    //   3527: istore #10
    //   3529: aload #32
    //   3531: astore #34
    //   3533: iload #8
    //   3535: istore #9
    //   3537: goto -> 3867
    //   3540: aload #38
    //   3542: iload #8
    //   3544: aaload
    //   3545: astore #33
    //   3547: aload #36
    //   3549: iload #8
    //   3551: aaload
    //   3552: astore #42
    //   3554: aconst_null
    //   3555: astore #35
    //   3557: aconst_null
    //   3558: astore #34
    //   3560: iconst_m1
    //   3561: istore #10
    //   3563: iconst_0
    //   3564: istore #11
    //   3566: iload #11
    //   3568: aload #33
    //   3570: getfield b : I
    //   3573: if_icmpge -> 3714
    //   3576: aload #33
    //   3578: getfield c : [Luv1;
    //   3581: iload #11
    //   3583: aaload
    //   3584: astore #43
    //   3586: aload #42
    //   3588: iload #11
    //   3590: aaload
    //   3591: astore #44
    //   3593: iconst_0
    //   3594: istore #9
    //   3596: aload #34
    //   3598: astore #41
    //   3600: aload #42
    //   3602: astore #34
    //   3604: iload #9
    //   3606: aload #43
    //   3608: getfield b : I
    //   3611: if_icmpge -> 3700
    //   3614: aload #44
    //   3616: iload #9
    //   3618: iaload
    //   3619: aload #47
    //   3621: getfield z : Z
    //   3624: invokestatic t : (IZ)Z
    //   3627: ifeq -> 3694
    //   3630: new rx
    //   3633: dup
    //   3634: aload #43
    //   3636: getfield c : [Lla0;
    //   3639: iload #9
    //   3641: aaload
    //   3642: aload #47
    //   3644: aload #44
    //   3646: iload #9
    //   3648: iaload
    //   3649: aload #40
    //   3651: invokespecial <init> : (Lla0;Lox;ILjava/lang/String;)V
    //   3654: astore #42
    //   3656: aload #42
    //   3658: getfield b : Z
    //   3661: ifeq -> 3694
    //   3664: aload #41
    //   3666: ifnull -> 3679
    //   3669: aload #42
    //   3671: aload #41
    //   3673: invokevirtual a : (Lrx;)I
    //   3676: ifle -> 3694
    //   3679: aload #42
    //   3681: astore #41
    //   3683: aload #43
    //   3685: astore #35
    //   3687: iload #9
    //   3689: istore #10
    //   3691: goto -> 3694
    //   3694: iinc #9, 1
    //   3697: goto -> 3604
    //   3700: iinc #11, 1
    //   3703: aload #34
    //   3705: astore #42
    //   3707: aload #41
    //   3709: astore #34
    //   3711: goto -> 3566
    //   3714: aload #35
    //   3716: ifnonnull -> 3725
    //   3719: aconst_null
    //   3720: astore #33
    //   3722: goto -> 3759
    //   3725: new wv1
    //   3728: dup
    //   3729: aload #35
    //   3731: iconst_1
    //   3732: newarray int
    //   3734: dup
    //   3735: iconst_0
    //   3736: iload #10
    //   3738: iastore
    //   3739: invokespecial <init> : (Luv1;[I)V
    //   3742: astore #33
    //   3744: aload #34
    //   3746: invokevirtual getClass : ()Ljava/lang/Class;
    //   3749: pop
    //   3750: aload #33
    //   3752: aload #34
    //   3754: invokestatic create : (Ljava/lang/Object;Ljava/lang/Object;)Landroid/util/Pair;
    //   3757: astore #33
    //   3759: iload #12
    //   3761: istore #10
    //   3763: aload #32
    //   3765: astore #34
    //   3767: iload #8
    //   3769: istore #9
    //   3771: aload #33
    //   3773: ifnull -> 3867
    //   3776: aload #32
    //   3778: ifnull -> 3809
    //   3781: iload #12
    //   3783: istore #10
    //   3785: aload #32
    //   3787: astore #34
    //   3789: iload #8
    //   3791: istore #9
    //   3793: aload #33
    //   3795: getfield second : Ljava/lang/Object;
    //   3798: checkcast rx
    //   3801: aload #32
    //   3803: invokevirtual a : (Lrx;)I
    //   3806: ifle -> 3867
    //   3809: iload #12
    //   3811: iconst_m1
    //   3812: if_icmpeq -> 3821
    //   3815: aload #39
    //   3817: iload #12
    //   3819: aconst_null
    //   3820: aastore
    //   3821: aload #39
    //   3823: iload #8
    //   3825: aload #33
    //   3827: getfield first : Ljava/lang/Object;
    //   3830: checkcast wv1
    //   3833: aastore
    //   3834: aload #33
    //   3836: getfield second : Ljava/lang/Object;
    //   3839: checkcast rx
    //   3842: astore #34
    //   3844: iload #8
    //   3846: istore #10
    //   3848: iload #8
    //   3850: istore #9
    //   3852: goto -> 3867
    //   3855: iload #8
    //   3857: istore #9
    //   3859: aload #32
    //   3861: astore #34
    //   3863: iload #12
    //   3865: istore #10
    //   3867: iload #9
    //   3869: iconst_1
    //   3870: iadd
    //   3871: istore #8
    //   3873: iload #10
    //   3875: istore #12
    //   3877: aload #34
    //   3879: astore #32
    //   3881: goto -> 3263
    //   3884: iconst_0
    //   3885: istore #8
    //   3887: iload #8
    //   3889: iload #23
    //   3891: if_icmpge -> 4066
    //   3894: aload #47
    //   3896: getfield C : Landroid/util/SparseBooleanArray;
    //   3899: astore #33
    //   3901: aload #47
    //   3903: getfield B : Landroid/util/SparseArray;
    //   3906: astore #32
    //   3908: aload #33
    //   3910: iload #8
    //   3912: invokevirtual get : (I)Z
    //   3915: ifeq -> 3927
    //   3918: aload #39
    //   3920: iload #8
    //   3922: aconst_null
    //   3923: aastore
    //   3924: goto -> 4060
    //   3927: aload #38
    //   3929: iload #8
    //   3931: aaload
    //   3932: astore #33
    //   3934: aload #32
    //   3936: iload #8
    //   3938: invokevirtual get : (I)Ljava/lang/Object;
    //   3941: checkcast java/util/Map
    //   3944: astore #34
    //   3946: aload #34
    //   3948: ifnull -> 4060
    //   3951: aload #34
    //   3953: aload #33
    //   3955: invokeinterface containsKey : (Ljava/lang/Object;)Z
    //   3960: ifeq -> 4060
    //   3963: aload #32
    //   3965: iload #8
    //   3967: invokevirtual get : (I)Ljava/lang/Object;
    //   3970: checkcast java/util/Map
    //   3973: astore #32
    //   3975: aload #32
    //   3977: ifnull -> 3997
    //   3980: aload #32
    //   3982: aload #33
    //   3984: invokeinterface get : (Ljava/lang/Object;)Ljava/lang/Object;
    //   3989: checkcast qx
    //   3992: astore #32
    //   3994: goto -> 4000
    //   3997: aconst_null
    //   3998: astore #32
    //   4000: aload #32
    //   4002: ifnonnull -> 4011
    //   4005: aconst_null
    //   4006: astore #32
    //   4008: goto -> 4053
    //   4011: aload #32
    //   4013: getfield b : I
    //   4016: istore #9
    //   4018: new wv1
    //   4021: dup
    //   4022: aload #33
    //   4024: getfield c : [Luv1;
    //   4027: iload #9
    //   4029: aaload
    //   4030: aload #32
    //   4032: getfield c : [I
    //   4035: aload #32
    //   4037: getfield e : I
    //   4040: aload #32
    //   4042: getfield f : I
    //   4045: invokestatic valueOf : (I)Ljava/lang/Integer;
    //   4048: invokespecial <init> : (Luv1;[IILjava/lang/Integer;)V
    //   4051: astore #32
    //   4053: aload #39
    //   4055: iload #8
    //   4057: aload #32
    //   4059: aastore
    //   4060: iinc #8, 1
    //   4063: goto -> 3887
    //   4066: aload #48
    //   4068: getfield e : Ljava/lang/Object;
    //   4071: checkcast hp2
    //   4074: astore #32
    //   4076: aload #48
    //   4078: getfield c : Ljava/lang/Object;
    //   4081: checkcast wv
    //   4084: invokevirtual getClass : ()Ljava/lang/Class;
    //   4087: pop
    //   4088: aload #32
    //   4090: invokevirtual getClass : ()Ljava/lang/Class;
    //   4093: pop
    //   4094: iload #23
    //   4096: anewarray zd
    //   4099: astore #33
    //   4101: iconst_0
    //   4102: istore #8
    //   4104: iload #8
    //   4106: iload #23
    //   4108: if_icmpge -> 4192
    //   4111: aload #39
    //   4113: iload #8
    //   4115: aaload
    //   4116: astore #35
    //   4118: aload #35
    //   4120: ifnull -> 4186
    //   4123: aload #35
    //   4125: getfield a : Luv1;
    //   4128: astore #34
    //   4130: aload #35
    //   4132: getfield b : [I
    //   4135: astore #32
    //   4137: aload #32
    //   4139: arraylength
    //   4140: iconst_1
    //   4141: if_icmpne -> 4186
    //   4144: aload #33
    //   4146: iload #8
    //   4148: new e80
    //   4151: dup
    //   4152: aload #34
    //   4154: aload #32
    //   4156: iconst_0
    //   4157: iaload
    //   4158: aload #35
    //   4160: getfield c : Ljava/lang/Object;
    //   4163: invokespecial <init> : (Luv1;ILjava/lang/Object;)V
    //   4166: aastore
    //   4167: aload #32
    //   4169: iconst_0
    //   4170: iaload
    //   4171: istore #9
    //   4173: aload #34
    //   4175: getfield c : [Lla0;
    //   4178: iload #9
    //   4180: aaload
    //   4181: getfield g : I
    //   4184: istore #9
    //   4186: iinc #8, 1
    //   4189: goto -> 4104
    //   4192: new java/util/ArrayList
    //   4195: dup
    //   4196: invokespecial <init> : ()V
    //   4199: astore #34
    //   4201: iconst_0
    //   4202: istore #8
    //   4204: iload #8
    //   4206: iload #23
    //   4208: if_icmpge -> 4281
    //   4211: aload #39
    //   4213: iload #8
    //   4215: aaload
    //   4216: astore #35
    //   4218: aload #35
    //   4220: ifnull -> 4275
    //   4223: aload #35
    //   4225: getfield b : [I
    //   4228: astore #32
    //   4230: aload #32
    //   4232: arraylength
    //   4233: iconst_1
    //   4234: if_icmple -> 4275
    //   4237: new w2
    //   4240: dup
    //   4241: aload #35
    //   4243: getfield a : Luv1;
    //   4246: aload #32
    //   4248: new java/lang/Object
    //   4251: dup
    //   4252: invokespecial <init> : ()V
    //   4255: invokespecial <init> : (Luv1;[ILip2;)V
    //   4258: astore #32
    //   4260: aload #34
    //   4262: aload #32
    //   4264: invokevirtual add : (Ljava/lang/Object;)Z
    //   4267: pop
    //   4268: aload #33
    //   4270: iload #8
    //   4272: aload #32
    //   4274: aastore
    //   4275: iinc #8, 1
    //   4278: goto -> 4204
    //   4281: aload #34
    //   4283: invokevirtual size : ()I
    //   4286: iconst_1
    //   4287: if_icmple -> 4992
    //   4290: aload #34
    //   4292: invokevirtual size : ()I
    //   4295: istore #12
    //   4297: iload #12
    //   4299: anewarray [J
    //   4302: astore #35
    //   4304: iconst_0
    //   4305: istore #8
    //   4307: iload #8
    //   4309: aload #34
    //   4311: invokevirtual size : ()I
    //   4314: if_icmpge -> 4406
    //   4317: aload #34
    //   4319: iload #8
    //   4321: invokevirtual get : (I)Ljava/lang/Object;
    //   4324: checkcast w2
    //   4327: astore #32
    //   4329: aload #35
    //   4331: iload #8
    //   4333: aload #32
    //   4335: getfield c : [I
    //   4338: arraylength
    //   4339: newarray long
    //   4341: aastore
    //   4342: iconst_0
    //   4343: istore #9
    //   4345: aload #32
    //   4347: getfield c : [I
    //   4350: astore #39
    //   4352: iload #9
    //   4354: aload #39
    //   4356: arraylength
    //   4357: if_icmpge -> 4400
    //   4360: aload #35
    //   4362: iload #8
    //   4364: aaload
    //   4365: astore #40
    //   4367: aload #39
    //   4369: arraylength
    //   4370: istore #10
    //   4372: aload #40
    //   4374: iload #9
    //   4376: aload #32
    //   4378: getfield d : [Lla0;
    //   4381: iload #10
    //   4383: iload #9
    //   4385: isub
    //   4386: iconst_1
    //   4387: isub
    //   4388: aaload
    //   4389: getfield g : I
    //   4392: i2l
    //   4393: lastore
    //   4394: iinc #9, 1
    //   4397: goto -> 4345
    //   4400: iinc #8, 1
    //   4403: goto -> 4307
    //   4406: iload #12
    //   4408: anewarray [D
    //   4411: astore #32
    //   4413: iconst_0
    //   4414: istore #8
    //   4416: iload #8
    //   4418: iload #12
    //   4420: if_icmpge -> 4507
    //   4423: aload #32
    //   4425: iload #8
    //   4427: aload #35
    //   4429: iload #8
    //   4431: aaload
    //   4432: arraylength
    //   4433: newarray double
    //   4435: aastore
    //   4436: iconst_0
    //   4437: istore #9
    //   4439: aload #35
    //   4441: iload #8
    //   4443: aaload
    //   4444: astore #40
    //   4446: iload #9
    //   4448: aload #40
    //   4450: arraylength
    //   4451: if_icmpge -> 4501
    //   4454: aload #32
    //   4456: iload #8
    //   4458: aaload
    //   4459: astore #39
    //   4461: aload #40
    //   4463: iload #9
    //   4465: laload
    //   4466: lstore #30
    //   4468: lload #30
    //   4470: ldc2_w -1
    //   4473: lcmp
    //   4474: ifne -> 4482
    //   4477: dconst_0
    //   4478: dstore_2
    //   4479: goto -> 4489
    //   4482: lload #30
    //   4484: l2d
    //   4485: invokestatic log : (D)D
    //   4488: dstore_2
    //   4489: aload #39
    //   4491: iload #9
    //   4493: dload_2
    //   4494: dastore
    //   4495: iinc #9, 1
    //   4498: goto -> 4439
    //   4501: iinc #8, 1
    //   4504: goto -> 4416
    //   4507: iload #12
    //   4509: anewarray [D
    //   4512: astore #40
    //   4514: iconst_0
    //   4515: istore #8
    //   4517: iload #8
    //   4519: iload #12
    //   4521: if_icmpge -> 4667
    //   4524: aload #32
    //   4526: iload #8
    //   4528: aaload
    //   4529: arraylength
    //   4530: iconst_1
    //   4531: isub
    //   4532: istore #9
    //   4534: aload #40
    //   4536: iload #8
    //   4538: iload #9
    //   4540: newarray double
    //   4542: aastore
    //   4543: iload #9
    //   4545: ifne -> 4551
    //   4548: goto -> 4661
    //   4551: aload #32
    //   4553: iload #8
    //   4555: aaload
    //   4556: astore #39
    //   4558: aload #39
    //   4560: aload #39
    //   4562: arraylength
    //   4563: iconst_1
    //   4564: isub
    //   4565: daload
    //   4566: aload #39
    //   4568: iconst_0
    //   4569: daload
    //   4570: dsub
    //   4571: dstore #4
    //   4573: iconst_0
    //   4574: istore #9
    //   4576: aload #32
    //   4578: iload #8
    //   4580: aaload
    //   4581: astore #41
    //   4583: iload #9
    //   4585: aload #41
    //   4587: arraylength
    //   4588: iconst_1
    //   4589: isub
    //   4590: if_icmpge -> 4661
    //   4593: aload #41
    //   4595: iload #9
    //   4597: daload
    //   4598: dstore_2
    //   4599: iload #9
    //   4601: iconst_1
    //   4602: iadd
    //   4603: istore #10
    //   4605: aload #41
    //   4607: iload #10
    //   4609: daload
    //   4610: dstore #6
    //   4612: aload #40
    //   4614: iload #8
    //   4616: aaload
    //   4617: astore #39
    //   4619: dload #4
    //   4621: dconst_0
    //   4622: dcmpl
    //   4623: ifne -> 4631
    //   4626: dconst_1
    //   4627: dstore_2
    //   4628: goto -> 4648
    //   4631: dload_2
    //   4632: dload #6
    //   4634: dadd
    //   4635: ldc2_w 0.5
    //   4638: dmul
    //   4639: aload #41
    //   4641: iconst_0
    //   4642: daload
    //   4643: dsub
    //   4644: dload #4
    //   4646: ddiv
    //   4647: dstore_2
    //   4648: aload #39
    //   4650: iload #9
    //   4652: dload_2
    //   4653: dastore
    //   4654: iload #10
    //   4656: istore #9
    //   4658: goto -> 4576
    //   4661: iinc #8, 1
    //   4664: goto -> 4517
    //   4667: iconst_0
    //   4668: istore #10
    //   4670: iconst_0
    //   4671: istore #8
    //   4673: iload #8
    //   4675: iload #12
    //   4677: if_icmpge -> 4697
    //   4680: iload #10
    //   4682: aload #40
    //   4684: iload #8
    //   4686: aaload
    //   4687: arraylength
    //   4688: iadd
    //   4689: istore #10
    //   4691: iinc #8, 1
    //   4694: goto -> 4673
    //   4697: iload #12
    //   4699: iload #10
    //   4701: iconst_3
    //   4702: iadd
    //   4703: iconst_2
    //   4704: multianewarray[[[J 3
    //   4708: astore #39
    //   4710: iload #12
    //   4712: newarray int
    //   4714: astore #41
    //   4716: aload #39
    //   4718: iconst_1
    //   4719: aload #35
    //   4721: aload #41
    //   4723: invokestatic a : ([[[JI[[J[I)V
    //   4726: iconst_2
    //   4727: istore #11
    //   4729: iload #12
    //   4731: istore #8
    //   4733: iload #10
    //   4735: iconst_2
    //   4736: iadd
    //   4737: istore #9
    //   4739: iload #11
    //   4741: iload #9
    //   4743: if_icmpge -> 4856
    //   4746: ldc2_w 1.7976931348623157E308
    //   4749: dstore #4
    //   4751: iconst_0
    //   4752: istore #9
    //   4754: iconst_0
    //   4755: istore #12
    //   4757: iload #9
    //   4759: iload #8
    //   4761: if_icmpge -> 4827
    //   4764: aload #41
    //   4766: iload #9
    //   4768: iaload
    //   4769: istore #13
    //   4771: iload #13
    //   4773: iconst_1
    //   4774: iadd
    //   4775: aload #32
    //   4777: iload #9
    //   4779: aaload
    //   4780: arraylength
    //   4781: if_icmpne -> 4790
    //   4784: dload #4
    //   4786: dstore_2
    //   4787: goto -> 4818
    //   4790: aload #40
    //   4792: iload #9
    //   4794: aaload
    //   4795: iload #13
    //   4797: daload
    //   4798: dstore #6
    //   4800: dload #4
    //   4802: dstore_2
    //   4803: dload #6
    //   4805: dload #4
    //   4807: dcmpg
    //   4808: ifge -> 4818
    //   4811: iload #9
    //   4813: istore #12
    //   4815: dload #6
    //   4817: dstore_2
    //   4818: iinc #9, 1
    //   4821: dload_2
    //   4822: dstore #4
    //   4824: goto -> 4757
    //   4827: aload #41
    //   4829: iload #12
    //   4831: aload #41
    //   4833: iload #12
    //   4835: iaload
    //   4836: iconst_1
    //   4837: iadd
    //   4838: iastore
    //   4839: aload #39
    //   4841: iload #11
    //   4843: aload #35
    //   4845: aload #41
    //   4847: invokestatic a : ([[[JI[[J[I)V
    //   4850: iinc #11, 1
    //   4853: goto -> 4733
    //   4856: aload #39
    //   4858: arraylength
    //   4859: istore #11
    //   4861: iconst_0
    //   4862: istore #8
    //   4864: iload #8
    //   4866: iload #11
    //   4868: if_icmpge -> 4924
    //   4871: aload #39
    //   4873: iload #8
    //   4875: aaload
    //   4876: astore #35
    //   4878: aload #35
    //   4880: iload #9
    //   4882: aaload
    //   4883: astore #32
    //   4885: aload #35
    //   4887: iload #10
    //   4889: iconst_1
    //   4890: iadd
    //   4891: aaload
    //   4892: astore #35
    //   4894: aload #32
    //   4896: iconst_0
    //   4897: aload #35
    //   4899: iconst_0
    //   4900: laload
    //   4901: ldc2_w 2
    //   4904: lmul
    //   4905: lastore
    //   4906: aload #32
    //   4908: iconst_1
    //   4909: aload #35
    //   4911: iconst_1
    //   4912: laload
    //   4913: ldc2_w 2
    //   4916: lmul
    //   4917: lastore
    //   4918: iinc #8, 1
    //   4921: goto -> 4864
    //   4924: iconst_0
    //   4925: istore #8
    //   4927: iload #8
    //   4929: aload #34
    //   4931: invokevirtual size : ()I
    //   4934: if_icmpge -> 4992
    //   4937: aload #34
    //   4939: iload #8
    //   4941: invokevirtual get : (I)Ljava/lang/Object;
    //   4944: checkcast w2
    //   4947: astore #35
    //   4949: aload #39
    //   4951: iload #8
    //   4953: aaload
    //   4954: astore #32
    //   4956: aload #35
    //   4958: getfield f : Lip2;
    //   4961: invokevirtual getClass : ()Ljava/lang/Class;
    //   4964: pop
    //   4965: aload #32
    //   4967: arraylength
    //   4968: iconst_2
    //   4969: if_icmplt -> 4978
    //   4972: iconst_1
    //   4973: istore #27
    //   4975: goto -> 4981
    //   4978: iconst_0
    //   4979: istore #27
    //   4981: iload #27
    //   4983: invokestatic h : (Z)V
    //   4986: iinc #8, 1
    //   4989: goto -> 4927
    //   4992: iload #23
    //   4994: anewarray pf1
    //   4997: astore #34
    //   4999: iconst_0
    //   5000: istore #8
    //   5002: iload #8
    //   5004: iload #23
    //   5006: if_icmpge -> 5064
    //   5009: aload #47
    //   5011: getfield C : Landroid/util/SparseBooleanArray;
    //   5014: iload #8
    //   5016: invokevirtual get : (I)Z
    //   5019: ifne -> 5048
    //   5022: aload #37
    //   5024: iload #8
    //   5026: iaload
    //   5027: bipush #6
    //   5029: if_icmpeq -> 5040
    //   5032: aload #33
    //   5034: iload #8
    //   5036: aaload
    //   5037: ifnull -> 5048
    //   5040: getstatic pf1.b : Lpf1;
    //   5043: astore #32
    //   5045: goto -> 5051
    //   5048: aconst_null
    //   5049: astore #32
    //   5051: aload #34
    //   5053: iload #8
    //   5055: aload #32
    //   5057: aastore
    //   5058: iinc #8, 1
    //   5061: goto -> 5002
    //   5064: aload #47
    //   5066: getfield A : I
    //   5069: istore #13
    //   5071: iload #13
    //   5073: ifne -> 5079
    //   5076: goto -> 5338
    //   5079: iconst_0
    //   5080: istore #8
    //   5082: iconst_m1
    //   5083: istore #11
    //   5085: iconst_m1
    //   5086: istore #10
    //   5088: iload #8
    //   5090: iload #23
    //   5092: if_icmpge -> 5281
    //   5095: aload #37
    //   5097: iload #8
    //   5099: iaload
    //   5100: istore #14
    //   5102: aload #33
    //   5104: iload #8
    //   5106: aaload
    //   5107: astore #35
    //   5109: iload #14
    //   5111: iconst_1
    //   5112: if_icmpeq -> 5127
    //   5115: iload #14
    //   5117: iconst_2
    //   5118: if_icmpne -> 5124
    //   5121: goto -> 5127
    //   5124: goto -> 5275
    //   5127: aload #35
    //   5129: ifnull -> 5124
    //   5132: aload #36
    //   5134: iload #8
    //   5136: aaload
    //   5137: astore #32
    //   5139: aload #38
    //   5141: iload #8
    //   5143: aaload
    //   5144: astore #40
    //   5146: aload #35
    //   5148: getfield a : Luv1;
    //   5151: astore #39
    //   5153: iconst_0
    //   5154: istore #9
    //   5156: iload #9
    //   5158: aload #40
    //   5160: getfield b : I
    //   5163: if_icmpge -> 5188
    //   5166: aload #40
    //   5168: getfield c : [Luv1;
    //   5171: iload #9
    //   5173: aaload
    //   5174: aload #39
    //   5176: if_acmpne -> 5182
    //   5179: goto -> 5191
    //   5182: iinc #9, 1
    //   5185: goto -> 5156
    //   5188: iconst_m1
    //   5189: istore #9
    //   5191: iconst_0
    //   5192: istore #12
    //   5194: aload #35
    //   5196: getfield c : [I
    //   5199: astore #39
    //   5201: iload #12
    //   5203: aload #39
    //   5205: arraylength
    //   5206: if_icmpge -> 5237
    //   5209: aload #32
    //   5211: iload #9
    //   5213: aaload
    //   5214: aload #39
    //   5216: iload #12
    //   5218: iaload
    //   5219: iaload
    //   5220: bipush #32
    //   5222: iand
    //   5223: bipush #32
    //   5225: if_icmpeq -> 5231
    //   5228: goto -> 5124
    //   5231: iinc #12, 1
    //   5234: goto -> 5194
    //   5237: iload #14
    //   5239: iconst_1
    //   5240: if_icmpne -> 5262
    //   5243: iload #10
    //   5245: iconst_m1
    //   5246: if_icmpeq -> 5255
    //   5249: iconst_0
    //   5250: istore #8
    //   5252: goto -> 5284
    //   5255: iload #8
    //   5257: istore #10
    //   5259: goto -> 5275
    //   5262: iload #11
    //   5264: iconst_m1
    //   5265: if_icmpeq -> 5271
    //   5268: goto -> 5249
    //   5271: iload #8
    //   5273: istore #11
    //   5275: iinc #8, 1
    //   5278: goto -> 5088
    //   5281: iconst_1
    //   5282: istore #8
    //   5284: iconst_1
    //   5285: istore #9
    //   5287: iload #10
    //   5289: iconst_m1
    //   5290: if_icmpeq -> 5302
    //   5293: iload #11
    //   5295: iconst_m1
    //   5296: if_icmpeq -> 5302
    //   5299: goto -> 5305
    //   5302: iconst_0
    //   5303: istore #9
    //   5305: iload #8
    //   5307: iload #9
    //   5309: iand
    //   5310: ifeq -> 5338
    //   5313: new pf1
    //   5316: dup
    //   5317: iload #13
    //   5319: invokespecial <init> : (I)V
    //   5322: astore #32
    //   5324: aload #34
    //   5326: iload #10
    //   5328: aload #32
    //   5330: aastore
    //   5331: aload #34
    //   5333: iload #11
    //   5335: aload #32
    //   5337: aastore
    //   5338: aload #34
    //   5340: aload #33
    //   5342: invokestatic create : (Ljava/lang/Object;Ljava/lang/Object;)Landroid/util/Pair;
    //   5345: astore #32
    //   5347: new oz0
    //   5350: dup
    //   5351: aload #32
    //   5353: getfield first : Ljava/lang/Object;
    //   5356: checkcast [Lpf1;
    //   5359: aload #32
    //   5361: getfield second : Ljava/lang/Object;
    //   5364: checkcast [Lzd;
    //   5367: aload #46
    //   5369: invokespecial <init> : ([Lpf1;[Lzd;Lnr0;)V
    //   5372: astore #34
    //   5374: aload #34
    //   5376: getfield e : Ljava/lang/Object;
    //   5379: checkcast xv1
    //   5382: getfield b : [Lzd;
    //   5385: invokevirtual clone : ()Ljava/lang/Object;
    //   5388: checkcast [Lzd;
    //   5391: astore #32
    //   5393: aload #32
    //   5395: arraylength
    //   5396: istore #9
    //   5398: iconst_0
    //   5399: istore #8
    //   5401: iload #8
    //   5403: iload #9
    //   5405: if_icmpge -> 5421
    //   5408: aload #32
    //   5410: iload #8
    //   5412: aaload
    //   5413: astore #33
    //   5415: iinc #8, 1
    //   5418: goto -> 5401
    //   5421: aload #34
    //   5423: areturn
  }
}


/* Location:              C:\Users\Kevin\Downloads\dex-tools-v2.4\dex-tools-v2.4\musicolet-dex2jar.jar!\ot0.class
 * Java compiler version: 6 (50.0)
 * JD-Core Version:       1.1.3
 */