public abstract class p40 {
  public static final String a = qp0.j("EnqueueRunnable");
  
  public static boolean a(f72 paramf72) {
    // Byte code:
    //   0: aload_0
    //   1: invokestatic b : (Lf72;)Ljava/util/HashSet;
    //   4: astore #19
    //   6: aload_0
    //   7: getfield a : Lq72;
    //   10: astore #17
    //   12: aload_0
    //   13: getfield d : Ljava/util/List;
    //   16: astore #18
    //   18: iconst_0
    //   19: istore #8
    //   21: aload #19
    //   23: iconst_0
    //   24: anewarray java/lang/String
    //   27: invokevirtual toArray : ([Ljava/lang/Object;)[Ljava/lang/Object;
    //   30: checkcast [Ljava/lang/String;
    //   33: astore #19
    //   35: aload_0
    //   36: getfield b : Ljava/lang/String;
    //   39: astore #24
    //   41: aload_0
    //   42: getfield c : Lk60;
    //   45: astore #28
    //   47: aload #17
    //   49: getfield b : Lip;
    //   52: getfield d : Lfb0;
    //   55: invokevirtual getClass : ()Ljava/lang/Class;
    //   58: pop
    //   59: invokestatic currentTimeMillis : ()J
    //   62: lstore #15
    //   64: aload #17
    //   66: getfield c : Landroidx/work/impl/WorkDatabase;
    //   69: astore #23
    //   71: aload #19
    //   73: ifnull -> 88
    //   76: aload #19
    //   78: arraylength
    //   79: ifle -> 88
    //   82: iconst_1
    //   83: istore #4
    //   85: goto -> 91
    //   88: iconst_0
    //   89: istore #4
    //   91: getstatic o72.e : Lo72;
    //   94: astore #29
    //   96: getstatic o72.h : Lo72;
    //   99: astore #25
    //   101: getstatic o72.f : Lo72;
    //   104: astore #26
    //   106: iload #4
    //   108: ifeq -> 291
    //   111: aload #19
    //   113: arraylength
    //   114: istore #9
    //   116: iconst_0
    //   117: istore #6
    //   119: iconst_0
    //   120: istore #5
    //   122: iconst_1
    //   123: istore #7
    //   125: aload #18
    //   127: astore #20
    //   129: iload #6
    //   131: istore_2
    //   132: iload #5
    //   134: istore_1
    //   135: iload #7
    //   137: istore_3
    //   138: iload #8
    //   140: iload #9
    //   142: if_icmpge -> 288
    //   145: aload #19
    //   147: iload #8
    //   149: aaload
    //   150: astore #20
    //   152: aload #23
    //   154: invokevirtual v : ()Lc82;
    //   157: aload #20
    //   159: invokevirtual b : (Ljava/lang/String;)Ly72;
    //   162: astore #21
    //   164: aload #21
    //   166: ifnonnull -> 224
    //   169: invokestatic h : ()Lqp0;
    //   172: astore #17
    //   174: new java/lang/StringBuilder
    //   177: dup
    //   178: ldc 'Prerequisite '
    //   180: invokespecial <init> : (Ljava/lang/String;)V
    //   183: astore #18
    //   185: aload #18
    //   187: aload #20
    //   189: invokevirtual append : (Ljava/lang/String;)Ljava/lang/StringBuilder;
    //   192: pop
    //   193: aload #18
    //   195: ldc ' doesn't exist; not enqueuing'
    //   197: invokevirtual append : (Ljava/lang/String;)Ljava/lang/StringBuilder;
    //   200: pop
    //   201: aload #18
    //   203: invokevirtual toString : ()Ljava/lang/String;
    //   206: astore #18
    //   208: aload #17
    //   210: getstatic p40.a : Ljava/lang/String;
    //   213: aload #18
    //   215: invokevirtual f : (Ljava/lang/String;Ljava/lang/String;)V
    //   218: iconst_0
    //   219: istore #10
    //   221: goto -> 1782
    //   224: aload #21
    //   226: getfield b : Lo72;
    //   229: astore #20
    //   231: aload #20
    //   233: aload #29
    //   235: if_acmpne -> 243
    //   238: iconst_1
    //   239: istore_1
    //   240: goto -> 245
    //   243: iconst_0
    //   244: istore_1
    //   245: iload #7
    //   247: iload_1
    //   248: iand
    //   249: istore #7
    //   251: aload #20
    //   253: aload #26
    //   255: if_acmpne -> 263
    //   258: iconst_1
    //   259: istore_1
    //   260: goto -> 279
    //   263: iload #5
    //   265: istore_1
    //   266: aload #20
    //   268: aload #25
    //   270: if_acmpne -> 279
    //   273: iconst_1
    //   274: istore #6
    //   276: iload #5
    //   278: istore_1
    //   279: iinc #8, 1
    //   282: iload_1
    //   283: istore #5
    //   285: goto -> 125
    //   288: goto -> 304
    //   291: iconst_0
    //   292: istore_2
    //   293: iconst_0
    //   294: istore_1
    //   295: iconst_1
    //   296: istore_3
    //   297: aload #18
    //   299: astore #20
    //   301: goto -> 288
    //   304: aload #24
    //   306: invokestatic isEmpty : (Ljava/lang/CharSequence;)Z
    //   309: istore #11
    //   311: getstatic o72.b : Lo72;
    //   314: astore #27
    //   316: iload #11
    //   318: ifne -> 1062
    //   321: iload #4
    //   323: ifne -> 1062
    //   326: aload #23
    //   328: invokevirtual v : ()Lc82;
    //   331: astore #18
    //   333: aload #18
    //   335: invokevirtual getClass : ()Ljava/lang/Class;
    //   338: pop
    //   339: aload #24
    //   341: invokevirtual getClass : ()Ljava/lang/Class;
    //   344: pop
    //   345: aload #18
    //   347: getfield a : Leh1;
    //   350: astore #18
    //   352: new ey
    //   355: dup
    //   356: aload #24
    //   358: bipush #16
    //   360: invokespecial <init> : (Ljava/lang/String;I)V
    //   363: astore #21
    //   365: aload #18
    //   367: iconst_1
    //   368: iconst_0
    //   369: aload #21
    //   371: invokestatic N : (Leh1;ZZLwc0;)Ljava/lang/Object;
    //   374: checkcast java/util/List
    //   377: astore #21
    //   379: aload #21
    //   381: invokeinterface isEmpty : ()Z
    //   386: ifne -> 1055
    //   389: getstatic k60.e : Lk60;
    //   392: astore #18
    //   394: getstatic k60.f : Lk60;
    //   397: astore #30
    //   399: aload #28
    //   401: aload #18
    //   403: if_acmpeq -> 674
    //   406: aload #28
    //   408: aload #30
    //   410: if_acmpne -> 416
    //   413: goto -> 674
    //   416: aload #28
    //   418: getstatic k60.c : Lk60;
    //   421: if_acmpne -> 476
    //   424: aload #21
    //   426: invokeinterface iterator : ()Ljava/util/Iterator;
    //   431: astore #18
    //   433: aload #18
    //   435: invokeinterface hasNext : ()Z
    //   440: ifeq -> 476
    //   443: aload #18
    //   445: invokeinterface next : ()Ljava/lang/Object;
    //   450: checkcast x72
    //   453: getfield b : Lo72;
    //   456: astore #22
    //   458: aload #22
    //   460: aload #27
    //   462: if_acmpeq -> 218
    //   465: aload #22
    //   467: getstatic o72.c : Lo72;
    //   470: if_acmpne -> 433
    //   473: goto -> 218
    //   476: aload #23
    //   478: invokevirtual getClass : ()Ljava/lang/Class;
    //   481: pop
    //   482: aload #23
    //   484: invokevirtual b : ()V
    //   487: aload #23
    //   489: invokevirtual v : ()Lc82;
    //   492: astore #18
    //   494: aload #18
    //   496: invokevirtual getClass : ()Ljava/lang/Class;
    //   499: pop
    //   500: aload #18
    //   502: getfield a : Leh1;
    //   505: astore #22
    //   507: new ey
    //   510: astore #18
    //   512: aload #18
    //   514: aload #24
    //   516: bipush #9
    //   518: invokespecial <init> : (Ljava/lang/String;I)V
    //   521: aload #22
    //   523: iconst_1
    //   524: iconst_0
    //   525: aload #18
    //   527: invokestatic N : (Leh1;ZZLwc0;)Ljava/lang/Object;
    //   530: checkcast java/util/List
    //   533: invokeinterface iterator : ()Ljava/util/Iterator;
    //   538: astore #18
    //   540: aload #18
    //   542: invokeinterface hasNext : ()Z
    //   547: ifeq -> 568
    //   550: aload #17
    //   552: aload #18
    //   554: invokeinterface next : ()Ljava/lang/Object;
    //   559: checkcast java/lang/String
    //   562: invokestatic f : (Lq72;Ljava/lang/String;)V
    //   565: goto -> 540
    //   568: aload #23
    //   570: invokevirtual o : ()V
    //   573: aload #23
    //   575: invokevirtual l : ()V
    //   578: aload #23
    //   580: invokevirtual v : ()Lc82;
    //   583: astore #18
    //   585: aload #21
    //   587: invokeinterface iterator : ()Ljava/util/Iterator;
    //   592: astore #21
    //   594: aload #21
    //   596: invokeinterface hasNext : ()Z
    //   601: ifeq -> 656
    //   604: aload #21
    //   606: invokeinterface next : ()Ljava/lang/Object;
    //   611: checkcast x72
    //   614: getfield a : Ljava/lang/String;
    //   617: astore #22
    //   619: aload #18
    //   621: invokevirtual getClass : ()Ljava/lang/Class;
    //   624: pop
    //   625: aload #22
    //   627: invokevirtual getClass : ()Ljava/lang/Class;
    //   630: pop
    //   631: aload #18
    //   633: getfield a : Leh1;
    //   636: iconst_0
    //   637: iconst_1
    //   638: new ey
    //   641: dup
    //   642: aload #22
    //   644: bipush #15
    //   646: invokespecial <init> : (Ljava/lang/String;I)V
    //   649: invokestatic N : (Leh1;ZZLwc0;)Ljava/lang/Object;
    //   652: pop
    //   653: goto -> 594
    //   656: iconst_1
    //   657: istore #10
    //   659: aload #19
    //   661: astore #18
    //   663: goto -> 1069
    //   666: astore_0
    //   667: aload #23
    //   669: invokevirtual l : ()V
    //   672: aload_0
    //   673: athrow
    //   674: aload #23
    //   676: invokevirtual q : ()Lgy;
    //   679: astore #18
    //   681: new java/util/ArrayList
    //   684: dup
    //   685: invokespecial <init> : ()V
    //   688: astore #22
    //   690: aload #21
    //   692: invokeinterface iterator : ()Ljava/util/Iterator;
    //   697: astore #21
    //   699: aload #21
    //   701: invokeinterface hasNext : ()Z
    //   706: ifeq -> 861
    //   709: aload #21
    //   711: invokeinterface next : ()Ljava/lang/Object;
    //   716: checkcast x72
    //   719: astore #31
    //   721: aload #31
    //   723: getfield a : Ljava/lang/String;
    //   726: astore #32
    //   728: aload #18
    //   730: invokevirtual getClass : ()Ljava/lang/Class;
    //   733: pop
    //   734: aload #32
    //   736: invokevirtual getClass : ()Ljava/lang/Class;
    //   739: pop
    //   740: iload_2
    //   741: istore #6
    //   743: iload_1
    //   744: istore #4
    //   746: iload_3
    //   747: istore #5
    //   749: aload #18
    //   751: getfield a : Leh1;
    //   754: iconst_1
    //   755: iconst_0
    //   756: new ey
    //   759: dup
    //   760: aload #32
    //   762: iconst_0
    //   763: invokespecial <init> : (Ljava/lang/String;I)V
    //   766: invokestatic N : (Leh1;ZZLwc0;)Ljava/lang/Object;
    //   769: checkcast java/lang/Boolean
    //   772: invokevirtual booleanValue : ()Z
    //   775: ifne -> 849
    //   778: aload #31
    //   780: getfield b : Lo72;
    //   783: astore #32
    //   785: aload #32
    //   787: aload #29
    //   789: if_acmpne -> 798
    //   792: iconst_1
    //   793: istore #5
    //   795: goto -> 801
    //   798: iconst_0
    //   799: istore #5
    //   801: aload #32
    //   803: aload #26
    //   805: if_acmpne -> 814
    //   808: iconst_1
    //   809: istore #4
    //   811: goto -> 829
    //   814: iload_1
    //   815: istore #4
    //   817: aload #32
    //   819: aload #25
    //   821: if_acmpne -> 829
    //   824: iconst_1
    //   825: istore_2
    //   826: iload_1
    //   827: istore #4
    //   829: aload #22
    //   831: aload #31
    //   833: getfield a : Ljava/lang/String;
    //   836: invokevirtual add : (Ljava/lang/Object;)Z
    //   839: pop
    //   840: iload_3
    //   841: iload #5
    //   843: iand
    //   844: istore #5
    //   846: iload_2
    //   847: istore #6
    //   849: iload #6
    //   851: istore_2
    //   852: iload #4
    //   854: istore_1
    //   855: iload #5
    //   857: istore_3
    //   858: goto -> 699
    //   861: aload #22
    //   863: astore #18
    //   865: iload_2
    //   866: istore #6
    //   868: iload_1
    //   869: istore #5
    //   871: aload #28
    //   873: aload #30
    //   875: if_acmpne -> 1008
    //   878: iload_2
    //   879: ifne -> 896
    //   882: aload #22
    //   884: astore #18
    //   886: iload_2
    //   887: istore #6
    //   889: iload_1
    //   890: istore #5
    //   892: iload_1
    //   893: ifeq -> 1008
    //   896: aload #23
    //   898: invokevirtual v : ()Lc82;
    //   901: astore #18
    //   903: aload #18
    //   905: invokevirtual getClass : ()Ljava/lang/Class;
    //   908: pop
    //   909: aload #18
    //   911: getfield a : Leh1;
    //   914: astore #21
    //   916: aload #21
    //   918: iconst_1
    //   919: iconst_0
    //   920: new ey
    //   923: dup
    //   924: aload #24
    //   926: bipush #16
    //   928: invokespecial <init> : (Ljava/lang/String;I)V
    //   931: invokestatic N : (Leh1;ZZLwc0;)Ljava/lang/Object;
    //   934: checkcast java/util/List
    //   937: invokeinterface iterator : ()Ljava/util/Iterator;
    //   942: astore #18
    //   944: aload #18
    //   946: invokeinterface hasNext : ()Z
    //   951: ifeq -> 997
    //   954: aload #18
    //   956: invokeinterface next : ()Ljava/lang/Object;
    //   961: checkcast x72
    //   964: getfield a : Ljava/lang/String;
    //   967: astore #22
    //   969: aload #22
    //   971: invokevirtual getClass : ()Ljava/lang/Class;
    //   974: pop
    //   975: aload #21
    //   977: iconst_0
    //   978: iconst_1
    //   979: new ey
    //   982: dup
    //   983: aload #22
    //   985: bipush #15
    //   987: invokespecial <init> : (Ljava/lang/String;I)V
    //   990: invokestatic N : (Leh1;ZZLwc0;)Ljava/lang/Object;
    //   993: pop
    //   994: goto -> 944
    //   997: getstatic java/util/Collections.EMPTY_LIST : Ljava/util/List;
    //   1000: astore #18
    //   1002: iconst_0
    //   1003: istore #6
    //   1005: iconst_0
    //   1006: istore #5
    //   1008: aload #18
    //   1010: aload #19
    //   1012: invokeinterface toArray : ([Ljava/lang/Object;)[Ljava/lang/Object;
    //   1017: checkcast [Ljava/lang/String;
    //   1020: astore #18
    //   1022: aload #18
    //   1024: arraylength
    //   1025: ifle -> 1040
    //   1028: iconst_1
    //   1029: istore #4
    //   1031: iload #6
    //   1033: istore_2
    //   1034: iload #5
    //   1036: istore_1
    //   1037: goto -> 1049
    //   1040: iconst_0
    //   1041: istore #4
    //   1043: iload #5
    //   1045: istore_1
    //   1046: iload #6
    //   1048: istore_2
    //   1049: iconst_0
    //   1050: istore #10
    //   1052: goto -> 1069
    //   1055: aload #19
    //   1057: astore #18
    //   1059: goto -> 1049
    //   1062: aload #19
    //   1064: astore #18
    //   1066: goto -> 1049
    //   1069: aload #20
    //   1071: invokeinterface iterator : ()Ljava/util/Iterator;
    //   1076: astore #19
    //   1078: aload #17
    //   1080: astore #20
    //   1082: aload #19
    //   1084: invokeinterface hasNext : ()Z
    //   1089: ifeq -> 1782
    //   1092: aload #19
    //   1094: invokeinterface next : ()Ljava/lang/Object;
    //   1099: checkcast t41
    //   1102: astore #28
    //   1104: aload #28
    //   1106: getfield b : Ly72;
    //   1109: astore #17
    //   1111: aload #28
    //   1113: getfield a : Ljava/util/UUID;
    //   1116: astore #22
    //   1118: iload #4
    //   1120: ifeq -> 1166
    //   1123: iload_3
    //   1124: ifne -> 1166
    //   1127: iload_1
    //   1128: ifeq -> 1141
    //   1131: aload #17
    //   1133: aload #26
    //   1135: putfield b : Lo72;
    //   1138: goto -> 1173
    //   1141: iload_2
    //   1142: ifeq -> 1155
    //   1145: aload #17
    //   1147: aload #25
    //   1149: putfield b : Lo72;
    //   1152: goto -> 1173
    //   1155: aload #17
    //   1157: getstatic o72.g : Lo72;
    //   1160: putfield b : Lo72;
    //   1163: goto -> 1173
    //   1166: aload #17
    //   1168: lload #15
    //   1170: putfield n : J
    //   1173: aload #17
    //   1175: getfield b : Lo72;
    //   1178: aload #27
    //   1180: if_acmpne -> 1186
    //   1183: iconst_1
    //   1184: istore #10
    //   1186: aload #23
    //   1188: invokevirtual v : ()Lc82;
    //   1191: astore #29
    //   1193: aload #20
    //   1195: getfield e : Ljava/util/List;
    //   1198: invokevirtual getClass : ()Ljava/lang/Class;
    //   1201: pop
    //   1202: aload #17
    //   1204: getfield e : Ldu;
    //   1207: astore #30
    //   1209: aload #30
    //   1211: ldc 'androidx.work.multiprocess.RemoteListenableDelegatingWorker.ARGUMENT_REMOTE_LISTENABLE_WORKER_NAME'
    //   1213: invokevirtual a : (Ljava/lang/String;)Z
    //   1216: istore #12
    //   1218: aload #30
    //   1220: ldc 'androidx.work.impl.workers.RemoteListenableWorker.ARGUMENT_PACKAGE_NAME'
    //   1222: invokevirtual a : (Ljava/lang/String;)Z
    //   1225: istore #14
    //   1227: aload #30
    //   1229: ldc 'androidx.work.impl.workers.RemoteListenableWorker.ARGUMENT_CLASS_NAME'
    //   1231: invokevirtual a : (Ljava/lang/String;)Z
    //   1234: istore #13
    //   1236: iload #12
    //   1238: ifne -> 1329
    //   1241: iload #14
    //   1243: ifeq -> 1329
    //   1246: iload #13
    //   1248: ifeq -> 1329
    //   1251: aload #17
    //   1253: getfield c : Ljava/lang/String;
    //   1256: astore #21
    //   1258: new c4
    //   1261: dup
    //   1262: iconst_1
    //   1263: invokespecial <init> : (I)V
    //   1266: astore #31
    //   1268: aload #31
    //   1270: aload #30
    //   1272: getfield a : Ljava/util/HashMap;
    //   1275: invokevirtual c : (Ljava/util/HashMap;)V
    //   1278: aload #31
    //   1280: getfield a : Ljava/util/LinkedHashMap;
    //   1283: astore #30
    //   1285: aload #30
    //   1287: ldc 'androidx.work.multiprocess.RemoteListenableDelegatingWorker.ARGUMENT_REMOTE_LISTENABLE_WORKER_NAME'
    //   1289: aload #21
    //   1291: invokeinterface put : (Ljava/lang/Object;Ljava/lang/Object;)Ljava/lang/Object;
    //   1296: pop
    //   1297: new du
    //   1300: dup
    //   1301: aload #30
    //   1303: invokespecial <init> : (Ljava/util/LinkedHashMap;)V
    //   1306: astore #21
    //   1308: aload #21
    //   1310: invokestatic n0 : (Ldu;)[B
    //   1313: pop
    //   1314: aload #17
    //   1316: ldc_w 'androidx.work.multiprocess.RemoteListenableDelegatingWorker'
    //   1319: aload #21
    //   1321: invokestatic b : (Ly72;Ljava/lang/String;Ldu;)Ly72;
    //   1324: astore #17
    //   1326: goto -> 1329
    //   1329: aload #17
    //   1331: astore #21
    //   1333: getstatic android/os/Build$VERSION.SDK_INT : I
    //   1336: bipush #25
    //   1338: if_icmpgt -> 1478
    //   1341: aload #17
    //   1343: getfield j : Lhr;
    //   1346: astore #31
    //   1348: aload #17
    //   1350: getfield c : Ljava/lang/String;
    //   1353: astore #30
    //   1355: aload #17
    //   1357: astore #21
    //   1359: aload #30
    //   1361: ldc_w androidx/work/impl/workers/ConstraintTrackingWorker
    //   1364: invokevirtual getName : ()Ljava/lang/String;
    //   1367: invokestatic c : (Ljava/lang/Object;Ljava/lang/Object;)Z
    //   1370: ifne -> 1478
    //   1373: aload #31
    //   1375: getfield e : Z
    //   1378: ifne -> 1393
    //   1381: aload #17
    //   1383: astore #21
    //   1385: aload #31
    //   1387: getfield f : Z
    //   1390: ifeq -> 1478
    //   1393: new c4
    //   1396: dup
    //   1397: iconst_1
    //   1398: invokespecial <init> : (I)V
    //   1401: astore #21
    //   1403: aload #17
    //   1405: getfield e : Ldu;
    //   1408: astore #31
    //   1410: aload #31
    //   1412: invokevirtual getClass : ()Ljava/lang/Class;
    //   1415: pop
    //   1416: aload #21
    //   1418: aload #31
    //   1420: getfield a : Ljava/util/HashMap;
    //   1423: invokevirtual c : (Ljava/util/HashMap;)V
    //   1426: aload #21
    //   1428: getfield a : Ljava/util/LinkedHashMap;
    //   1431: astore #21
    //   1433: aload #21
    //   1435: ldc_w 'androidx.work.impl.workers.ConstraintTrackingWorker.ARGUMENT_CLASS_NAME'
    //   1438: aload #30
    //   1440: invokeinterface put : (Ljava/lang/Object;Ljava/lang/Object;)Ljava/lang/Object;
    //   1445: pop
    //   1446: new du
    //   1449: dup
    //   1450: aload #21
    //   1452: invokespecial <init> : (Ljava/util/LinkedHashMap;)V
    //   1455: astore #21
    //   1457: aload #21
    //   1459: invokestatic n0 : (Ldu;)[B
    //   1462: pop
    //   1463: aload #17
    //   1465: ldc_w androidx/work/impl/workers/ConstraintTrackingWorker
    //   1468: invokevirtual getName : ()Ljava/lang/String;
    //   1471: aload #21
    //   1473: invokestatic b : (Ly72;Ljava/lang/String;Ldu;)Ly72;
    //   1476: astore #21
    //   1478: aload #29
    //   1480: invokevirtual getClass : ()Ljava/lang/Class;
    //   1483: pop
    //   1484: aload #29
    //   1486: getfield a : Leh1;
    //   1489: iconst_0
    //   1490: iconst_1
    //   1491: new dy
    //   1494: dup
    //   1495: bipush #8
    //   1497: aload #29
    //   1499: aload #21
    //   1501: invokespecial <init> : (ILjava/lang/Object;Ljava/lang/Object;)V
    //   1504: invokestatic N : (Leh1;ZZLwc0;)Ljava/lang/Object;
    //   1507: pop
    //   1508: iload #4
    //   1510: ifeq -> 1603
    //   1513: aload #18
    //   1515: arraylength
    //   1516: istore #6
    //   1518: iconst_0
    //   1519: istore #5
    //   1521: iload #5
    //   1523: iload #6
    //   1525: if_icmpge -> 1603
    //   1528: aload #18
    //   1530: iload #5
    //   1532: aaload
    //   1533: astore #21
    //   1535: aload #22
    //   1537: invokevirtual toString : ()Ljava/lang/String;
    //   1540: astore #17
    //   1542: aload #17
    //   1544: invokevirtual getClass : ()Ljava/lang/Class;
    //   1547: pop
    //   1548: new ay
    //   1551: dup
    //   1552: aload #17
    //   1554: aload #21
    //   1556: invokespecial <init> : (Ljava/lang/String;Ljava/lang/String;)V
    //   1559: astore #17
    //   1561: aload #23
    //   1563: invokevirtual q : ()Lgy;
    //   1566: astore #21
    //   1568: aload #21
    //   1570: invokevirtual getClass : ()Ljava/lang/Class;
    //   1573: pop
    //   1574: aload #21
    //   1576: getfield a : Leh1;
    //   1579: iconst_0
    //   1580: iconst_1
    //   1581: new dy
    //   1584: dup
    //   1585: iconst_0
    //   1586: aload #21
    //   1588: aload #17
    //   1590: invokespecial <init> : (ILjava/lang/Object;Ljava/lang/Object;)V
    //   1593: invokestatic N : (Leh1;ZZLwc0;)Ljava/lang/Object;
    //   1596: pop
    //   1597: iinc #5, 1
    //   1600: goto -> 1521
    //   1603: aload #23
    //   1605: invokevirtual w : ()Le82;
    //   1608: astore #17
    //   1610: aload #22
    //   1612: invokevirtual toString : ()Ljava/lang/String;
    //   1615: astore #21
    //   1617: aload #21
    //   1619: invokevirtual getClass : ()Ljava/lang/Class;
    //   1622: pop
    //   1623: aload #28
    //   1625: getfield c : Ljava/util/Set;
    //   1628: astore #28
    //   1630: aload #17
    //   1632: invokevirtual getClass : ()Ljava/lang/Class;
    //   1635: pop
    //   1636: aload #28
    //   1638: invokevirtual getClass : ()Ljava/lang/Class;
    //   1641: pop
    //   1642: aload #28
    //   1644: invokeinterface iterator : ()Ljava/util/Iterator;
    //   1649: astore #29
    //   1651: aload #29
    //   1653: invokeinterface hasNext : ()Z
    //   1658: ifeq -> 1709
    //   1661: new d82
    //   1664: dup
    //   1665: aload #29
    //   1667: invokeinterface next : ()Ljava/lang/Object;
    //   1672: checkcast java/lang/String
    //   1675: aload #21
    //   1677: invokespecial <init> : (Ljava/lang/String;Ljava/lang/String;)V
    //   1680: astore #28
    //   1682: aload #17
    //   1684: getfield a : Leh1;
    //   1687: iconst_0
    //   1688: iconst_1
    //   1689: new dy
    //   1692: dup
    //   1693: bipush #9
    //   1695: aload #17
    //   1697: aload #28
    //   1699: invokespecial <init> : (ILjava/lang/Object;Ljava/lang/Object;)V
    //   1702: invokestatic N : (Leh1;ZZLwc0;)Ljava/lang/Object;
    //   1705: pop
    //   1706: goto -> 1651
    //   1709: iload #11
    //   1711: ifne -> 1779
    //   1714: aload #23
    //   1716: invokevirtual t : ()Lt72;
    //   1719: astore #17
    //   1721: aload #22
    //   1723: invokevirtual toString : ()Ljava/lang/String;
    //   1726: astore #21
    //   1728: aload #21
    //   1730: invokevirtual getClass : ()Ljava/lang/Class;
    //   1733: pop
    //   1734: new s72
    //   1737: dup
    //   1738: aload #24
    //   1740: aload #21
    //   1742: invokespecial <init> : (Ljava/lang/String;Ljava/lang/String;)V
    //   1745: astore #21
    //   1747: aload #17
    //   1749: invokevirtual getClass : ()Ljava/lang/Class;
    //   1752: pop
    //   1753: aload #17
    //   1755: getfield a : Leh1;
    //   1758: iconst_0
    //   1759: iconst_1
    //   1760: new dy
    //   1763: dup
    //   1764: iconst_5
    //   1765: aload #17
    //   1767: aload #21
    //   1769: invokespecial <init> : (ILjava/lang/Object;Ljava/lang/Object;)V
    //   1772: invokestatic N : (Leh1;ZZLwc0;)Ljava/lang/Object;
    //   1775: pop
    //   1776: goto -> 1779
    //   1779: goto -> 1082
    //   1782: aload_0
    //   1783: iconst_1
    //   1784: putfield g : Z
    //   1787: iload #10
    //   1789: ireturn
    // Exception table:
    //   from	to	target	type
    //   487	540	666	finally
    //   540	565	666	finally
    //   568	573	666	finally
  }
}


/* Location:              C:\Users\Kevin\Downloads\dex-tools-v2.4\dex-tools-v2.4\musicolet-dex2jar.jar!\p40.class
 * Java compiler version: 6 (50.0)
 * JD-Core Version:       1.1.3
 */