import android.content.Context;
import androidx.work.impl.WorkDatabase;
import java.util.ArrayList;

public final class q82 {
  public final y72 a;
  
  public final Context b;
  
  public final String c;
  
  public final n2 d;
  
  public final ip e;
  
  public final fb0 f;
  
  public final ma1 g;
  
  public final WorkDatabase h;
  
  public final c82 i;
  
  public final gy j;
  
  public final ArrayList k;
  
  public final String l;
  
  public final xj0 m;
  
  public q82(rv1 paramrv1) {
    y72 y721 = (y72)paramrv1.h;
    this.a = y721;
    this.b = (Context)paramrv1.b;
    String str = y721.a;
    this.c = str;
    this.d = (n2)paramrv1.e;
    ip ip1 = (ip)paramrv1.c;
    this.e = ip1;
    this.f = ip1.d;
    this.g = (ma1)paramrv1.f;
    WorkDatabase workDatabase = (WorkDatabase)paramrv1.g;
    this.h = workDatabase;
    this.i = workDatabase.v();
    this.j = workDatabase.q();
    ArrayList arrayList = (ArrayList)paramrv1.i;
    this.k = arrayList;
    this.l = x41.n(x41.q("Work [ id=", str, ", tags={ "), nm.p0(arrayList, ",", null, null, null, 62), " } ]");
    this.m = g92.a();
  }
  
  public static final Object a(q82 paramq82, ds paramds) {
    // Byte code:
    //   0: aload_0
    //   1: getfield l : Ljava/lang/String;
    //   4: astore #5
    //   6: aload_0
    //   7: getfield c : Ljava/lang/String;
    //   10: astore #14
    //   12: aload_0
    //   13: getfield d : Ln2;
    //   16: astore #8
    //   18: aload_0
    //   19: getfield h : Landroidx/work/impl/WorkDatabase;
    //   22: astore #9
    //   24: aload_0
    //   25: getfield e : Lip;
    //   28: astore #12
    //   30: aload #12
    //   32: getfield m : Lhp2;
    //   35: astore #7
    //   37: aload_0
    //   38: getfield a : Ly72;
    //   41: astore #16
    //   43: aload_1
    //   44: instanceof p82
    //   47: ifeq -> 81
    //   50: aload_1
    //   51: checkcast p82
    //   54: astore #6
    //   56: aload #6
    //   58: getfield h : I
    //   61: istore_2
    //   62: iload_2
    //   63: ldc -2147483648
    //   65: iand
    //   66: ifeq -> 81
    //   69: aload #6
    //   71: iload_2
    //   72: ldc -2147483648
    //   74: iadd
    //   75: putfield h : I
    //   78: goto -> 92
    //   81: new p82
    //   84: dup
    //   85: aload_0
    //   86: aload_1
    //   87: invokespecial <init> : (Lq82;Lds;)V
    //   90: astore #6
    //   92: aload #6
    //   94: getfield f : Ljava/lang/Object;
    //   97: astore_1
    //   98: aload #6
    //   100: getfield h : I
    //   103: istore_2
    //   104: iload_2
    //   105: ifeq -> 140
    //   108: iload_2
    //   109: iconst_1
    //   110: if_icmpne -> 133
    //   113: aload_1
    //   114: invokestatic r0 : (Ljava/lang/Object;)V
    //   117: aload_1
    //   118: astore_0
    //   119: goto -> 1027
    //   122: astore_0
    //   123: goto -> 1060
    //   126: astore_0
    //   127: aload #5
    //   129: astore_1
    //   130: goto -> 1118
    //   133: ldc 'call to 'resume' before 'invoke' with coroutine'
    //   135: invokestatic f : (Ljava/lang/String;)V
    //   138: aconst_null
    //   139: areturn
    //   140: aload_1
    //   141: invokestatic r0 : (Ljava/lang/Object;)V
    //   144: aload #12
    //   146: getfield e : Lj30;
    //   149: astore #13
    //   151: aload #7
    //   153: invokevirtual getClass : ()Ljava/lang/Class;
    //   156: pop
    //   157: invokestatic N : ()Z
    //   160: istore #4
    //   162: aload #16
    //   164: getfield x : Ljava/lang/String;
    //   167: astore #11
    //   169: aload #16
    //   171: getfield c : Ljava/lang/String;
    //   174: astore #10
    //   176: aload #16
    //   178: getfield d : Ljava/lang/String;
    //   181: astore #15
    //   183: aload #16
    //   185: getfield e : Ldu;
    //   188: astore #7
    //   190: iload #4
    //   192: ifeq -> 340
    //   195: aload #11
    //   197: ifnull -> 340
    //   200: aload #16
    //   202: invokevirtual hashCode : ()I
    //   205: istore_2
    //   206: getstatic android/os/Build$VERSION.SDK_INT : I
    //   209: bipush #29
    //   211: if_icmplt -> 226
    //   214: aload #11
    //   216: invokestatic p0 : (Ljava/lang/String;)Ljava/lang/String;
    //   219: iload_2
    //   220: invokestatic a : (Ljava/lang/String;I)V
    //   223: goto -> 340
    //   226: aload #11
    //   228: invokestatic p0 : (Ljava/lang/String;)Ljava/lang/String;
    //   231: astore #18
    //   233: getstatic com/google/android/material/textview/pJx/ybWnIKHovcRr.Heyxk : Ljava/lang/String;
    //   236: astore #17
    //   238: getstatic ui0.l : Ljava/lang/reflect/Method;
    //   241: ifnonnull -> 295
    //   244: getstatic java/lang/Long.TYPE : Ljava/lang/Class;
    //   247: astore_1
    //   248: ldc android/os/Trace
    //   250: aload #17
    //   252: iconst_3
    //   253: anewarray java/lang/Class
    //   256: dup
    //   257: iconst_0
    //   258: aload_1
    //   259: aastore
    //   260: dup
    //   261: iconst_1
    //   262: ldc java/lang/String
    //   264: aastore
    //   265: dup
    //   266: iconst_2
    //   267: getstatic java/lang/Integer.TYPE : Ljava/lang/Class;
    //   270: aastore
    //   271: invokevirtual getMethod : (Ljava/lang/String;[Ljava/lang/Class;)Ljava/lang/reflect/Method;
    //   274: putstatic ui0.l : Ljava/lang/reflect/Method;
    //   277: goto -> 295
    //   280: astore_1
    //   281: goto -> 331
    //   284: goto -> 331
    //   287: astore_1
    //   288: goto -> 284
    //   291: astore_1
    //   292: goto -> 331
    //   295: getstatic ui0.l : Ljava/lang/reflect/Method;
    //   298: aconst_null
    //   299: iconst_3
    //   300: anewarray java/lang/Object
    //   303: dup
    //   304: iconst_0
    //   305: getstatic ui0.j : J
    //   308: invokestatic valueOf : (J)Ljava/lang/Long;
    //   311: aastore
    //   312: dup
    //   313: iconst_1
    //   314: aload #18
    //   316: aastore
    //   317: dup
    //   318: iconst_2
    //   319: iload_2
    //   320: invokestatic valueOf : (I)Ljava/lang/Integer;
    //   323: aastore
    //   324: invokevirtual invoke : (Ljava/lang/Object;[Ljava/lang/Object;)Ljava/lang/Object;
    //   327: pop
    //   328: goto -> 340
    //   331: aload #17
    //   333: aload_1
    //   334: invokestatic F : (Ljava/lang/String;Ljava/lang/Exception;)V
    //   337: goto -> 340
    //   340: iconst_0
    //   341: istore_2
    //   342: aload #9
    //   344: new h82
    //   347: dup
    //   348: aload_0
    //   349: iconst_0
    //   350: invokespecial <init> : (Lq82;I)V
    //   353: invokevirtual n : (Ljava/util/concurrent/Callable;)Ljava/lang/Object;
    //   356: checkcast java/lang/Boolean
    //   359: invokevirtual booleanValue : ()Z
    //   362: ifeq -> 376
    //   365: new l82
    //   368: dup
    //   369: invokespecial <init> : ()V
    //   372: astore_0
    //   373: goto -> 1225
    //   376: aload #16
    //   378: invokevirtual c : ()Z
    //   381: ifeq -> 390
    //   384: aload #7
    //   386: astore_1
    //   387: goto -> 685
    //   390: aload #12
    //   392: getfield f : Lvs2;
    //   395: invokevirtual getClass : ()Ljava/lang/Class;
    //   398: pop
    //   399: aload #15
    //   401: invokevirtual getClass : ()Ljava/lang/Class;
    //   404: pop
    //   405: getstatic ei0.a : Ljava/lang/String;
    //   408: astore_1
    //   409: aload #15
    //   411: invokestatic forName : (Ljava/lang/String;)Ljava/lang/Class;
    //   414: astore_1
    //   415: aload_1
    //   416: aconst_null
    //   417: invokevirtual getDeclaredConstructor : ([Ljava/lang/Class;)Ljava/lang/reflect/Constructor;
    //   420: aconst_null
    //   421: invokevirtual newInstance : ([Ljava/lang/Object;)Ljava/lang/Object;
    //   424: astore_1
    //   425: aload_1
    //   426: invokevirtual getClass : ()Ljava/lang/Class;
    //   429: pop
    //   430: aload_1
    //   431: checkcast androidx/work/OverwritingInputMerger
    //   434: astore_1
    //   435: goto -> 463
    //   438: astore_1
    //   439: goto -> 443
    //   442: astore_1
    //   443: invokestatic h : ()Lqp0;
    //   446: getstatic ei0.a : Ljava/lang/String;
    //   449: ldc_w 'Trouble instantiating '
    //   452: aload #15
    //   454: invokevirtual concat : (Ljava/lang/String;)Ljava/lang/String;
    //   457: aload_1
    //   458: invokevirtual g : (Ljava/lang/String;Ljava/lang/String;Ljava/lang/Throwable;)V
    //   461: aconst_null
    //   462: astore_1
    //   463: aload_1
    //   464: ifnonnull -> 497
    //   467: getstatic s82.a : Ljava/lang/String;
    //   470: astore_0
    //   471: invokestatic h : ()Lqp0;
    //   474: aload_0
    //   475: ldc_w 'Could not create Input Merger '
    //   478: aload #15
    //   480: invokevirtual concat : (Ljava/lang/String;)Ljava/lang/String;
    //   483: invokevirtual f : (Ljava/lang/String;Ljava/lang/String;)V
    //   486: new j82
    //   489: dup
    //   490: invokespecial <init> : ()V
    //   493: astore_0
    //   494: goto -> 1225
    //   497: aload #7
    //   499: invokestatic E : (Ljava/lang/Object;)Ljava/util/List;
    //   502: astore #7
    //   504: aload_0
    //   505: getfield i : Lc82;
    //   508: astore_1
    //   509: aload_1
    //   510: invokevirtual getClass : ()Ljava/lang/Class;
    //   513: pop
    //   514: aload #14
    //   516: invokevirtual getClass : ()Ljava/lang/Class;
    //   519: pop
    //   520: aload_1
    //   521: getfield a : Leh1;
    //   524: iconst_1
    //   525: iconst_0
    //   526: new ey
    //   529: dup
    //   530: aload #14
    //   532: bipush #13
    //   534: invokespecial <init> : (Ljava/lang/String;I)V
    //   537: invokestatic N : (Leh1;ZZLwc0;)Ljava/lang/Object;
    //   540: checkcast java/util/List
    //   543: astore #15
    //   545: aload #15
    //   547: invokevirtual getClass : ()Ljava/lang/Class;
    //   550: pop
    //   551: aload #7
    //   553: invokeinterface size : ()I
    //   558: istore_3
    //   559: new java/util/ArrayList
    //   562: dup
    //   563: aload #15
    //   565: invokeinterface size : ()I
    //   570: iload_3
    //   571: iadd
    //   572: invokespecial <init> : (I)V
    //   575: astore_1
    //   576: aload_1
    //   577: aload #7
    //   579: invokevirtual addAll : (Ljava/util/Collection;)Z
    //   582: pop
    //   583: aload_1
    //   584: aload #15
    //   586: invokevirtual addAll : (Ljava/util/Collection;)Z
    //   589: pop
    //   590: new c4
    //   593: dup
    //   594: iconst_1
    //   595: invokespecial <init> : (I)V
    //   598: astore #7
    //   600: new java/util/LinkedHashMap
    //   603: dup
    //   604: invokespecial <init> : ()V
    //   607: astore #15
    //   609: aload_1
    //   610: invokevirtual size : ()I
    //   613: istore_3
    //   614: iload_2
    //   615: iload_3
    //   616: if_icmpge -> 660
    //   619: aload_1
    //   620: iload_2
    //   621: invokevirtual get : (I)Ljava/lang/Object;
    //   624: astore #16
    //   626: iinc #2, 1
    //   629: aload #16
    //   631: checkcast du
    //   634: getfield a : Ljava/util/HashMap;
    //   637: invokestatic unmodifiableMap : (Ljava/util/Map;)Ljava/util/Map;
    //   640: astore #16
    //   642: aload #16
    //   644: invokevirtual getClass : ()Ljava/lang/Class;
    //   647: pop
    //   648: aload #15
    //   650: aload #16
    //   652: invokeinterface putAll : (Ljava/util/Map;)V
    //   657: goto -> 614
    //   660: aload #7
    //   662: aload #15
    //   664: invokevirtual c : (Ljava/util/HashMap;)V
    //   667: new du
    //   670: dup
    //   671: aload #7
    //   673: getfield a : Ljava/util/LinkedHashMap;
    //   676: invokespecial <init> : (Ljava/util/LinkedHashMap;)V
    //   679: astore_1
    //   680: aload_1
    //   681: invokestatic n0 : (Ldu;)[B
    //   684: pop
    //   685: aload #14
    //   687: invokestatic fromString : (Ljava/lang/String;)Ljava/util/UUID;
    //   690: astore #14
    //   692: aload_0
    //   693: getfield k : Ljava/util/ArrayList;
    //   696: astore #16
    //   698: aload #12
    //   700: getfield a : Ljava/util/concurrent/ExecutorService;
    //   703: astore #15
    //   705: aload #12
    //   707: getfield b : Lyw;
    //   710: astore #12
    //   712: new v72
    //   715: astore #7
    //   717: new m72
    //   720: dup
    //   721: aload #9
    //   723: aload_0
    //   724: getfield g : Lma1;
    //   727: aload #8
    //   729: invokespecial <init> : (Landroidx/work/impl/WorkDatabase;Lma1;Ln2;)V
    //   732: astore #7
    //   734: new java/lang/Object
    //   737: dup
    //   738: invokespecial <init> : ()V
    //   741: astore #17
    //   743: aload #17
    //   745: aload #14
    //   747: putfield a : Ljava/util/UUID;
    //   750: aload #17
    //   752: aload_1
    //   753: putfield b : Ldu;
    //   756: new java/util/HashSet
    //   759: dup
    //   760: aload #16
    //   762: invokespecial <init> : (Ljava/util/Collection;)V
    //   765: pop
    //   766: aload #17
    //   768: aload #15
    //   770: putfield c : Ljava/util/concurrent/ExecutorService;
    //   773: aload #17
    //   775: aload #12
    //   777: putfield d : Los;
    //   780: aload #17
    //   782: aload #8
    //   784: putfield e : Ln2;
    //   787: aload #17
    //   789: aload #13
    //   791: putfield f : Lj30;
    //   794: aload #13
    //   796: aload_0
    //   797: getfield b : Landroid/content/Context;
    //   800: aload #10
    //   802: aload #17
    //   804: invokevirtual a : (Landroid/content/Context;Ljava/lang/String;Landroidx/work/WorkerParameters;)Loo0;
    //   807: astore_1
    //   808: aload_1
    //   809: iconst_1
    //   810: putfield d : Z
    //   813: aload #6
    //   815: getfield c : Los;
    //   818: astore #10
    //   820: aload #10
    //   822: invokevirtual getClass : ()Ljava/lang/Class;
    //   825: pop
    //   826: aload #10
    //   828: getstatic vs2.g : Lvs2;
    //   831: invokeinterface l : (Lns;)Lms;
    //   836: astore #10
    //   838: aload #10
    //   840: invokevirtual getClass : ()Ljava/lang/Class;
    //   843: pop
    //   844: aload #10
    //   846: checkcast vj0
    //   849: astore #12
    //   851: new i82
    //   854: dup
    //   855: aload_1
    //   856: iload #4
    //   858: aload #11
    //   860: aload_0
    //   861: invokespecial <init> : (Loo0;ZLjava/lang/String;Lq82;)V
    //   864: astore #10
    //   866: aload #12
    //   868: checkcast dk0
    //   871: astore #11
    //   873: aload #11
    //   875: iconst_1
    //   876: new aj0
    //   879: dup
    //   880: aload #10
    //   882: invokespecial <init> : (Lwc0;)V
    //   885: invokevirtual M : (ZLyj0;)Lk00;
    //   888: pop
    //   889: aload #9
    //   891: new h82
    //   894: dup
    //   895: aload_0
    //   896: iconst_1
    //   897: invokespecial <init> : (Lq82;I)V
    //   900: invokevirtual n : (Ljava/util/concurrent/Callable;)Ljava/lang/Object;
    //   903: astore #9
    //   905: aload #9
    //   907: invokevirtual getClass : ()Ljava/lang/Class;
    //   910: pop
    //   911: aload #9
    //   913: checkcast java/lang/Boolean
    //   916: invokevirtual booleanValue : ()Z
    //   919: ifne -> 933
    //   922: new l82
    //   925: dup
    //   926: invokespecial <init> : ()V
    //   929: astore_0
    //   930: goto -> 1225
    //   933: aload #11
    //   935: invokevirtual N : ()Z
    //   938: ifeq -> 952
    //   941: new l82
    //   944: dup
    //   945: invokespecial <init> : ()V
    //   948: astore_0
    //   949: goto -> 1225
    //   952: aload #8
    //   954: getfield g : Ljava/lang/Object;
    //   957: checkcast ki1
    //   960: astore #8
    //   962: aload #8
    //   964: invokevirtual getClass : ()Ljava/lang/Class;
    //   967: pop
    //   968: aload #8
    //   970: invokestatic t : (Ljava/util/concurrent/Executor;)Lrs;
    //   973: astore #9
    //   975: new ek
    //   978: astore #8
    //   980: aload #8
    //   982: aload_0
    //   983: aload_1
    //   984: aload #7
    //   986: aconst_null
    //   987: bipush #8
    //   989: invokespecial <init> : (Ljava/lang/Object;Ljava/lang/Object;Ljava/lang/Object;Lcs;I)V
    //   992: aload #6
    //   994: iconst_1
    //   995: putfield h : I
    //   998: aload #9
    //   1000: aload #8
    //   1002: aload #6
    //   1004: invokestatic l0 : (Los;Lad0;Lcs;)Ljava/lang/Object;
    //   1007: astore_1
    //   1008: getstatic ys.b : Lys;
    //   1011: astore #6
    //   1013: aload_1
    //   1014: astore_0
    //   1015: aload_1
    //   1016: aload #6
    //   1018: if_acmpne -> 1027
    //   1021: aload #6
    //   1023: astore_0
    //   1024: goto -> 1225
    //   1027: aload_0
    //   1028: checkcast no0
    //   1031: astore_1
    //   1032: new k82
    //   1035: astore_0
    //   1036: aload_1
    //   1037: invokevirtual getClass : ()Ljava/lang/Class;
    //   1040: pop
    //   1041: aload_0
    //   1042: aload_1
    //   1043: invokespecial <init> : (Lno0;)V
    //   1046: goto -> 1024
    //   1049: astore_0
    //   1050: goto -> 1060
    //   1053: astore_0
    //   1054: aload #5
    //   1056: astore_1
    //   1057: goto -> 1118
    //   1060: getstatic s82.a : Ljava/lang/String;
    //   1063: astore #7
    //   1065: invokestatic h : ()Lqp0;
    //   1068: astore_1
    //   1069: new java/lang/StringBuilder
    //   1072: dup
    //   1073: invokespecial <init> : ()V
    //   1076: astore #6
    //   1078: aload #6
    //   1080: aload #5
    //   1082: invokevirtual append : (Ljava/lang/String;)Ljava/lang/StringBuilder;
    //   1085: pop
    //   1086: aload #6
    //   1088: ldc_w ' failed because it threw an exception/error'
    //   1091: invokevirtual append : (Ljava/lang/String;)Ljava/lang/StringBuilder;
    //   1094: pop
    //   1095: aload_1
    //   1096: aload #7
    //   1098: aload #6
    //   1100: invokevirtual toString : ()Ljava/lang/String;
    //   1103: aload_0
    //   1104: invokevirtual g : (Ljava/lang/String;Ljava/lang/String;Ljava/lang/Throwable;)V
    //   1107: new j82
    //   1110: dup
    //   1111: invokespecial <init> : ()V
    //   1114: astore_0
    //   1115: goto -> 1225
    //   1118: getstatic s82.a : Ljava/lang/String;
    //   1121: astore_1
    //   1122: invokestatic h : ()Lqp0;
    //   1125: astore #6
    //   1127: new java/lang/StringBuilder
    //   1130: dup
    //   1131: invokespecial <init> : ()V
    //   1134: astore #7
    //   1136: aload #7
    //   1138: aload #5
    //   1140: invokevirtual append : (Ljava/lang/String;)Ljava/lang/StringBuilder;
    //   1143: pop
    //   1144: aload #7
    //   1146: ldc_w ' was cancelled'
    //   1149: invokevirtual append : (Ljava/lang/String;)Ljava/lang/StringBuilder;
    //   1152: pop
    //   1153: aload #7
    //   1155: invokevirtual toString : ()Ljava/lang/String;
    //   1158: astore #5
    //   1160: aload #6
    //   1162: getfield b : I
    //   1165: iconst_4
    //   1166: if_icmpgt -> 1177
    //   1169: aload_1
    //   1170: aload #5
    //   1172: aload_0
    //   1173: invokestatic i : (Ljava/lang/String;Ljava/lang/String;Ljava/lang/Throwable;)I
    //   1176: pop
    //   1177: aload_0
    //   1178: athrow
    //   1179: astore_0
    //   1180: getstatic s82.a : Ljava/lang/String;
    //   1183: astore #5
    //   1185: invokestatic h : ()Lqp0;
    //   1188: astore_0
    //   1189: new java/lang/StringBuilder
    //   1192: dup
    //   1193: ldc_w 'Could not create Worker '
    //   1196: invokespecial <init> : (Ljava/lang/String;)V
    //   1199: astore_1
    //   1200: aload_1
    //   1201: aload #10
    //   1203: invokevirtual append : (Ljava/lang/String;)Ljava/lang/StringBuilder;
    //   1206: pop
    //   1207: aload_0
    //   1208: aload #5
    //   1210: aload_1
    //   1211: invokevirtual toString : ()Ljava/lang/String;
    //   1214: invokevirtual f : (Ljava/lang/String;Ljava/lang/String;)V
    //   1217: new j82
    //   1220: dup
    //   1221: invokespecial <init> : ()V
    //   1224: astore_0
    //   1225: aload_0
    //   1226: areturn
    // Exception table:
    //   from	to	target	type
    //   113	117	126	java/util/concurrent/CancellationException
    //   113	117	122	finally
    //   238	244	291	java/lang/Exception
    //   244	248	287	java/lang/Exception
    //   248	277	280	java/lang/Exception
    //   295	328	280	java/lang/Exception
    //   409	415	442	java/lang/Exception
    //   415	435	438	java/lang/Exception
    //   794	808	1179	finally
    //   975	1008	1053	java/util/concurrent/CancellationException
    //   975	1008	1049	finally
    //   1027	1046	1053	java/util/concurrent/CancellationException
    //   1027	1046	1049	finally
  }
  
  public final void b(int paramInt) {
    c82 c821 = this.i;
    o72 o72 = o72.b;
    String str = this.c;
    c821.f(o72, str);
    this.f.getClass();
    c821.e(System.currentTimeMillis(), str);
    c821.d(str, this.a.v);
    c821.c(-1L, str);
    c821.g(str, paramInt);
  }
  
  public final void c() {
    this.f.getClass();
    long l = System.currentTimeMillis();
    c82 c821 = this.i;
    String str = this.c;
    c821.e(l, str);
    c821.f(o72.b, str);
    eh1 eh1 = c821.a;
    ((Number)zo2.N(eh1, false, true, new ey(str, 11))).intValue();
    c821.d(str, this.a.v);
    zo2.N(eh1, false, true, new ey(str, 12));
    c821.c(-1L, str);
  }
  
  public final void d(no0 paramno0) {
    paramno0.getClass();
    String str = this.c;
    ArrayList arrayList = om.i0((Object[])new String[] { str });
    while (true) {
      boolean bool = arrayList.isEmpty();
      c82 c821 = this.i;
      if (!bool) {
        String str1 = (String)tm.m0(arrayList);
        if (c821.a(str1) != o72.h)
          c821.f(o72.f, str1); 
        arrayList.addAll(this.j.a(str1));
        continue;
      } 
      du du = ((ko0)paramno0).a;
      du.getClass();
      c821.d(str, this.a.v);
      zo2.N(c821.a, false, true, new dy(7, du, str));
      return;
    } 
  }
}


/* Location:              C:\Users\Kevin\Downloads\dex-tools-v2.4\dex-tools-v2.4\musicolet-dex2jar.jar!\q82.class
 * Java compiler version: 6 (50.0)
 * JD-Core Version:       1.1.3
 */