import java.util.HashMap;
import java.util.Locale;

public final class sw {
  public HashMap a;
  
  public HashMap b;
  
  public static HashMap a() {
    return new HashMap<Object, Object>(7);
  }
  
  public final String[] b(Locale paramLocale, String paramString1, String paramString2) {
    // Byte code:
    //   0: aload_0
    //   1: monitorenter
    //   2: aconst_null
    //   3: astore #8
    //   5: aload_1
    //   6: ifnull -> 394
    //   9: aload_2
    //   10: ifnull -> 394
    //   13: aload_0
    //   14: getfield a : Ljava/util/HashMap;
    //   17: aload_1
    //   18: invokevirtual get : (Ljava/lang/Object;)Ljava/lang/Object;
    //   21: checkcast java/util/Map
    //   24: astore #7
    //   26: aload #7
    //   28: astore #6
    //   30: aload #7
    //   32: ifnonnull -> 62
    //   35: aload_0
    //   36: getfield a : Ljava/util/HashMap;
    //   39: astore #7
    //   41: invokestatic a : ()Ljava/util/HashMap;
    //   44: astore #6
    //   46: aload #7
    //   48: aload_1
    //   49: aload #6
    //   51: invokevirtual put : (Ljava/lang/Object;Ljava/lang/Object;)Ljava/lang/Object;
    //   54: pop
    //   55: goto -> 62
    //   58: astore_1
    //   59: goto -> 390
    //   62: aload #6
    //   64: aload_2
    //   65: invokeinterface get : (Ljava/lang/Object;)Ljava/lang/Object;
    //   70: checkcast java/util/Map
    //   73: astore #9
    //   75: aload #9
    //   77: astore #7
    //   79: aload #9
    //   81: ifnonnull -> 374
    //   84: invokestatic a : ()Ljava/util/HashMap;
    //   87: astore #9
    //   89: aload #6
    //   91: aload_2
    //   92: aload #9
    //   94: invokeinterface put : (Ljava/lang/Object;Ljava/lang/Object;)Ljava/lang/Object;
    //   99: pop
    //   100: getstatic java/util/Locale.ENGLISH : Ljava/util/Locale;
    //   103: invokestatic a : (Ljava/util/Locale;)Ljava/text/DateFormatSymbols;
    //   106: invokevirtual getZoneStrings : ()[[Ljava/lang/String;
    //   109: astore #7
    //   111: aload #7
    //   113: arraylength
    //   114: istore #5
    //   116: iconst_0
    //   117: istore #4
    //   119: iload #4
    //   121: iload #5
    //   123: if_icmpge -> 165
    //   126: aload #7
    //   128: iload #4
    //   130: aaload
    //   131: astore #6
    //   133: aload #6
    //   135: ifnull -> 159
    //   138: aload #6
    //   140: arraylength
    //   141: iconst_5
    //   142: if_icmplt -> 159
    //   145: aload_2
    //   146: aload #6
    //   148: iconst_0
    //   149: aaload
    //   150: invokevirtual equals : (Ljava/lang/Object;)Z
    //   153: ifeq -> 159
    //   156: goto -> 168
    //   159: iinc #4, 1
    //   162: goto -> 119
    //   165: aconst_null
    //   166: astore #6
    //   168: aload_1
    //   169: invokestatic a : (Ljava/util/Locale;)Ljava/text/DateFormatSymbols;
    //   172: invokevirtual getZoneStrings : ()[[Ljava/lang/String;
    //   175: astore #7
    //   177: aload #7
    //   179: arraylength
    //   180: istore #5
    //   182: iconst_0
    //   183: istore #4
    //   185: aload #8
    //   187: astore_1
    //   188: iload #4
    //   190: iload #5
    //   192: if_icmpge -> 230
    //   195: aload #7
    //   197: iload #4
    //   199: aaload
    //   200: astore_1
    //   201: aload_1
    //   202: ifnull -> 224
    //   205: aload_1
    //   206: arraylength
    //   207: iconst_5
    //   208: if_icmplt -> 224
    //   211: aload_2
    //   212: aload_1
    //   213: iconst_0
    //   214: aaload
    //   215: invokevirtual equals : (Ljava/lang/Object;)Z
    //   218: ifeq -> 224
    //   221: goto -> 230
    //   224: iinc #4, 1
    //   227: goto -> 185
    //   230: aload #9
    //   232: astore #7
    //   234: aload #6
    //   236: ifnull -> 374
    //   239: aload #9
    //   241: astore #7
    //   243: aload_1
    //   244: ifnull -> 374
    //   247: aload #9
    //   249: aload #6
    //   251: iconst_2
    //   252: aaload
    //   253: iconst_2
    //   254: anewarray java/lang/String
    //   257: dup
    //   258: iconst_0
    //   259: aload_1
    //   260: iconst_2
    //   261: aaload
    //   262: aastore
    //   263: dup
    //   264: iconst_1
    //   265: aload_1
    //   266: iconst_1
    //   267: aaload
    //   268: aastore
    //   269: invokevirtual put : (Ljava/lang/Object;Ljava/lang/Object;)Ljava/lang/Object;
    //   272: pop
    //   273: aload #6
    //   275: iconst_2
    //   276: aaload
    //   277: aload #6
    //   279: iconst_4
    //   280: aaload
    //   281: invokevirtual equals : (Ljava/lang/Object;)Z
    //   284: ifeq -> 344
    //   287: new java/lang/StringBuilder
    //   290: astore_2
    //   291: aload_2
    //   292: invokespecial <init> : ()V
    //   295: aload_2
    //   296: aload #6
    //   298: iconst_4
    //   299: aaload
    //   300: invokevirtual append : (Ljava/lang/String;)Ljava/lang/StringBuilder;
    //   303: pop
    //   304: aload_2
    //   305: ldc '-Summer'
    //   307: invokevirtual append : (Ljava/lang/String;)Ljava/lang/StringBuilder;
    //   310: pop
    //   311: aload #9
    //   313: aload_2
    //   314: invokevirtual toString : ()Ljava/lang/String;
    //   317: iconst_2
    //   318: anewarray java/lang/String
    //   321: dup
    //   322: iconst_0
    //   323: aload_1
    //   324: iconst_4
    //   325: aaload
    //   326: aastore
    //   327: dup
    //   328: iconst_1
    //   329: aload_1
    //   330: iconst_3
    //   331: aaload
    //   332: aastore
    //   333: invokevirtual put : (Ljava/lang/Object;Ljava/lang/Object;)Ljava/lang/Object;
    //   336: pop
    //   337: aload #9
    //   339: astore #7
    //   341: goto -> 374
    //   344: aload #9
    //   346: aload #6
    //   348: iconst_4
    //   349: aaload
    //   350: iconst_2
    //   351: anewarray java/lang/String
    //   354: dup
    //   355: iconst_0
    //   356: aload_1
    //   357: iconst_4
    //   358: aaload
    //   359: aastore
    //   360: dup
    //   361: iconst_1
    //   362: aload_1
    //   363: iconst_3
    //   364: aaload
    //   365: aastore
    //   366: invokevirtual put : (Ljava/lang/Object;Ljava/lang/Object;)Ljava/lang/Object;
    //   369: pop
    //   370: aload #9
    //   372: astore #7
    //   374: aload #7
    //   376: aload_3
    //   377: invokeinterface get : (Ljava/lang/Object;)Ljava/lang/Object;
    //   382: checkcast [Ljava/lang/String;
    //   385: astore_1
    //   386: aload_0
    //   387: monitorexit
    //   388: aload_1
    //   389: areturn
    //   390: aload_0
    //   391: monitorexit
    //   392: aload_1
    //   393: athrow
    //   394: aload_0
    //   395: monitorexit
    //   396: aconst_null
    //   397: areturn
    // Exception table:
    //   from	to	target	type
    //   13	26	58	finally
    //   35	55	58	finally
    //   62	75	58	finally
    //   84	116	58	finally
    //   138	156	58	finally
    //   168	182	58	finally
    //   205	221	58	finally
    //   247	337	58	finally
    //   344	370	58	finally
    //   374	386	58	finally
    //   390	392	58	finally
  }
  
  public final String[] c(Locale paramLocale, String paramString1, String paramString2, boolean paramBoolean) {
    // Byte code:
    //   0: aload_0
    //   1: monitorenter
    //   2: aconst_null
    //   3: astore #8
    //   5: aload_1
    //   6: ifnull -> 331
    //   9: aload_2
    //   10: ifnull -> 331
    //   13: aload_2
    //   14: astore_3
    //   15: aload_2
    //   16: ldc 'Etc/'
    //   18: invokevirtual startsWith : (Ljava/lang/String;)Z
    //   21: ifeq -> 37
    //   24: aload_2
    //   25: iconst_4
    //   26: invokevirtual substring : (I)Ljava/lang/String;
    //   29: astore_3
    //   30: goto -> 37
    //   33: astore_1
    //   34: goto -> 327
    //   37: aload_0
    //   38: getfield b : Ljava/util/HashMap;
    //   41: aload_1
    //   42: invokevirtual get : (Ljava/lang/Object;)Ljava/lang/Object;
    //   45: checkcast java/util/Map
    //   48: astore #7
    //   50: aload #7
    //   52: astore_2
    //   53: aload #7
    //   55: ifnonnull -> 76
    //   58: aload_0
    //   59: getfield b : Ljava/util/HashMap;
    //   62: astore #7
    //   64: invokestatic a : ()Ljava/util/HashMap;
    //   67: astore_2
    //   68: aload #7
    //   70: aload_1
    //   71: aload_2
    //   72: invokevirtual put : (Ljava/lang/Object;Ljava/lang/Object;)Ljava/lang/Object;
    //   75: pop
    //   76: aload_2
    //   77: aload_3
    //   78: invokeinterface get : (Ljava/lang/Object;)Ljava/lang/Object;
    //   83: checkcast java/util/Map
    //   86: astore #9
    //   88: aload #9
    //   90: astore #7
    //   92: aload #9
    //   94: ifnonnull -> 307
    //   97: invokestatic a : ()Ljava/util/HashMap;
    //   100: astore #9
    //   102: aload_2
    //   103: aload_3
    //   104: aload #9
    //   106: invokeinterface put : (Ljava/lang/Object;Ljava/lang/Object;)Ljava/lang/Object;
    //   111: pop
    //   112: getstatic java/util/Locale.ENGLISH : Ljava/util/Locale;
    //   115: invokestatic a : (Ljava/util/Locale;)Ljava/text/DateFormatSymbols;
    //   118: invokevirtual getZoneStrings : ()[[Ljava/lang/String;
    //   121: astore #7
    //   123: aload #7
    //   125: arraylength
    //   126: istore #6
    //   128: iconst_0
    //   129: istore #5
    //   131: iload #5
    //   133: iload #6
    //   135: if_icmpge -> 173
    //   138: aload #7
    //   140: iload #5
    //   142: aaload
    //   143: astore_2
    //   144: aload_2
    //   145: ifnull -> 167
    //   148: aload_2
    //   149: arraylength
    //   150: iconst_5
    //   151: if_icmplt -> 167
    //   154: aload_3
    //   155: aload_2
    //   156: iconst_0
    //   157: aaload
    //   158: invokevirtual equals : (Ljava/lang/Object;)Z
    //   161: ifeq -> 167
    //   164: goto -> 175
    //   167: iinc #5, 1
    //   170: goto -> 131
    //   173: aconst_null
    //   174: astore_2
    //   175: aload_1
    //   176: invokestatic a : (Ljava/util/Locale;)Ljava/text/DateFormatSymbols;
    //   179: invokevirtual getZoneStrings : ()[[Ljava/lang/String;
    //   182: astore #7
    //   184: aload #7
    //   186: arraylength
    //   187: istore #6
    //   189: iconst_0
    //   190: istore #5
    //   192: aload #8
    //   194: astore_1
    //   195: iload #5
    //   197: iload #6
    //   199: if_icmpge -> 237
    //   202: aload #7
    //   204: iload #5
    //   206: aaload
    //   207: astore_1
    //   208: aload_1
    //   209: ifnull -> 231
    //   212: aload_1
    //   213: arraylength
    //   214: iconst_5
    //   215: if_icmplt -> 231
    //   218: aload_3
    //   219: aload_1
    //   220: iconst_0
    //   221: aaload
    //   222: invokevirtual equals : (Ljava/lang/Object;)Z
    //   225: ifeq -> 231
    //   228: goto -> 237
    //   231: iinc #5, 1
    //   234: goto -> 192
    //   237: aload #9
    //   239: astore #7
    //   241: aload_2
    //   242: ifnull -> 307
    //   245: aload #9
    //   247: astore #7
    //   249: aload_1
    //   250: ifnull -> 307
    //   253: aload #9
    //   255: getstatic java/lang/Boolean.TRUE : Ljava/lang/Boolean;
    //   258: iconst_2
    //   259: anewarray java/lang/String
    //   262: dup
    //   263: iconst_0
    //   264: aload_1
    //   265: iconst_2
    //   266: aaload
    //   267: aastore
    //   268: dup
    //   269: iconst_1
    //   270: aload_1
    //   271: iconst_1
    //   272: aaload
    //   273: aastore
    //   274: invokevirtual put : (Ljava/lang/Object;Ljava/lang/Object;)Ljava/lang/Object;
    //   277: pop
    //   278: aload #9
    //   280: getstatic java/lang/Boolean.FALSE : Ljava/lang/Boolean;
    //   283: iconst_2
    //   284: anewarray java/lang/String
    //   287: dup
    //   288: iconst_0
    //   289: aload_1
    //   290: iconst_4
    //   291: aaload
    //   292: aastore
    //   293: dup
    //   294: iconst_1
    //   295: aload_1
    //   296: iconst_3
    //   297: aaload
    //   298: aastore
    //   299: invokevirtual put : (Ljava/lang/Object;Ljava/lang/Object;)Ljava/lang/Object;
    //   302: pop
    //   303: aload #9
    //   305: astore #7
    //   307: aload #7
    //   309: iload #4
    //   311: invokestatic valueOf : (Z)Ljava/lang/Boolean;
    //   314: invokeinterface get : (Ljava/lang/Object;)Ljava/lang/Object;
    //   319: checkcast [Ljava/lang/String;
    //   322: astore_1
    //   323: aload_0
    //   324: monitorexit
    //   325: aload_1
    //   326: areturn
    //   327: aload_0
    //   328: monitorexit
    //   329: aload_1
    //   330: athrow
    //   331: aload_0
    //   332: monitorexit
    //   333: aconst_null
    //   334: areturn
    // Exception table:
    //   from	to	target	type
    //   15	30	33	finally
    //   37	50	33	finally
    //   58	76	33	finally
    //   76	88	33	finally
    //   97	128	33	finally
    //   148	164	33	finally
    //   175	189	33	finally
    //   212	228	33	finally
    //   253	303	33	finally
    //   307	323	33	finally
    //   327	329	33	finally
  }
}


/* Location:              C:\Users\Kevin\Downloads\dex-tools-v2.4\dex-tools-v2.4\musicolet-dex2jar.jar!\sw.class
 * Java compiler version: 6 (50.0)
 * JD-Core Version:       1.1.3
 */