import android.os.Binder;
import android.os.IBinder;
import android.os.IInterface;
import android.os.Parcel;

public abstract class y92 extends Binder implements IInterface {
  public final int e;
  
  public y92(String paramString, int paramInt) {
    attachInterface(this, paramString);
  }
  
  public final IBinder asBinder() {
    int i = this.e;
    return (IBinder)this;
  }
  
  public boolean o0(int paramInt, Parcel paramParcel1, Parcel paramParcel2) {
    return false;
  }
  
  public final boolean onTransact(int paramInt1, Parcel paramParcel1, Parcel paramParcel2, int paramInt2) {
    // Byte code:
    //   0: aload_0
    //   1: getfield e : I
    //   4: istore #5
    //   6: iconst_0
    //   7: istore #7
    //   9: iconst_0
    //   10: istore #11
    //   12: iconst_0
    //   13: istore #9
    //   15: iconst_0
    //   16: istore #8
    //   18: iconst_1
    //   19: istore #6
    //   21: iconst_1
    //   22: istore #10
    //   24: iload #5
    //   26: tableswitch default -> 60, 0 -> 1333, 1 -> 1074, 2 -> 965, 3 -> 924, 4 -> 879
    //   60: iload_1
    //   61: ldc 16777215
    //   63: if_icmple -> 84
    //   66: aload_0
    //   67: iload_1
    //   68: aload_2
    //   69: aload_3
    //   70: iload #4
    //   72: invokespecial onTransact : (ILandroid/os/Parcel;Landroid/os/Parcel;I)Z
    //   75: ifeq -> 92
    //   78: iconst_1
    //   79: istore #6
    //   81: goto -> 876
    //   84: aload_2
    //   85: aload_0
    //   86: invokevirtual getInterfaceDescriptor : ()Ljava/lang/String;
    //   89: invokevirtual enforceInterface : (Ljava/lang/String;)V
    //   92: aload_0
    //   93: checkcast ze2
    //   96: astore #13
    //   98: aload #13
    //   100: getfield f : Lnt1;
    //   103: astore #12
    //   105: aload #13
    //   107: getfield g : Ldg2;
    //   110: astore_3
    //   111: iload_1
    //   112: tableswitch default -> 176, 2 -> 799, 3 -> 745, 4 -> 673, 5 -> 619, 6 -> 549, 7 -> 513, 8 -> 471, 9 -> 403, 10 -> 361, 11 -> 319, 12 -> 251, 13 -> 183
    //   176: iload #8
    //   178: istore #6
    //   180: goto -> 876
    //   183: getstatic android/os/Bundle.CREATOR : Landroid/os/Parcelable$Creator;
    //   186: astore_3
    //   187: aload_2
    //   188: invokestatic a : (Landroid/os/Parcel;)Landroid/os/Parcelable;
    //   191: checkcast android/os/Bundle
    //   194: astore_3
    //   195: aload_2
    //   196: invokestatic b : (Landroid/os/Parcel;)V
    //   199: aload #13
    //   201: getfield h : I
    //   204: tableswitch default -> 224, 3 -> 233
    //   224: aload #13
    //   226: aload_3
    //   227: invokevirtual s0 : (Landroid/os/Bundle;)V
    //   230: goto -> 78
    //   233: aload #13
    //   235: aload_3
    //   236: invokevirtual s0 : (Landroid/os/Bundle;)V
    //   239: aload #13
    //   241: getfield f : Lnt1;
    //   244: aconst_null
    //   245: invokevirtual d : (Ljava/lang/Object;)V
    //   248: goto -> 78
    //   251: getstatic android/os/Bundle.CREATOR : Landroid/os/Parcelable$Creator;
    //   254: astore_3
    //   255: aload_2
    //   256: invokestatic a : (Landroid/os/Parcel;)Landroid/os/Parcelable;
    //   259: checkcast android/os/Bundle
    //   262: astore_3
    //   263: aload_2
    //   264: invokestatic b : (Landroid/os/Parcel;)V
    //   267: aload #13
    //   269: getfield h : I
    //   272: tableswitch default -> 292, 2 -> 301
    //   292: aload #13
    //   294: aload_3
    //   295: invokevirtual r0 : (Landroid/os/Bundle;)V
    //   298: goto -> 78
    //   301: aload #13
    //   303: aload_3
    //   304: invokevirtual r0 : (Landroid/os/Bundle;)V
    //   307: aload #13
    //   309: getfield f : Lnt1;
    //   312: aconst_null
    //   313: invokevirtual d : (Ljava/lang/Object;)V
    //   316: goto -> 78
    //   319: getstatic android/os/Bundle.CREATOR : Landroid/os/Parcelable$Creator;
    //   322: astore #13
    //   324: aload_2
    //   325: invokestatic a : (Landroid/os/Parcel;)Landroid/os/Parcelable;
    //   328: checkcast android/os/Bundle
    //   331: astore #13
    //   333: aload_2
    //   334: invokestatic b : (Landroid/os/Parcel;)V
    //   337: aload_3
    //   338: getfield b : Lmd2;
    //   341: aload #12
    //   343: invokevirtual d : (Lnt1;)V
    //   346: getstatic dg2.c : Lf1;
    //   349: ldc 'onCompleteInstallForAppUpdate'
    //   351: iconst_0
    //   352: anewarray java/lang/Object
    //   355: invokevirtual e : (Ljava/lang/String;[Ljava/lang/Object;)V
    //   358: goto -> 78
    //   361: getstatic android/os/Bundle.CREATOR : Landroid/os/Parcelable$Creator;
    //   364: astore #13
    //   366: aload_2
    //   367: invokestatic a : (Landroid/os/Parcel;)Landroid/os/Parcelable;
    //   370: checkcast android/os/Bundle
    //   373: astore #13
    //   375: aload_2
    //   376: invokestatic b : (Landroid/os/Parcel;)V
    //   379: aload_3
    //   380: getfield b : Lmd2;
    //   383: aload #12
    //   385: invokevirtual d : (Lnt1;)V
    //   388: getstatic dg2.c : Lf1;
    //   391: ldc 'onGetSplitsForAppUpdate'
    //   393: iconst_0
    //   394: anewarray java/lang/Object
    //   397: invokevirtual e : (Ljava/lang/String;[Ljava/lang/Object;)V
    //   400: goto -> 78
    //   403: getstatic android/os/Bundle.CREATOR : Landroid/os/Parcelable$Creator;
    //   406: astore_3
    //   407: aload_2
    //   408: invokestatic a : (Landroid/os/Parcel;)Landroid/os/Parcelable;
    //   411: checkcast android/os/Bundle
    //   414: astore_3
    //   415: aload_2
    //   416: invokestatic b : (Landroid/os/Parcel;)V
    //   419: aload #13
    //   421: getfield h : I
    //   424: tableswitch default -> 444, 1 -> 453
    //   444: aload #13
    //   446: aload_3
    //   447: invokevirtual q0 : (Landroid/os/Bundle;)V
    //   450: goto -> 78
    //   453: aload #13
    //   455: aload_3
    //   456: invokevirtual q0 : (Landroid/os/Bundle;)V
    //   459: aload #13
    //   461: getfield f : Lnt1;
    //   464: aconst_null
    //   465: invokevirtual d : (Ljava/lang/Object;)V
    //   468: goto -> 78
    //   471: getstatic android/os/Bundle.CREATOR : Landroid/os/Parcelable$Creator;
    //   474: astore #13
    //   476: aload_2
    //   477: invokestatic a : (Landroid/os/Parcel;)Landroid/os/Parcelable;
    //   480: checkcast android/os/Bundle
    //   483: astore #13
    //   485: aload_2
    //   486: invokestatic b : (Landroid/os/Parcel;)V
    //   489: aload_3
    //   490: getfield b : Lmd2;
    //   493: aload #12
    //   495: invokevirtual d : (Lnt1;)V
    //   498: getstatic dg2.c : Lf1;
    //   501: ldc 'onDeferredUninstall'
    //   503: iconst_0
    //   504: anewarray java/lang/Object
    //   507: invokevirtual e : (Ljava/lang/String;[Ljava/lang/Object;)V
    //   510: goto -> 78
    //   513: aload_2
    //   514: getstatic android/os/Bundle.CREATOR : Landroid/os/Parcelable$Creator;
    //   517: invokevirtual createTypedArrayList : (Landroid/os/Parcelable$Creator;)Ljava/util/ArrayList;
    //   520: pop
    //   521: aload_2
    //   522: invokestatic b : (Landroid/os/Parcel;)V
    //   525: aload_3
    //   526: getfield b : Lmd2;
    //   529: aload #12
    //   531: invokevirtual d : (Lnt1;)V
    //   534: getstatic dg2.c : Lf1;
    //   537: ldc 'onGetSessionStates'
    //   539: iconst_0
    //   540: anewarray java/lang/Object
    //   543: invokevirtual e : (Ljava/lang/String;[Ljava/lang/Object;)V
    //   546: goto -> 78
    //   549: getstatic android/os/Bundle.CREATOR : Landroid/os/Parcelable$Creator;
    //   552: astore #13
    //   554: aload_2
    //   555: invokestatic a : (Landroid/os/Parcel;)Landroid/os/Parcelable;
    //   558: checkcast android/os/Bundle
    //   561: astore #13
    //   563: aload_2
    //   564: invokestatic b : (Landroid/os/Parcel;)V
    //   567: aload_3
    //   568: getfield b : Lmd2;
    //   571: aload #12
    //   573: invokevirtual d : (Lnt1;)V
    //   576: aload #13
    //   578: ldc 'error_code'
    //   580: invokevirtual getInt : (Ljava/lang/String;)I
    //   583: istore_1
    //   584: getstatic dg2.c : Lf1;
    //   587: ldc 'onError(%d)'
    //   589: iconst_1
    //   590: anewarray java/lang/Object
    //   593: dup
    //   594: iconst_0
    //   595: iload_1
    //   596: invokestatic valueOf : (I)Ljava/lang/Integer;
    //   599: aastore
    //   600: invokevirtual b : (Ljava/lang/String;[Ljava/lang/Object;)V
    //   603: aload #12
    //   605: new jo1
    //   608: dup
    //   609: iload_1
    //   610: invokespecial <init> : (I)V
    //   613: invokevirtual c : (Ljava/lang/Exception;)V
    //   616: goto -> 78
    //   619: aload_2
    //   620: invokevirtual readInt : ()I
    //   623: istore_1
    //   624: getstatic android/os/Bundle.CREATOR : Landroid/os/Parcelable$Creator;
    //   627: astore #13
    //   629: aload_2
    //   630: invokestatic a : (Landroid/os/Parcel;)Landroid/os/Parcelable;
    //   633: checkcast android/os/Bundle
    //   636: astore #13
    //   638: aload_2
    //   639: invokestatic b : (Landroid/os/Parcel;)V
    //   642: aload_3
    //   643: getfield b : Lmd2;
    //   646: aload #12
    //   648: invokevirtual d : (Lnt1;)V
    //   651: getstatic dg2.c : Lf1;
    //   654: ldc 'onGetSession(%d)'
    //   656: iconst_1
    //   657: anewarray java/lang/Object
    //   660: dup
    //   661: iconst_0
    //   662: iload_1
    //   663: invokestatic valueOf : (I)Ljava/lang/Integer;
    //   666: aastore
    //   667: invokevirtual e : (Ljava/lang/String;[Ljava/lang/Object;)V
    //   670: goto -> 78
    //   673: aload_2
    //   674: invokevirtual readInt : ()I
    //   677: istore_1
    //   678: getstatic android/os/Bundle.CREATOR : Landroid/os/Parcelable$Creator;
    //   681: astore_3
    //   682: aload_2
    //   683: invokestatic a : (Landroid/os/Parcel;)Landroid/os/Parcelable;
    //   686: checkcast android/os/Bundle
    //   689: astore_3
    //   690: aload_2
    //   691: invokestatic b : (Landroid/os/Parcel;)V
    //   694: aload #13
    //   696: getfield h : I
    //   699: tableswitch default -> 716, 0 -> 726
    //   716: aload #13
    //   718: iload_1
    //   719: aload_3
    //   720: invokevirtual p0 : (ILandroid/os/Bundle;)V
    //   723: goto -> 78
    //   726: aload #13
    //   728: iload_1
    //   729: aload_3
    //   730: invokevirtual p0 : (ILandroid/os/Bundle;)V
    //   733: aload #13
    //   735: getfield f : Lnt1;
    //   738: aconst_null
    //   739: invokevirtual d : (Ljava/lang/Object;)V
    //   742: goto -> 78
    //   745: aload_2
    //   746: invokevirtual readInt : ()I
    //   749: istore_1
    //   750: getstatic android/os/Bundle.CREATOR : Landroid/os/Parcelable$Creator;
    //   753: astore #13
    //   755: aload_2
    //   756: invokestatic a : (Landroid/os/Parcel;)Landroid/os/Parcelable;
    //   759: checkcast android/os/Bundle
    //   762: astore #13
    //   764: aload_2
    //   765: invokestatic b : (Landroid/os/Parcel;)V
    //   768: aload_3
    //   769: getfield b : Lmd2;
    //   772: aload #12
    //   774: invokevirtual d : (Lnt1;)V
    //   777: getstatic dg2.c : Lf1;
    //   780: ldc 'onCompleteInstall(%d)'
    //   782: iconst_1
    //   783: anewarray java/lang/Object
    //   786: dup
    //   787: iconst_0
    //   788: iload_1
    //   789: invokestatic valueOf : (I)Ljava/lang/Integer;
    //   792: aastore
    //   793: invokevirtual e : (Ljava/lang/String;[Ljava/lang/Object;)V
    //   796: goto -> 78
    //   799: aload_2
    //   800: invokevirtual readInt : ()I
    //   803: istore_1
    //   804: getstatic android/os/Bundle.CREATOR : Landroid/os/Parcelable$Creator;
    //   807: astore_3
    //   808: aload_2
    //   809: invokestatic a : (Landroid/os/Parcel;)Landroid/os/Parcelable;
    //   812: checkcast android/os/Bundle
    //   815: astore_3
    //   816: aload_2
    //   817: invokestatic b : (Landroid/os/Parcel;)V
    //   820: aload #13
    //   822: getfield h : I
    //   825: tableswitch default -> 844, 4 -> 854
    //   844: aload #13
    //   846: iload_1
    //   847: aload_3
    //   848: invokevirtual t0 : (ILandroid/os/Bundle;)V
    //   851: goto -> 78
    //   854: aload #13
    //   856: iload_1
    //   857: aload_3
    //   858: invokevirtual t0 : (ILandroid/os/Bundle;)V
    //   861: aload #13
    //   863: getfield f : Lnt1;
    //   866: iload_1
    //   867: invokestatic valueOf : (I)Ljava/lang/Integer;
    //   870: invokevirtual d : (Ljava/lang/Object;)V
    //   873: goto -> 78
    //   876: iload #6
    //   878: ireturn
    //   879: iload_1
    //   880: ldc 16777215
    //   882: if_icmple -> 904
    //   885: aload_0
    //   886: iload_1
    //   887: aload_2
    //   888: aload_3
    //   889: iload #4
    //   891: invokespecial onTransact : (ILandroid/os/Parcel;Landroid/os/Parcel;I)Z
    //   894: ifeq -> 912
    //   897: iload #10
    //   899: istore #6
    //   901: goto -> 921
    //   904: aload_2
    //   905: aload_0
    //   906: invokevirtual getInterfaceDescriptor : ()Ljava/lang/String;
    //   909: invokevirtual enforceInterface : (Ljava/lang/String;)V
    //   912: aload_0
    //   913: iload_1
    //   914: aload_2
    //   915: aload_3
    //   916: invokevirtual o0 : (ILandroid/os/Parcel;Landroid/os/Parcel;)Z
    //   919: istore #6
    //   921: iload #6
    //   923: ireturn
    //   924: iload_1
    //   925: ldc 16777215
    //   927: if_icmple -> 945
    //   930: aload_0
    //   931: iload_1
    //   932: aload_2
    //   933: aload_3
    //   934: iload #4
    //   936: invokespecial onTransact : (ILandroid/os/Parcel;Landroid/os/Parcel;I)Z
    //   939: ifeq -> 953
    //   942: goto -> 962
    //   945: aload_2
    //   946: aload_0
    //   947: invokevirtual getInterfaceDescriptor : ()Ljava/lang/String;
    //   950: invokevirtual enforceInterface : (Ljava/lang/String;)V
    //   953: aload_0
    //   954: iload_1
    //   955: aload_2
    //   956: aload_3
    //   957: invokevirtual o0 : (ILandroid/os/Parcel;Landroid/os/Parcel;)Z
    //   960: istore #6
    //   962: iload #6
    //   964: ireturn
    //   965: iload_1
    //   966: ldc 16777215
    //   968: if_icmple -> 985
    //   971: aload_0
    //   972: iload_1
    //   973: aload_2
    //   974: aload_3
    //   975: iload #4
    //   977: invokespecial onTransact : (ILandroid/os/Parcel;Landroid/os/Parcel;I)Z
    //   980: istore #6
    //   982: goto -> 996
    //   985: aload_2
    //   986: aload_0
    //   987: invokevirtual getInterfaceDescriptor : ()Ljava/lang/String;
    //   990: invokevirtual enforceInterface : (Ljava/lang/String;)V
    //   993: iconst_0
    //   994: istore #6
    //   996: iload #6
    //   998: ifeq -> 1007
    //   1001: iconst_1
    //   1002: istore #6
    //   1004: goto -> 1071
    //   1007: aload_0
    //   1008: checkcast ui2
    //   1011: astore_3
    //   1012: iload #7
    //   1014: istore #6
    //   1016: iload_1
    //   1017: iconst_1
    //   1018: if_icmpne -> 1071
    //   1021: aload_2
    //   1022: invokevirtual readInt : ()I
    //   1025: istore_1
    //   1026: getstatic bf2.a : I
    //   1029: istore #4
    //   1031: aload_2
    //   1032: invokevirtual dataAvail : ()I
    //   1035: istore #4
    //   1037: iload #4
    //   1039: ifgt -> 1056
    //   1042: aload_3
    //   1043: getfield f : Ltp2;
    //   1046: iload_1
    //   1047: invokestatic valueOf : (I)Ljava/lang/Integer;
    //   1050: invokevirtual a : (Ljava/lang/Object;)V
    //   1053: goto -> 1001
    //   1056: new android/os/BadParcelableException
    //   1059: dup
    //   1060: ldc 'Parcel data not fully consumed, unread size: '
    //   1062: iload #4
    //   1064: invokestatic i : (Ljava/lang/String;I)Ljava/lang/String;
    //   1067: invokespecial <init> : (Ljava/lang/String;)V
    //   1070: athrow
    //   1071: iload #6
    //   1073: ireturn
    //   1074: iload_1
    //   1075: ldc 16777215
    //   1077: if_icmple -> 1098
    //   1080: aload_0
    //   1081: iload_1
    //   1082: aload_2
    //   1083: aload_3
    //   1084: iload #4
    //   1086: invokespecial onTransact : (ILandroid/os/Parcel;Landroid/os/Parcel;I)Z
    //   1089: ifeq -> 1106
    //   1092: iconst_1
    //   1093: istore #6
    //   1095: goto -> 1330
    //   1098: aload_2
    //   1099: aload_0
    //   1100: invokevirtual getInterfaceDescriptor : ()Ljava/lang/String;
    //   1103: invokevirtual enforceInterface : (Ljava/lang/String;)V
    //   1106: aload_0
    //   1107: checkcast cb2
    //   1110: astore #12
    //   1112: iload_1
    //   1113: tableswitch default -> 1156, 3 -> 1295, 4 -> 1276, 5 -> 1156, 6 -> 1257, 7 -> 1226, 8 -> 1182, 9 -> 1163
    //   1156: iload #11
    //   1158: istore #6
    //   1160: goto -> 1330
    //   1163: aload_2
    //   1164: getstatic kb2.CREATOR : Landroid/os/Parcelable$Creator;
    //   1167: invokestatic a : (Landroid/os/Parcel;Landroid/os/Parcelable$Creator;)Landroid/os/Parcelable;
    //   1170: checkcast kb2
    //   1173: astore #12
    //   1175: aload_2
    //   1176: invokestatic b : (Landroid/os/Parcel;)V
    //   1179: goto -> 1323
    //   1182: aload_2
    //   1183: getstatic nb2.CREATOR : Landroid/os/Parcelable$Creator;
    //   1186: invokestatic a : (Landroid/os/Parcel;Landroid/os/Parcelable$Creator;)Landroid/os/Parcelable;
    //   1189: checkcast nb2
    //   1192: astore #13
    //   1194: aload_2
    //   1195: invokestatic b : (Landroid/os/Parcel;)V
    //   1198: new vi2
    //   1201: dup
    //   1202: aload #12
    //   1204: aload #13
    //   1206: bipush #19
    //   1208: iconst_0
    //   1209: invokespecial <init> : (Ljava/lang/Object;Ljava/lang/Object;IZ)V
    //   1212: astore_2
    //   1213: aload #12
    //   1215: getfield g : Landroid/os/Handler;
    //   1218: aload_2
    //   1219: invokevirtual post : (Ljava/lang/Runnable;)Z
    //   1222: pop
    //   1223: goto -> 1323
    //   1226: aload_2
    //   1227: getstatic com/google/android/gms/common/api/Status.CREATOR : Landroid/os/Parcelable$Creator;
    //   1230: invokestatic a : (Landroid/os/Parcel;Landroid/os/Parcelable$Creator;)Landroid/os/Parcelable;
    //   1233: checkcast com/google/android/gms/common/api/Status
    //   1236: astore #12
    //   1238: aload_2
    //   1239: getstatic com/google/android/gms/auth/api/signin/GoogleSignInAccount.CREATOR : Landroid/os/Parcelable$Creator;
    //   1242: invokestatic a : (Landroid/os/Parcel;Landroid/os/Parcelable$Creator;)Landroid/os/Parcelable;
    //   1245: checkcast com/google/android/gms/auth/api/signin/GoogleSignInAccount
    //   1248: astore #12
    //   1250: aload_2
    //   1251: invokestatic b : (Landroid/os/Parcel;)V
    //   1254: goto -> 1323
    //   1257: aload_2
    //   1258: getstatic com/google/android/gms/common/api/Status.CREATOR : Landroid/os/Parcelable$Creator;
    //   1261: invokestatic a : (Landroid/os/Parcel;Landroid/os/Parcelable$Creator;)Landroid/os/Parcelable;
    //   1264: checkcast com/google/android/gms/common/api/Status
    //   1267: astore #12
    //   1269: aload_2
    //   1270: invokestatic b : (Landroid/os/Parcel;)V
    //   1273: goto -> 1323
    //   1276: aload_2
    //   1277: getstatic com/google/android/gms/common/api/Status.CREATOR : Landroid/os/Parcelable$Creator;
    //   1280: invokestatic a : (Landroid/os/Parcel;Landroid/os/Parcelable$Creator;)Landroid/os/Parcelable;
    //   1283: checkcast com/google/android/gms/common/api/Status
    //   1286: astore #12
    //   1288: aload_2
    //   1289: invokestatic b : (Landroid/os/Parcel;)V
    //   1292: goto -> 1323
    //   1295: aload_2
    //   1296: getstatic sp.CREATOR : Landroid/os/Parcelable$Creator;
    //   1299: invokestatic a : (Landroid/os/Parcel;Landroid/os/Parcelable$Creator;)Landroid/os/Parcelable;
    //   1302: checkcast sp
    //   1305: astore #12
    //   1307: aload_2
    //   1308: getstatic ma2.CREATOR : Landroid/os/Parcelable$Creator;
    //   1311: invokestatic a : (Landroid/os/Parcel;Landroid/os/Parcelable$Creator;)Landroid/os/Parcelable;
    //   1314: checkcast ma2
    //   1317: astore #12
    //   1319: aload_2
    //   1320: invokestatic b : (Landroid/os/Parcel;)V
    //   1323: aload_3
    //   1324: invokevirtual writeNoException : ()V
    //   1327: goto -> 1092
    //   1330: iload #6
    //   1332: ireturn
    //   1333: iload_1
    //   1334: ldc 16777215
    //   1336: if_icmple -> 1357
    //   1339: aload_0
    //   1340: iload_1
    //   1341: aload_2
    //   1342: aload_3
    //   1343: iload #4
    //   1345: invokespecial onTransact : (ILandroid/os/Parcel;Landroid/os/Parcel;I)Z
    //   1348: ifeq -> 1365
    //   1351: iconst_1
    //   1352: istore #6
    //   1354: goto -> 1695
    //   1357: aload_2
    //   1358: aload_0
    //   1359: invokevirtual getInterfaceDescriptor : ()Ljava/lang/String;
    //   1362: invokevirtual enforceInterface : (Ljava/lang/String;)V
    //   1365: aload_0
    //   1366: checkcast r92
    //   1369: astore #13
    //   1371: iload #9
    //   1373: istore #6
    //   1375: iload_1
    //   1376: iconst_2
    //   1377: if_icmpne -> 1695
    //   1380: getstatic android/os/Bundle.CREATOR : Landroid/os/Parcelable$Creator;
    //   1383: astore_3
    //   1384: getstatic z92.a : I
    //   1387: istore_1
    //   1388: aload_2
    //   1389: invokevirtual readInt : ()I
    //   1392: ifne -> 1400
    //   1395: aconst_null
    //   1396: astore_3
    //   1397: goto -> 1411
    //   1400: aload_3
    //   1401: aload_2
    //   1402: invokeinterface createFromParcel : (Landroid/os/Parcel;)Ljava/lang/Object;
    //   1407: checkcast android/os/Parcelable
    //   1410: astore_3
    //   1411: aload_3
    //   1412: checkcast android/os/Bundle
    //   1415: astore_3
    //   1416: aload_2
    //   1417: invokevirtual dataAvail : ()I
    //   1420: istore_1
    //   1421: iload_1
    //   1422: ifgt -> 1681
    //   1425: aload #13
    //   1427: getfield h : Ls92;
    //   1430: astore_2
    //   1431: aload_2
    //   1432: getfield e : Lk92;
    //   1435: astore #14
    //   1437: aload #13
    //   1439: getfield g : Lnt1;
    //   1442: astore #12
    //   1444: aload #14
    //   1446: getfield f : Ljava/lang/Object;
    //   1449: astore #15
    //   1451: aload #15
    //   1453: monitorenter
    //   1454: aload #14
    //   1456: getfield e : Ljava/util/HashSet;
    //   1459: aload #12
    //   1461: invokevirtual remove : (Ljava/lang/Object;)Z
    //   1464: pop
    //   1465: aload #15
    //   1467: monitorexit
    //   1468: new j92
    //   1471: dup
    //   1472: aload #14
    //   1474: invokespecial <init> : (Lk92;)V
    //   1477: astore #15
    //   1479: aload #14
    //   1481: invokevirtual a : ()Landroid/os/Handler;
    //   1484: aload #15
    //   1486: invokevirtual post : (Ljava/lang/Runnable;)Z
    //   1489: pop
    //   1490: aload #13
    //   1492: getfield f : Lha2;
    //   1495: ldc_w 'onRequestIntegrityToken'
    //   1498: iconst_0
    //   1499: anewarray java/lang/Object
    //   1502: invokevirtual a : (Ljava/lang/String;[Ljava/lang/Object;)V
    //   1505: aload_2
    //   1506: getfield d : Lzb0;
    //   1509: invokevirtual getClass : ()Ljava/lang/Class;
    //   1512: pop
    //   1513: aload_3
    //   1514: ldc_w 'error'
    //   1517: invokevirtual getInt : (Ljava/lang/String;)I
    //   1520: istore_1
    //   1521: iload_1
    //   1522: ifne -> 1530
    //   1525: aconst_null
    //   1526: astore_2
    //   1527: goto -> 1548
    //   1530: aload_3
    //   1531: ldc_w 'is.error.remediable'
    //   1534: invokevirtual getBoolean : (Ljava/lang/String;)Z
    //   1537: pop
    //   1538: new ni0
    //   1541: dup
    //   1542: iload_1
    //   1543: aconst_null
    //   1544: invokespecial <init> : (ILjava/lang/Exception;)V
    //   1547: astore_2
    //   1548: aload_2
    //   1549: ifnull -> 1561
    //   1552: aload #12
    //   1554: aload_2
    //   1555: invokevirtual c : (Ljava/lang/Exception;)V
    //   1558: goto -> 1351
    //   1561: aload_3
    //   1562: ldc_w 'token'
    //   1565: invokevirtual getString : (Ljava/lang/String;)Ljava/lang/String;
    //   1568: astore_2
    //   1569: aload_2
    //   1570: ifnonnull -> 1591
    //   1573: aload #12
    //   1575: new ni0
    //   1578: dup
    //   1579: bipush #-100
    //   1581: aconst_null
    //   1582: invokespecial <init> : (ILjava/lang/Exception;)V
    //   1585: invokevirtual c : (Ljava/lang/Exception;)V
    //   1588: goto -> 1351
    //   1591: aload_3
    //   1592: ldc_w 'request.token.sid'
    //   1595: invokevirtual getLong : (Ljava/lang/String;)J
    //   1598: pop2
    //   1599: invokestatic myUid : ()I
    //   1602: istore_1
    //   1603: invokestatic myPid : ()I
    //   1606: istore #4
    //   1608: new java/lang/StringBuilder
    //   1611: dup
    //   1612: ldc_w 'UID: ['
    //   1615: invokespecial <init> : (Ljava/lang/String;)V
    //   1618: astore_3
    //   1619: aload_3
    //   1620: iload_1
    //   1621: invokevirtual append : (I)Ljava/lang/StringBuilder;
    //   1624: pop
    //   1625: aload_3
    //   1626: ldc_w ']  PID: ['
    //   1629: invokevirtual append : (Ljava/lang/String;)Ljava/lang/StringBuilder;
    //   1632: pop
    //   1633: aload_3
    //   1634: iload #4
    //   1636: invokevirtual append : (I)Ljava/lang/StringBuilder;
    //   1639: pop
    //   1640: aload_3
    //   1641: ldc_w '] '
    //   1644: invokevirtual append : (Ljava/lang/String;)Ljava/lang/StringBuilder;
    //   1647: pop
    //   1648: aload_3
    //   1649: invokevirtual toString : ()Ljava/lang/String;
    //   1652: ldc_w 'IntegrityDialogWrapper'
    //   1655: invokevirtual concat : (Ljava/lang/String;)Ljava/lang/String;
    //   1658: pop
    //   1659: aload #12
    //   1661: new v92
    //   1664: dup
    //   1665: aload_2
    //   1666: invokespecial <init> : (Ljava/lang/String;)V
    //   1669: invokevirtual d : (Ljava/lang/Object;)V
    //   1672: goto -> 1351
    //   1675: astore_2
    //   1676: aload #15
    //   1678: monitorexit
    //   1679: aload_2
    //   1680: athrow
    //   1681: new android/os/BadParcelableException
    //   1684: dup
    //   1685: ldc 'Parcel data not fully consumed, unread size: '
    //   1687: iload_1
    //   1688: invokestatic i : (Ljava/lang/String;I)Ljava/lang/String;
    //   1691: invokespecial <init> : (Ljava/lang/String;)V
    //   1694: athrow
    //   1695: iload #6
    //   1697: ireturn
    // Exception table:
    //   from	to	target	type
    //   1454	1468	1675	finally
    //   1676	1679	1675	finally
  }
}


/* Location:              C:\Users\Kevin\Downloads\dex-tools-v2.4\dex-tools-v2.4\musicolet-dex2jar.jar!\y92.class
 * Java compiler version: 6 (50.0)
 * JD-Core Version:       1.1.3
 */