import java.util.Objects;

public final class yi1 implements Runnable {
  public final int b;
  
  public Object c;
  
  public yi1(cb2 paramcb2) {
    Objects.requireNonNull(paramcb2);
    this.c = paramcb2;
  }
  
  public yi1(oa2 paramoa2, mi2 parammi2) {
    Objects.requireNonNull(paramoa2);
    this.c = parammi2;
  }
  
  public final void run() {
    // Byte code:
    //   0: aload_0
    //   1: getfield b : I
    //   4: istore_2
    //   5: iconst_0
    //   6: istore_3
    //   7: iload_2
    //   8: tableswitch default -> 132, 0 -> 2811, 1 -> 2800, 2 -> 2727, 3 -> 2715, 4 -> 2621, 5 -> 2594, 6 -> 2582, 7 -> 2455, 8 -> 2302, 9 -> 2290, 10 -> 2269, 11 -> 2245, 12 -> 2217, 13 -> 1613, 14 -> 1602, 15 -> 1546, 16 -> 1518, 17 -> 1516, 18 -> 1462, 19 -> 1418, 20 -> 1387, 21 -> 852, 22 -> 767, 23 -> 709, 24 -> 647, 25 -> 635, 26 -> 162
    //   132: aload_0
    //   133: getfield c : Ljava/lang/Object;
    //   136: checkcast io1
    //   139: getfield a : Lpz0;
    //   142: invokevirtual f : ()V
    //   145: goto -> 161
    //   148: astore #12
    //   150: getstatic com/pavelsikun/seekbarpreference/lu/FgdLmmRfTxSFKI.KlWaFyNfeHV : Ljava/lang/String;
    //   153: ldc 'Failed to cleanup splitcompat storage'
    //   155: aload #12
    //   157: invokestatic e : (Ljava/lang/String;Ljava/lang/String;Ljava/lang/Throwable;)I
    //   160: pop
    //   161: return
    //   162: aload_0
    //   163: getfield c : Ljava/lang/Object;
    //   166: checkcast zq2
    //   169: astore #13
    //   171: aload #13
    //   173: getfield b : Landroid/content/SharedPreferences;
    //   176: astore #14
    //   178: aload #13
    //   180: getfield f : Ljava/util/HashSet;
    //   183: astore #15
    //   185: aload #15
    //   187: invokevirtual isEmpty : ()Z
    //   190: ifeq -> 196
    //   193: goto -> 634
    //   196: aload #13
    //   198: getfield g : Ljava/util/HashSet;
    //   201: astore #12
    //   203: iconst_1
    //   204: aload #12
    //   206: aload #15
    //   208: invokevirtual equals : (Ljava/lang/Object;)Z
    //   211: if_icmpeq -> 222
    //   214: ldc2_w 86400000
    //   217: lstore #5
    //   219: goto -> 227
    //   222: ldc2_w 172800000
    //   225: lstore #5
    //   227: invokestatic currentTimeMillis : ()J
    //   230: lstore #7
    //   232: aload #13
    //   234: getfield h : J
    //   237: lstore #9
    //   239: lload #9
    //   241: lconst_0
    //   242: lcmp
    //   243: ifeq -> 257
    //   246: lload #7
    //   248: lload #9
    //   250: lsub
    //   251: lload #5
    //   253: lcmp
    //   254: iflt -> 634
    //   257: getstatic zq2.i : Lrp0;
    //   260: ldc 'Upload the feature usage report.'
    //   262: iconst_0
    //   263: anewarray java/lang/Object
    //   266: invokevirtual b : (Ljava/lang/String;[Ljava/lang/Object;)V
    //   269: invokestatic l : ()Leq2;
    //   272: astore #16
    //   274: getstatic zq2.j : Ljava/lang/String;
    //   277: astore #17
    //   279: aload #16
    //   281: invokevirtual a : ()V
    //   284: aload #16
    //   286: getfield c : Lpv2;
    //   289: checkcast fq2
    //   292: aload #17
    //   294: invokevirtual n : (Ljava/lang/String;)V
    //   297: aload #13
    //   299: getfield c : Ljava/lang/String;
    //   302: astore #17
    //   304: aload #16
    //   306: invokevirtual a : ()V
    //   309: aload #16
    //   311: getfield c : Lpv2;
    //   314: checkcast fq2
    //   317: aload #17
    //   319: invokevirtual m : (Ljava/lang/String;)V
    //   322: aload #16
    //   324: invokevirtual b : ()Lpv2;
    //   327: checkcast fq2
    //   330: astore #18
    //   332: new java/util/ArrayList
    //   335: dup
    //   336: invokespecial <init> : ()V
    //   339: astore #17
    //   341: aload #17
    //   343: aload #15
    //   345: invokevirtual addAll : (Ljava/util/Collection;)Z
    //   348: pop
    //   349: invokestatic l : ()Lyp2;
    //   352: astore #16
    //   354: aload #16
    //   356: invokevirtual a : ()V
    //   359: aload #16
    //   361: getfield c : Lpv2;
    //   364: checkcast zp2
    //   367: aload #17
    //   369: invokevirtual n : (Ljava/util/ArrayList;)V
    //   372: aload #16
    //   374: invokevirtual a : ()V
    //   377: aload #16
    //   379: getfield c : Lpv2;
    //   382: checkcast zp2
    //   385: aload #18
    //   387: invokevirtual m : (Lfq2;)V
    //   390: aload #16
    //   392: invokevirtual b : ()Lpv2;
    //   395: checkcast zp2
    //   398: astore #17
    //   400: invokestatic m : ()Lnq2;
    //   403: astore #16
    //   405: aload #16
    //   407: invokevirtual a : ()V
    //   410: aload #16
    //   412: getfield c : Lpv2;
    //   415: checkcast oq2
    //   418: aload #17
    //   420: invokevirtual y : (Lzp2;)V
    //   423: aload #16
    //   425: invokevirtual b : ()Lpv2;
    //   428: checkcast oq2
    //   431: astore #16
    //   433: aload #13
    //   435: getfield a : Lhn2;
    //   438: aload #16
    //   440: sipush #243
    //   443: invokevirtual a : (Loq2;I)V
    //   446: aload #14
    //   448: invokeinterface edit : ()Landroid/content/SharedPreferences$Editor;
    //   453: astore #16
    //   455: aload #12
    //   457: aload #15
    //   459: invokevirtual equals : (Ljava/lang/Object;)Z
    //   462: ifne -> 611
    //   465: aload #12
    //   467: invokevirtual clear : ()V
    //   470: aload #12
    //   472: aload #15
    //   474: invokeinterface addAll : (Ljava/util/Collection;)Z
    //   479: pop
    //   480: aload #12
    //   482: invokevirtual iterator : ()Ljava/util/Iterator;
    //   485: astore #15
    //   487: aload #15
    //   489: invokeinterface hasNext : ()Z
    //   494: ifeq -> 611
    //   497: aload #15
    //   499: invokeinterface next : ()Ljava/lang/Object;
    //   504: checkcast wp2
    //   507: getfield b : I
    //   510: invokestatic toString : (I)Ljava/lang/String;
    //   513: astore #17
    //   515: ldc 'feature_usage_timestamp_reported_feature_'
    //   517: aload #17
    //   519: invokestatic k : (Ljava/lang/String;Ljava/lang/String;)Ljava/lang/String;
    //   522: astore #12
    //   524: aload #14
    //   526: aload #12
    //   528: invokeinterface contains : (Ljava/lang/String;)Z
    //   533: ifeq -> 539
    //   536: goto -> 548
    //   539: ldc 'feature_usage_timestamp_detected_feature_'
    //   541: aload #17
    //   543: invokestatic k : (Ljava/lang/String;Ljava/lang/String;)Ljava/lang/String;
    //   546: astore #12
    //   548: ldc 'feature_usage_timestamp_reported_feature_'
    //   550: aload #17
    //   552: invokestatic k : (Ljava/lang/String;Ljava/lang/String;)Ljava/lang/String;
    //   555: astore #17
    //   557: aload #12
    //   559: aload #17
    //   561: invokestatic equals : (Ljava/lang/CharSequence;Ljava/lang/CharSequence;)Z
    //   564: ifne -> 487
    //   567: aload #14
    //   569: aload #12
    //   571: lconst_0
    //   572: invokeinterface getLong : (Ljava/lang/String;J)J
    //   577: lstore #5
    //   579: aload #16
    //   581: aload #12
    //   583: invokeinterface remove : (Ljava/lang/String;)Landroid/content/SharedPreferences$Editor;
    //   588: pop
    //   589: lload #5
    //   591: lconst_0
    //   592: lcmp
    //   593: ifeq -> 487
    //   596: aload #16
    //   598: aload #17
    //   600: lload #5
    //   602: invokeinterface putLong : (Ljava/lang/String;J)Landroid/content/SharedPreferences$Editor;
    //   607: pop
    //   608: goto -> 487
    //   611: aload #13
    //   613: lload #7
    //   615: putfield h : J
    //   618: aload #16
    //   620: ldc 'feature_usage_last_report_time'
    //   622: lload #7
    //   624: invokeinterface putLong : (Ljava/lang/String;J)Landroid/content/SharedPreferences$Editor;
    //   629: invokeinterface apply : ()V
    //   634: return
    //   635: aload_0
    //   636: getfield c : Ljava/lang/Object;
    //   639: checkcast qr2
    //   642: iconst_0
    //   643: invokevirtual i : (Z)V
    //   646: return
    //   647: aload_0
    //   648: getfield c : Ljava/lang/Object;
    //   651: checkcast android/content/Context
    //   654: astore #12
    //   656: getstatic io1.e : Ljava/util/concurrent/atomic/AtomicReference;
    //   659: astore #13
    //   661: aload #12
    //   663: invokestatic b : (Landroid/content/Context;)Lbv2;
    //   666: astore #12
    //   668: aload #12
    //   670: monitorenter
    //   671: aload #12
    //   673: iconst_1
    //   674: putfield f : Z
    //   677: aload #12
    //   679: invokevirtual a : ()V
    //   682: aload #12
    //   684: monitorexit
    //   685: goto -> 708
    //   688: astore #13
    //   690: aload #12
    //   692: monitorexit
    //   693: aload #13
    //   695: athrow
    //   696: astore #12
    //   698: ldc_w 'SplitCompat'
    //   701: ldc_w 'Failed to set broadcast receiver to always on.'
    //   704: invokestatic e : (Ljava/lang/String;Ljava/lang/String;)I
    //   707: pop
    //   708: return
    //   709: aload_0
    //   710: getfield c : Ljava/lang/Object;
    //   713: checkcast fp2
    //   716: astore #12
    //   718: aload #12
    //   720: getfield g : Lop2;
    //   723: astore #14
    //   725: aload #14
    //   727: ifnull -> 761
    //   730: aload #12
    //   732: getfield c : Lsp2;
    //   735: astore #13
    //   737: aload #12
    //   739: getfield a : Lhn2;
    //   742: aload #13
    //   744: aload #14
    //   746: invokevirtual b : (Lop2;)Lnq2;
    //   749: invokevirtual b : ()Lpv2;
    //   752: checkcast oq2
    //   755: sipush #223
    //   758: invokevirtual a : (Loq2;I)V
    //   761: aload #12
    //   763: invokevirtual c : ()V
    //   766: return
    //   767: aload_0
    //   768: getfield c : Ljava/lang/Object;
    //   771: checkcast dk2
    //   774: astore #13
    //   776: aload #13
    //   778: getfield h : Ljava/lang/Object;
    //   781: astore #12
    //   783: aload #12
    //   785: monitorenter
    //   786: aload #13
    //   788: getfield e : Ljava/util/ArrayList;
    //   791: invokevirtual isEmpty : ()Z
    //   794: istore #11
    //   796: aload #12
    //   798: monitorexit
    //   799: iload #11
    //   801: ifne -> 842
    //   804: aload #13
    //   806: getfield i : Z
    //   809: ifne -> 842
    //   812: aload #13
    //   814: getfield c : Landroid/net/ConnectivityManager;
    //   817: astore #12
    //   819: aload #12
    //   821: ifnull -> 842
    //   824: aload #12
    //   826: invokevirtual getActiveNetworkInfo : ()Landroid/net/NetworkInfo;
    //   829: astore #12
    //   831: aload #12
    //   833: ifnull -> 842
    //   836: aload #12
    //   838: invokevirtual isConnected : ()Z
    //   841: pop
    //   842: aconst_null
    //   843: athrow
    //   844: astore #13
    //   846: aload #12
    //   848: monitorexit
    //   849: aload #13
    //   851: athrow
    //   852: aload_0
    //   853: getfield c : Ljava/lang/Object;
    //   856: checkcast kj2
    //   859: astore #15
    //   861: aload #15
    //   863: ifnonnull -> 869
    //   866: goto -> 1386
    //   869: aload #15
    //   871: getfield j : Lhj2;
    //   874: astore #16
    //   876: aload #16
    //   878: ifnull -> 1386
    //   881: aload_0
    //   882: aconst_null
    //   883: putfield c : Ljava/lang/Object;
    //   886: aload #16
    //   888: invokeinterface isDone : ()Z
    //   893: ifeq -> 1067
    //   896: aload #15
    //   898: getfield b : Ljava/lang/Object;
    //   901: astore #13
    //   903: aload #13
    //   905: astore #12
    //   907: aload #13
    //   909: ifnonnull -> 1040
    //   912: aload #16
    //   914: invokeinterface isDone : ()Z
    //   919: ifeq -> 951
    //   922: aload #16
    //   924: invokestatic h : (Lhj2;)Ljava/lang/Object;
    //   927: astore #12
    //   929: getstatic li2.i : Lwf2;
    //   932: aload #15
    //   934: aconst_null
    //   935: aload #12
    //   937: invokevirtual J0 : (Lli2;Ljava/lang/Object;Ljava/lang/Object;)Z
    //   940: ifeq -> 1386
    //   943: aload #15
    //   945: invokestatic j : (Lkj2;)V
    //   948: goto -> 1386
    //   951: new ci2
    //   954: dup
    //   955: aload #15
    //   957: aload #16
    //   959: invokespecial <init> : (Lkj2;Lhj2;)V
    //   962: astore #13
    //   964: getstatic li2.i : Lwf2;
    //   967: aload #15
    //   969: aconst_null
    //   970: aload #13
    //   972: invokevirtual J0 : (Lli2;Ljava/lang/Object;Ljava/lang/Object;)Z
    //   975: ifeq -> 1033
    //   978: aload #16
    //   980: aload #13
    //   982: getstatic ti2.b : Lti2;
    //   985: invokeinterface b : (Ljava/lang/Runnable;Ljava/util/concurrent/Executor;)V
    //   990: goto -> 1386
    //   993: astore #14
    //   995: new ei2
    //   998: astore #12
    //   1000: aload #12
    //   1002: aload #14
    //   1004: invokespecial <init> : (Ljava/lang/Throwable;)V
    //   1007: goto -> 1017
    //   1010: astore #12
    //   1012: getstatic ei2.b : Lei2;
    //   1015: astore #12
    //   1017: getstatic li2.i : Lwf2;
    //   1020: aload #15
    //   1022: aload #13
    //   1024: aload #12
    //   1026: invokevirtual J0 : (Lli2;Ljava/lang/Object;Ljava/lang/Object;)Z
    //   1029: pop
    //   1030: goto -> 1386
    //   1033: aload #15
    //   1035: getfield b : Ljava/lang/Object;
    //   1038: astore #12
    //   1040: aload #12
    //   1042: instanceof bi2
    //   1045: ifeq -> 1386
    //   1048: aload #16
    //   1050: aload #12
    //   1052: checkcast bi2
    //   1055: getfield a : Z
    //   1058: invokeinterface cancel : (Z)Z
    //   1063: pop
    //   1064: goto -> 1386
    //   1067: aload #15
    //   1069: getfield k : Ljava/util/concurrent/ScheduledFuture;
    //   1072: astore #17
    //   1074: aload #15
    //   1076: aconst_null
    //   1077: putfield k : Ljava/util/concurrent/ScheduledFuture;
    //   1080: ldc_w 'Timed out'
    //   1083: astore #14
    //   1085: aload #14
    //   1087: astore #12
    //   1089: aload #17
    //   1091: ifnull -> 1191
    //   1094: aload #14
    //   1096: astore #13
    //   1098: aload #17
    //   1100: getstatic java/util/concurrent/TimeUnit.MILLISECONDS : Ljava/util/concurrent/TimeUnit;
    //   1103: invokeinterface getDelay : (Ljava/util/concurrent/TimeUnit;)J
    //   1108: invokestatic abs : (J)J
    //   1111: lstore #5
    //   1113: aload #14
    //   1115: astore #12
    //   1117: lload #5
    //   1119: ldc2_w 10
    //   1122: lcmp
    //   1123: ifle -> 1191
    //   1126: aload #14
    //   1128: astore #13
    //   1130: new java/lang/StringBuilder
    //   1133: astore #12
    //   1135: aload #14
    //   1137: astore #13
    //   1139: aload #12
    //   1141: ldc_w 'Timed out (timeout delayed by '
    //   1144: invokespecial <init> : (Ljava/lang/String;)V
    //   1147: aload #14
    //   1149: astore #13
    //   1151: aload #12
    //   1153: lload #5
    //   1155: invokevirtual append : (J)Ljava/lang/StringBuilder;
    //   1158: pop
    //   1159: aload #14
    //   1161: astore #13
    //   1163: aload #12
    //   1165: ldc_w ' ms after scheduled time)'
    //   1168: invokevirtual append : (Ljava/lang/String;)Ljava/lang/StringBuilder;
    //   1171: pop
    //   1172: aload #14
    //   1174: astore #13
    //   1176: aload #12
    //   1178: invokevirtual toString : ()Ljava/lang/String;
    //   1181: astore #12
    //   1183: goto -> 1191
    //   1186: astore #12
    //   1188: goto -> 1328
    //   1191: aload #12
    //   1193: astore #13
    //   1195: aload #16
    //   1197: invokevirtual toString : ()Ljava/lang/String;
    //   1200: astore #14
    //   1202: aload #12
    //   1204: astore #13
    //   1206: new java/lang/StringBuilder
    //   1209: astore #17
    //   1211: aload #12
    //   1213: astore #13
    //   1215: aload #17
    //   1217: invokespecial <init> : ()V
    //   1220: aload #12
    //   1222: astore #13
    //   1224: aload #17
    //   1226: aload #12
    //   1228: invokevirtual append : (Ljava/lang/String;)Ljava/lang/StringBuilder;
    //   1231: pop
    //   1232: aload #12
    //   1234: astore #13
    //   1236: aload #17
    //   1238: ldc_w ': '
    //   1241: invokevirtual append : (Ljava/lang/String;)Ljava/lang/StringBuilder;
    //   1244: pop
    //   1245: aload #12
    //   1247: astore #13
    //   1249: aload #17
    //   1251: aload #14
    //   1253: invokevirtual append : (Ljava/lang/String;)Ljava/lang/StringBuilder;
    //   1256: pop
    //   1257: aload #12
    //   1259: astore #13
    //   1261: aload #17
    //   1263: invokevirtual toString : ()Ljava/lang/String;
    //   1266: astore #14
    //   1268: new jj2
    //   1271: astore #12
    //   1273: aload #12
    //   1275: aload #14
    //   1277: invokespecial <init> : (Ljava/lang/String;)V
    //   1280: new ei2
    //   1283: astore #13
    //   1285: aload #13
    //   1287: aload #12
    //   1289: invokespecial <init> : (Ljava/lang/Throwable;)V
    //   1292: getstatic li2.i : Lwf2;
    //   1295: aload #15
    //   1297: aconst_null
    //   1298: aload #13
    //   1300: invokevirtual J0 : (Lli2;Ljava/lang/Object;Ljava/lang/Object;)Z
    //   1303: ifeq -> 1311
    //   1306: aload #15
    //   1308: invokestatic j : (Lkj2;)V
    //   1311: aload #16
    //   1313: iconst_1
    //   1314: invokeinterface cancel : (Z)Z
    //   1319: pop
    //   1320: goto -> 1386
    //   1323: astore #12
    //   1325: goto -> 1374
    //   1328: new jj2
    //   1331: astore #14
    //   1333: aload #14
    //   1335: aload #13
    //   1337: invokespecial <init> : (Ljava/lang/String;)V
    //   1340: new ei2
    //   1343: astore #13
    //   1345: aload #13
    //   1347: aload #14
    //   1349: invokespecial <init> : (Ljava/lang/Throwable;)V
    //   1352: getstatic li2.i : Lwf2;
    //   1355: aload #15
    //   1357: aconst_null
    //   1358: aload #13
    //   1360: invokevirtual J0 : (Lli2;Ljava/lang/Object;Ljava/lang/Object;)Z
    //   1363: ifeq -> 1371
    //   1366: aload #15
    //   1368: invokestatic j : (Lkj2;)V
    //   1371: aload #12
    //   1373: athrow
    //   1374: aload #16
    //   1376: iconst_1
    //   1377: invokeinterface cancel : (Z)Z
    //   1382: pop
    //   1383: aload #12
    //   1385: athrow
    //   1386: return
    //   1387: aload_0
    //   1388: getfield c : Ljava/lang/Object;
    //   1391: checkcast nt1
    //   1394: astore #12
    //   1396: getstatic ki2.d : Lrp0;
    //   1399: ldc_w 'get checkbox consent timed out'
    //   1402: iconst_0
    //   1403: anewarray java/lang/Object
    //   1406: invokevirtual b : (Ljava/lang/String;[Ljava/lang/Object;)V
    //   1409: aload #12
    //   1411: getstatic java/lang/Boolean.FALSE : Ljava/lang/Boolean;
    //   1414: invokevirtual d : (Ljava/lang/Object;)V
    //   1417: return
    //   1418: aload_0
    //   1419: getfield c : Ljava/lang/Object;
    //   1422: checkcast dh2
    //   1425: astore #13
    //   1427: aload #13
    //   1429: getfield f : Lef;
    //   1432: astore #12
    //   1434: aload #12
    //   1436: iconst_0
    //   1437: invokevirtual s : (I)V
    //   1440: getstatic ij2.k : Lqf;
    //   1443: astore #14
    //   1445: aload #12
    //   1447: bipush #24
    //   1449: aload #14
    //   1451: invokevirtual r : (ILqf;)V
    //   1454: aload #13
    //   1456: aload #14
    //   1458: invokevirtual c : (Lqf;)V
    //   1461: return
    //   1462: aload_0
    //   1463: getfield c : Ljava/lang/Object;
    //   1466: checkcast df2
    //   1469: astore #13
    //   1471: getstatic df2.i : Ljava/lang/Object;
    //   1474: astore #12
    //   1476: aload #12
    //   1478: monitorenter
    //   1479: aload #13
    //   1481: invokevirtual b : ()Z
    //   1484: ifne -> 1498
    //   1487: aload #12
    //   1489: monitorexit
    //   1490: goto -> 1509
    //   1493: astore #13
    //   1495: goto -> 1510
    //   1498: aload #13
    //   1500: bipush #15
    //   1502: invokevirtual e : (I)Z
    //   1505: pop
    //   1506: aload #12
    //   1508: monitorexit
    //   1509: return
    //   1510: aload #12
    //   1512: monitorexit
    //   1513: aload #13
    //   1515: athrow
    //   1516: aconst_null
    //   1517: athrow
    //   1518: new sp
    //   1521: dup
    //   1522: iconst_4
    //   1523: aconst_null
    //   1524: aconst_null
    //   1525: invokespecial <init> : (ILandroid/app/PendingIntent;Ljava/lang/String;)V
    //   1528: astore #12
    //   1530: aload_0
    //   1531: getfield c : Ljava/lang/Object;
    //   1534: checkcast cb2
    //   1537: getfield l : Lsa2;
    //   1540: aload #12
    //   1542: invokevirtual a : (Lsp;)V
    //   1545: return
    //   1546: aload_0
    //   1547: getfield c : Ljava/lang/Object;
    //   1550: checkcast a42
    //   1553: getfield c : Ljava/lang/Object;
    //   1556: checkcast qa2
    //   1559: astore #12
    //   1561: aload #12
    //   1563: getfield f : Lhe0;
    //   1566: invokevirtual getClass : ()Ljava/lang/Class;
    //   1569: invokevirtual getName : ()Ljava/lang/String;
    //   1572: astore #13
    //   1574: aload #12
    //   1576: getfield f : Lhe0;
    //   1579: astore #12
    //   1581: aload #13
    //   1583: ldc_w ' disconnecting because it was signed out.'
    //   1586: invokevirtual concat : (Ljava/lang/String;)Ljava/lang/String;
    //   1589: astore #13
    //   1591: aload #12
    //   1593: checkcast yc
    //   1596: aload #13
    //   1598: invokevirtual c : (Ljava/lang/String;)V
    //   1601: return
    //   1602: aload_0
    //   1603: getfield c : Ljava/lang/Object;
    //   1606: checkcast qa2
    //   1609: invokevirtual a : ()V
    //   1612: return
    //   1613: aload_0
    //   1614: getfield c : Ljava/lang/Object;
    //   1617: checkcast in/krosbits/musicolet/WidgetPrefActivity
    //   1620: astore #12
    //   1622: aload #12
    //   1624: getfield M0 : Lj52;
    //   1627: invokevirtual a : ()Landroid/graphics/Bitmap;
    //   1630: astore #13
    //   1632: aload #12
    //   1634: getfield u0 : Landroid/widget/ImageView;
    //   1637: astore #14
    //   1639: aload #14
    //   1641: ifnull -> 1659
    //   1644: aload #13
    //   1646: ifnull -> 1659
    //   1649: aload #14
    //   1651: aload #13
    //   1653: invokevirtual setImageBitmap : (Landroid/graphics/Bitmap;)V
    //   1656: goto -> 1687
    //   1659: aload #12
    //   1661: getfield M0 : Lj52;
    //   1664: getfield a : Z
    //   1667: ifeq -> 1677
    //   1670: ldc_w 2131230843
    //   1673: istore_2
    //   1674: goto -> 1681
    //   1677: ldc_w 2131230842
    //   1680: istore_2
    //   1681: aload #14
    //   1683: iload_2
    //   1684: invokevirtual setImageResource : (I)V
    //   1687: aload #12
    //   1689: getfield M0 : Lj52;
    //   1692: astore #13
    //   1694: aload #13
    //   1696: getfield b : Z
    //   1699: ifeq -> 2181
    //   1702: aload #12
    //   1704: getfield z0 : Landroid/widget/ImageView;
    //   1707: astore #14
    //   1709: aload #14
    //   1711: ifnull -> 1749
    //   1714: aload #14
    //   1716: aload #13
    //   1718: getfield e : I
    //   1721: invokevirtual setColorFilter : (I)V
    //   1724: aload #12
    //   1726: getfield s0 : I
    //   1729: iconst_1
    //   1730: if_icmpeq -> 1749
    //   1733: aload #12
    //   1735: getfield z0 : Landroid/widget/ImageView;
    //   1738: aload #12
    //   1740: getfield M0 : Lj52;
    //   1743: getfield f : I
    //   1746: invokevirtual setImageAlpha : (I)V
    //   1749: aload #12
    //   1751: getfield A0 : Landroid/widget/ImageView;
    //   1754: astore #13
    //   1756: aload #13
    //   1758: ifnull -> 1790
    //   1761: aload #13
    //   1763: aload #12
    //   1765: getfield M0 : Lj52;
    //   1768: getfield e : I
    //   1771: invokevirtual setColorFilter : (I)V
    //   1774: aload #12
    //   1776: getfield A0 : Landroid/widget/ImageView;
    //   1779: aload #12
    //   1781: getfield M0 : Lj52;
    //   1784: getfield f : I
    //   1787: invokevirtual setImageAlpha : (I)V
    //   1790: aload #12
    //   1792: getfield B0 : Landroid/widget/ImageView;
    //   1795: astore #13
    //   1797: aload #13
    //   1799: ifnull -> 1831
    //   1802: aload #13
    //   1804: aload #12
    //   1806: getfield M0 : Lj52;
    //   1809: getfield e : I
    //   1812: invokevirtual setColorFilter : (I)V
    //   1815: aload #12
    //   1817: getfield B0 : Landroid/widget/ImageView;
    //   1820: aload #12
    //   1822: getfield M0 : Lj52;
    //   1825: getfield f : I
    //   1828: invokevirtual setImageAlpha : (I)V
    //   1831: aload #12
    //   1833: getfield v0 : Landroid/widget/ImageView;
    //   1836: astore #13
    //   1838: aload #13
    //   1840: ifnull -> 1872
    //   1843: aload #13
    //   1845: aload #12
    //   1847: getfield M0 : Lj52;
    //   1850: getfield e : I
    //   1853: invokevirtual setColorFilter : (I)V
    //   1856: aload #12
    //   1858: getfield v0 : Landroid/widget/ImageView;
    //   1861: aload #12
    //   1863: getfield M0 : Lj52;
    //   1866: getfield f : I
    //   1869: invokevirtual setImageAlpha : (I)V
    //   1872: aload #12
    //   1874: getfield w0 : Landroid/widget/ImageView;
    //   1877: astore #13
    //   1879: aload #13
    //   1881: ifnull -> 1913
    //   1884: aload #13
    //   1886: aload #12
    //   1888: getfield M0 : Lj52;
    //   1891: getfield e : I
    //   1894: invokevirtual setColorFilter : (I)V
    //   1897: aload #12
    //   1899: getfield w0 : Landroid/widget/ImageView;
    //   1902: aload #12
    //   1904: getfield M0 : Lj52;
    //   1907: getfield f : I
    //   1910: invokevirtual setImageAlpha : (I)V
    //   1913: aload #12
    //   1915: getfield x0 : Landroid/widget/ImageView;
    //   1918: astore #13
    //   1920: aload #13
    //   1922: ifnull -> 1954
    //   1925: aload #13
    //   1927: aload #12
    //   1929: getfield M0 : Lj52;
    //   1932: getfield e : I
    //   1935: invokevirtual setColorFilter : (I)V
    //   1938: aload #12
    //   1940: getfield x0 : Landroid/widget/ImageView;
    //   1943: aload #12
    //   1945: getfield M0 : Lj52;
    //   1948: getfield f : I
    //   1951: invokevirtual setImageAlpha : (I)V
    //   1954: aload #12
    //   1956: getfield y0 : Landroid/widget/ImageView;
    //   1959: astore #13
    //   1961: aload #13
    //   1963: ifnull -> 1995
    //   1966: aload #13
    //   1968: aload #12
    //   1970: getfield M0 : Lj52;
    //   1973: getfield e : I
    //   1976: invokevirtual setColorFilter : (I)V
    //   1979: aload #12
    //   1981: getfield y0 : Landroid/widget/ImageView;
    //   1984: aload #12
    //   1986: getfield M0 : Lj52;
    //   1989: getfield f : I
    //   1992: invokevirtual setImageAlpha : (I)V
    //   1995: aload #12
    //   1997: getfield D0 : Landroid/widget/TextView;
    //   2000: astore #13
    //   2002: aload #13
    //   2004: ifnull -> 2020
    //   2007: aload #13
    //   2009: aload #12
    //   2011: getfield M0 : Lj52;
    //   2014: getfield c : I
    //   2017: invokevirtual setTextColor : (I)V
    //   2020: aload #12
    //   2022: getfield E0 : Landroid/widget/TextView;
    //   2025: astore #13
    //   2027: aload #13
    //   2029: ifnull -> 2045
    //   2032: aload #13
    //   2034: aload #12
    //   2036: getfield M0 : Lj52;
    //   2039: getfield c : I
    //   2042: invokevirtual setTextColor : (I)V
    //   2045: aload #12
    //   2047: getfield F0 : Landroid/widget/TextView;
    //   2050: astore #13
    //   2052: iload_3
    //   2053: istore_2
    //   2054: aload #13
    //   2056: ifnull -> 2074
    //   2059: aload #13
    //   2061: aload #12
    //   2063: getfield M0 : Lj52;
    //   2066: getfield d : I
    //   2069: invokevirtual setTextColor : (I)V
    //   2072: iload_3
    //   2073: istore_2
    //   2074: aload #12
    //   2076: getfield t0 : [Landroid/widget/ImageView;
    //   2079: astore #13
    //   2081: iload_2
    //   2082: aload #13
    //   2084: arraylength
    //   2085: if_icmpge -> 2118
    //   2088: aload #13
    //   2090: iload_2
    //   2091: aaload
    //   2092: astore #13
    //   2094: aload #13
    //   2096: ifnull -> 2112
    //   2099: aload #13
    //   2101: aload #12
    //   2103: getfield M0 : Lj52;
    //   2106: getfield g : I
    //   2109: invokevirtual setColorFilter : (I)V
    //   2112: iinc #2, 1
    //   2115: goto -> 2074
    //   2118: aload #12
    //   2120: getfield C0 : Landroid/widget/ImageView;
    //   2123: astore #13
    //   2125: aload #13
    //   2127: ifnull -> 2181
    //   2130: aload #13
    //   2132: aload #12
    //   2134: getfield M0 : Lj52;
    //   2137: getfield g : I
    //   2140: invokevirtual setColorFilter : (I)V
    //   2143: aload #12
    //   2145: getfield M0 : Lj52;
    //   2148: astore #13
    //   2150: ldc_w 4.0
    //   2153: aload #13
    //   2155: getfield g : I
    //   2158: aload #13
    //   2160: getfield e : I
    //   2163: invokestatic f : (FII)I
    //   2166: istore_2
    //   2167: iload_2
    //   2168: iconst_m1
    //   2169: if_icmpeq -> 2181
    //   2172: aload #12
    //   2174: getfield C0 : Landroid/widget/ImageView;
    //   2177: iload_2
    //   2178: invokevirtual setImageAlpha : (I)V
    //   2181: aload #12
    //   2183: getfield G0 : Landroid/widget/ListView;
    //   2186: astore #12
    //   2188: aload #12
    //   2190: ifnull -> 2216
    //   2193: aload #12
    //   2195: invokevirtual getAdapter : ()Landroid/widget/ListAdapter;
    //   2198: astore #12
    //   2200: aload #12
    //   2202: instanceof android/widget/BaseAdapter
    //   2205: ifeq -> 2216
    //   2208: aload #12
    //   2210: checkcast android/widget/BaseAdapter
    //   2213: invokevirtual notifyDataSetChanged : ()V
    //   2216: return
    //   2217: aload_0
    //   2218: getfield c : Ljava/lang/Object;
    //   2221: checkcast in/krosbits/musicolet/WelcomeActivity
    //   2224: astore #12
    //   2226: aload #12
    //   2228: getfield X : Lcom/google/android/material/floatingactionbutton/FloatingActionButton;
    //   2231: iconst_1
    //   2232: invokevirtual setEnabled : (Z)V
    //   2235: aload #12
    //   2237: getfield W : Lcom/google/android/material/floatingactionbutton/FloatingActionButton;
    //   2240: iconst_1
    //   2241: invokevirtual setEnabled : (Z)V
    //   2244: return
    //   2245: getstatic in/krosbits/musicolet/MyApplication.p : F
    //   2248: ldc_w 48.0
    //   2251: fmul
    //   2252: f2i
    //   2253: istore_2
    //   2254: aload_0
    //   2255: getfield c : Ljava/lang/Object;
    //   2258: checkcast u42
    //   2261: getfield a0 : Landroid/widget/ScrollView;
    //   2264: iload_2
    //   2265: invokevirtual setScrollY : (I)V
    //   2268: return
    //   2269: aload_0
    //   2270: getfield c : Ljava/lang/Object;
    //   2273: checkcast in/krosbits/android/widgets/ViewPager2
    //   2276: astore #12
    //   2278: aload #12
    //   2280: iconst_0
    //   2281: invokevirtual setScrollState : (I)V
    //   2284: aload #12
    //   2286: invokevirtual r : ()V
    //   2289: return
    //   2290: aload_0
    //   2291: getfield c : Ljava/lang/Object;
    //   2294: checkcast y22
    //   2297: iconst_0
    //   2298: invokevirtual m : (I)V
    //   2301: return
    //   2302: aload_0
    //   2303: getfield c : Ljava/lang/Object;
    //   2306: checkcast in/krosbits/audio_cutter/TrimActivity
    //   2309: astore #12
    //   2311: aload #12
    //   2313: getfield f0 : Landroid/os/Handler;
    //   2316: astore #13
    //   2318: aload #13
    //   2320: aload_0
    //   2321: invokevirtual removeCallbacks : (Ljava/lang/Runnable;)V
    //   2324: aload #12
    //   2326: getfield b0 : Z
    //   2329: ifeq -> 2454
    //   2332: aload #12
    //   2334: invokevirtual s0 : ()V
    //   2337: aload #12
    //   2339: getfield a0 : Lw60;
    //   2342: astore #14
    //   2344: aload #14
    //   2346: ifnull -> 2454
    //   2349: aload #14
    //   2351: invokevirtual J : ()Z
    //   2354: ifeq -> 2454
    //   2357: aload #12
    //   2359: getfield g0 : Z
    //   2362: ifeq -> 2434
    //   2365: aload #14
    //   2367: invokevirtual A : ()I
    //   2370: i2f
    //   2371: fstore_1
    //   2372: aload #12
    //   2374: getfield U : Lby1;
    //   2377: astore #14
    //   2379: aload #14
    //   2381: ifnull -> 2426
    //   2384: fload_1
    //   2385: aload #14
    //   2387: getfield d : Led1;
    //   2390: getfield b : Lip1;
    //   2393: invokevirtual f : ()Ljava/lang/Object;
    //   2396: checkcast cy1
    //   2399: getfield c : Ljava/util/List;
    //   2402: iconst_1
    //   2403: invokeinterface get : (I)Ljava/lang/Object;
    //   2408: checkcast java/lang/Number
    //   2411: invokevirtual floatValue : ()F
    //   2414: fcmpl
    //   2415: iflt -> 2434
    //   2418: aload #12
    //   2420: invokevirtual q0 : ()V
    //   2423: goto -> 2454
    //   2426: ldc_w 'mViewModel'
    //   2429: invokestatic n0 : (Ljava/lang/String;)V
    //   2432: aconst_null
    //   2433: athrow
    //   2434: aload #13
    //   2436: aload_0
    //   2437: ldc2_w 100
    //   2440: invokevirtual postDelayed : (Ljava/lang/Runnable;J)Z
    //   2443: pop
    //   2444: goto -> 2454
    //   2447: astore #12
    //   2449: aload #12
    //   2451: invokevirtual printStackTrace : ()V
    //   2454: return
    //   2455: aload_0
    //   2456: getfield c : Ljava/lang/Object;
    //   2459: checkcast kv1
    //   2462: astore #12
    //   2464: aload #12
    //   2466: getfield p : Landroid/view/Window$Callback;
    //   2469: astore #13
    //   2471: aload #12
    //   2473: invokevirtual D0 : ()Landroid/view/Menu;
    //   2476: astore #14
    //   2478: aload #14
    //   2480: instanceof rw0
    //   2483: ifeq -> 2496
    //   2486: aload #14
    //   2488: checkcast rw0
    //   2491: astore #12
    //   2493: goto -> 2499
    //   2496: aconst_null
    //   2497: astore #12
    //   2499: aload #12
    //   2501: ifnull -> 2509
    //   2504: aload #12
    //   2506: invokevirtual w : ()V
    //   2509: aload #14
    //   2511: invokeinterface clear : ()V
    //   2516: aload #13
    //   2518: iconst_0
    //   2519: aload #14
    //   2521: invokeinterface onCreatePanelMenu : (ILandroid/view/Menu;)Z
    //   2526: ifeq -> 2551
    //   2529: aload #13
    //   2531: iconst_0
    //   2532: aconst_null
    //   2533: aload #14
    //   2535: invokeinterface onPreparePanel : (ILandroid/view/View;Landroid/view/Menu;)Z
    //   2540: ifne -> 2558
    //   2543: goto -> 2551
    //   2546: astore #13
    //   2548: goto -> 2569
    //   2551: aload #14
    //   2553: invokeinterface clear : ()V
    //   2558: aload #12
    //   2560: ifnull -> 2568
    //   2563: aload #12
    //   2565: invokevirtual v : ()V
    //   2568: return
    //   2569: aload #12
    //   2571: ifnull -> 2579
    //   2574: aload #12
    //   2576: invokevirtual v : ()V
    //   2579: aload #13
    //   2581: athrow
    //   2582: aload_0
    //   2583: getfield c : Ljava/lang/Object;
    //   2586: checkcast androidx/appcompat/widget/Toolbar
    //   2589: invokevirtual u : ()Z
    //   2592: pop
    //   2593: return
    //   2594: aload_0
    //   2595: getfield c : Ljava/lang/Object;
    //   2598: checkcast com/google/android/material/textfield/TextInputLayout
    //   2601: getfield e : Ln40;
    //   2604: getfield i : Lcom/google/android/material/internal/CheckableImageButton;
    //   2607: astore #12
    //   2609: aload #12
    //   2611: invokevirtual performClick : ()Z
    //   2614: pop
    //   2615: aload #12
    //   2617: invokevirtual jumpDrawablesToCurrentState : ()V
    //   2620: return
    //   2621: aload_0
    //   2622: getfield c : Ljava/lang/Object;
    //   2625: checkcast in/krosbits/musicolet/Tag2Activity
    //   2628: astore #12
    //   2630: aload #12
    //   2632: invokevirtual isFinishing : ()Z
    //   2635: ifeq -> 2641
    //   2638: goto -> 2714
    //   2641: aload #12
    //   2643: getfield R : Lss0;
    //   2646: astore #13
    //   2648: aload #13
    //   2650: ifnull -> 2714
    //   2653: aload #13
    //   2655: aload #12
    //   2657: getfield Z : I
    //   2660: invokevirtual l : (I)V
    //   2663: aload #12
    //   2665: getfield R : Lss0;
    //   2668: aload #12
    //   2670: getfield Y : I
    //   2673: invokevirtual m : (I)V
    //   2676: aload #12
    //   2678: getfield R : Lss0;
    //   2681: invokevirtual isShowing : ()Z
    //   2684: ifne -> 2695
    //   2687: aload #12
    //   2689: getfield R : Lss0;
    //   2692: invokevirtual show : ()V
    //   2695: aload #12
    //   2697: getfield S : Lss0;
    //   2700: invokevirtual isShowing : ()Z
    //   2703: ifeq -> 2714
    //   2706: aload #12
    //   2708: getfield S : Lss0;
    //   2711: invokevirtual dismiss : ()V
    //   2714: return
    //   2715: aload_0
    //   2716: getfield c : Ljava/lang/Object;
    //   2719: checkcast androidx/recyclerview/widget/StaggeredGridLayoutManager
    //   2722: invokevirtual R0 : ()Z
    //   2725: pop
    //   2726: return
    //   2727: aload_0
    //   2728: getfield c : Ljava/lang/Object;
    //   2731: checkcast qg
    //   2734: getfield c : Ljava/lang/Object;
    //   2737: checkcast ss/com/bannerslider/Slider
    //   2740: astore #12
    //   2742: aload #12
    //   2744: getfield m : Lm9;
    //   2747: astore #13
    //   2749: aload #12
    //   2751: getfield k : I
    //   2754: istore_2
    //   2755: iload_2
    //   2756: aload #13
    //   2758: getfield b : Ljava/lang/Object;
    //   2761: checkcast jn1
    //   2764: invokevirtual c : ()I
    //   2767: iconst_1
    //   2768: isub
    //   2769: if_icmpge -> 2778
    //   2772: iinc #2, 1
    //   2775: goto -> 2784
    //   2778: aload #13
    //   2780: getfield a : Z
    //   2783: istore_2
    //   2784: aload #12
    //   2786: getfield c : Landroidx/recyclerview/widget/RecyclerView;
    //   2789: iload_2
    //   2790: invokevirtual n0 : (I)V
    //   2793: aload #12
    //   2795: iload_2
    //   2796: invokevirtual a : (I)V
    //   2799: return
    //   2800: aload_0
    //   2801: getfield c : Ljava/lang/Object;
    //   2804: checkcast androidx/appcompat/widget/SearchView
    //   2807: invokevirtual updateFocusedState : ()V
    //   2810: return
    //   2811: getstatic com/sdsmdg/harjot/crollerTest/TG/ckOPp.BIPTFhmi : Ljava/lang/String;
    //   2814: astore #14
    //   2816: aload_0
    //   2817: getfield c : Ljava/lang/Object;
    //   2820: checkcast zi1
    //   2823: astore #13
    //   2825: aload #13
    //   2827: getfield g : Landroid/widget/TextView;
    //   2830: astore #15
    //   2832: aload #13
    //   2834: getfield m : Landroid/widget/TextView;
    //   2837: astore #16
    //   2839: aload #13
    //   2841: getfield o : Landroid/widget/TextView;
    //   2844: astore #17
    //   2846: aload #13
    //   2848: getfield p : Landroid/widget/TextView;
    //   2851: astore #18
    //   2853: aload #13
    //   2855: getfield l : Landroid/widget/TextView;
    //   2858: astore #19
    //   2860: aload #13
    //   2862: getfield k : Landroid/widget/TextView;
    //   2865: astore #20
    //   2867: aload #13
    //   2869: getfield t : Landroid/widget/Button;
    //   2872: astore #25
    //   2874: aload #13
    //   2876: getfield f : Landroid/widget/TextView;
    //   2879: astore #12
    //   2881: aload #13
    //   2883: getfield e : Landroid/widget/ScrollView;
    //   2886: astore #21
    //   2888: aload #13
    //   2890: getfield q : Landroid/widget/ImageView;
    //   2893: astore #24
    //   2895: aload #13
    //   2897: getfield c : Landroid/widget/ScrollView;
    //   2900: astore #22
    //   2902: aload #13
    //   2904: getfield v : Landroid/widget/ProgressBar;
    //   2907: astore #26
    //   2909: aload #13
    //   2911: getfield u : Landroid/widget/Button;
    //   2914: astore #23
    //   2916: getstatic in/krosbits/musicolet/MyApplication.j : Lwn1;
    //   2919: astore #27
    //   2921: aload #27
    //   2923: ifnull -> 4201
    //   2926: aload #27
    //   2928: getfield c : Llm0;
    //   2931: ifnull -> 4201
    //   2934: aload #13
    //   2936: getfield b : Lss0;
    //   2939: ifnonnull -> 2945
    //   2942: goto -> 4201
    //   2945: getstatic im0.g0 : Lim0;
    //   2948: astore #27
    //   2950: aload #27
    //   2952: ifnull -> 3133
    //   2955: aload #22
    //   2957: bipush #8
    //   2959: invokevirtual setVisibility : (I)V
    //   2962: aload #24
    //   2964: iconst_4
    //   2965: invokevirtual setVisibility : (I)V
    //   2968: aload #21
    //   2970: iconst_0
    //   2971: invokevirtual setVisibility : (I)V
    //   2974: aload #12
    //   2976: aload #27
    //   2978: getfield d : Ljava/lang/String;
    //   2981: invokevirtual setText : (Ljava/lang/CharSequence;)V
    //   2984: aload #13
    //   2986: getfield i : Landroid/widget/TextView;
    //   2989: aload #27
    //   2991: getfield c : Ljava/lang/String;
    //   2994: invokevirtual setText : (Ljava/lang/CharSequence;)V
    //   2997: aload #27
    //   2999: getfield a : I
    //   3002: ifle -> 3034
    //   3005: aload #26
    //   3007: iconst_0
    //   3008: invokevirtual setIndeterminate : (Z)V
    //   3011: aload #26
    //   3013: aload #27
    //   3015: getfield a : I
    //   3018: invokevirtual setMax : (I)V
    //   3021: aload #26
    //   3023: aload #27
    //   3025: getfield b : I
    //   3028: invokevirtual setProgress : (I)V
    //   3031: goto -> 3040
    //   3034: aload #26
    //   3036: iconst_1
    //   3037: invokevirtual setIndeterminate : (Z)V
    //   3040: aload #27
    //   3042: getfield E : Z
    //   3045: ifeq -> 3057
    //   3048: aload #25
    //   3050: iconst_0
    //   3051: invokevirtual setVisibility : (I)V
    //   3054: goto -> 3064
    //   3057: aload #25
    //   3059: bipush #8
    //   3061: invokevirtual setVisibility : (I)V
    //   3064: aload #27
    //   3066: getfield i : Z
    //   3069: ifeq -> 3082
    //   3072: aload #23
    //   3074: bipush #8
    //   3076: invokevirtual setVisibility : (I)V
    //   3079: goto -> 3096
    //   3082: aload #23
    //   3084: ldc_w 2131886405
    //   3087: invokevirtual setText : (I)V
    //   3090: aload #23
    //   3092: iconst_0
    //   3093: invokevirtual setVisibility : (I)V
    //   3096: aload #27
    //   3098: getfield K : Z
    //   3101: istore #11
    //   3103: aload #13
    //   3105: getfield b : Lss0;
    //   3108: astore #12
    //   3110: iload #11
    //   3112: ifeq -> 3124
    //   3115: aload #12
    //   3117: iconst_0
    //   3118: invokevirtual setCancelable : (Z)V
    //   3121: goto -> 4229
    //   3124: aload #12
    //   3126: iconst_1
    //   3127: invokevirtual setCancelable : (Z)V
    //   3130: goto -> 4229
    //   3133: aload #13
    //   3135: getfield B : Z
    //   3138: ifeq -> 3148
    //   3141: ldc_w 2131886133
    //   3144: istore_2
    //   3145: goto -> 3152
    //   3148: ldc_w 2131887275
    //   3151: istore_2
    //   3152: aload #12
    //   3154: iload_2
    //   3155: invokevirtual setText : (I)V
    //   3158: aload #13
    //   3160: getfield h : Landroid/widget/TextView;
    //   3163: astore #12
    //   3165: new java/lang/StringBuilder
    //   3168: dup
    //   3169: ldc_w '<u>'
    //   3172: invokespecial <init> : (Ljava/lang/String;)V
    //   3175: astore #26
    //   3177: getstatic in/krosbits/musicolet/MyApplication.i : Lin/krosbits/musicolet/MyApplication;
    //   3180: invokevirtual getApplicationContext : ()Landroid/content/Context;
    //   3183: astore #27
    //   3185: aload #13
    //   3187: getfield B : Z
    //   3190: ifeq -> 3200
    //   3193: ldc_w 2131887005
    //   3196: istore_2
    //   3197: goto -> 3204
    //   3200: ldc_w 2131886133
    //   3203: istore_2
    //   3204: aload #26
    //   3206: aload #27
    //   3208: iload_2
    //   3209: invokevirtual getString : (I)Ljava/lang/String;
    //   3212: invokevirtual append : (Ljava/lang/String;)Ljava/lang/StringBuilder;
    //   3215: pop
    //   3216: aload #26
    //   3218: aload #14
    //   3220: invokevirtual append : (Ljava/lang/String;)Ljava/lang/StringBuilder;
    //   3223: pop
    //   3224: aload #12
    //   3226: aload #26
    //   3228: invokevirtual toString : ()Ljava/lang/String;
    //   3231: invokestatic fromHtml : (Ljava/lang/String;)Landroid/text/Spanned;
    //   3234: invokevirtual setText : (Ljava/lang/CharSequence;)V
    //   3237: aload #13
    //   3239: getfield A : [Landroid/view/View;
    //   3242: astore #12
    //   3244: aload #12
    //   3246: arraylength
    //   3247: istore #4
    //   3249: iconst_0
    //   3250: istore_2
    //   3251: iload_2
    //   3252: iload #4
    //   3254: if_icmpge -> 3291
    //   3257: aload #12
    //   3259: iload_2
    //   3260: aaload
    //   3261: astore #26
    //   3263: aload #13
    //   3265: getfield B : Z
    //   3268: ifeq -> 3276
    //   3271: iconst_0
    //   3272: istore_3
    //   3273: goto -> 3279
    //   3276: bipush #8
    //   3278: istore_3
    //   3279: aload #26
    //   3281: iload_3
    //   3282: invokevirtual setVisibility : (I)V
    //   3285: iinc #2, 1
    //   3288: goto -> 3251
    //   3291: aload #24
    //   3293: iconst_0
    //   3294: invokevirtual setVisibility : (I)V
    //   3297: aload #25
    //   3299: bipush #8
    //   3301: invokevirtual setVisibility : (I)V
    //   3304: aload #23
    //   3306: ldc_w 2131886363
    //   3309: invokevirtual setText : (I)V
    //   3312: aload #23
    //   3314: iconst_0
    //   3315: invokevirtual setVisibility : (I)V
    //   3318: aload #22
    //   3320: iconst_0
    //   3321: invokevirtual setVisibility : (I)V
    //   3324: aload #21
    //   3326: bipush #8
    //   3328: invokevirtual setVisibility : (I)V
    //   3331: aload #13
    //   3333: getfield n : Landroid/widget/TextView;
    //   3336: iconst_1
    //   3337: invokevirtual setEnabled : (Z)V
    //   3340: getstatic in/krosbits/musicolet/MyApplication.j : Lwn1;
    //   3343: getfield c : Llm0;
    //   3346: astore #12
    //   3348: aload #12
    //   3350: getfield b : Ljava/util/ArrayList;
    //   3353: invokevirtual size : ()I
    //   3356: aload #12
    //   3358: getfield A : I
    //   3361: iadd
    //   3362: aload #12
    //   3364: getfield z : I
    //   3367: iadd
    //   3368: istore_2
    //   3369: getstatic in/krosbits/musicolet/MyApplication.j : Lwn1;
    //   3372: getfield c : Llm0;
    //   3375: getfield b : Ljava/util/ArrayList;
    //   3378: invokevirtual size : ()I
    //   3381: istore_3
    //   3382: aload #13
    //   3384: getfield j : Landroid/widget/TextView;
    //   3387: astore #21
    //   3389: new java/lang/StringBuilder
    //   3392: dup
    //   3393: invokespecial <init> : ()V
    //   3396: astore #12
    //   3398: aload #12
    //   3400: getstatic in/krosbits/musicolet/MyApplication.i : Lin/krosbits/musicolet/MyApplication;
    //   3403: invokevirtual getApplicationContext : ()Landroid/content/Context;
    //   3406: ldc_w 2131887514
    //   3409: invokevirtual getString : (I)Ljava/lang/String;
    //   3412: invokevirtual append : (Ljava/lang/String;)Ljava/lang/StringBuilder;
    //   3415: pop
    //   3416: aload #12
    //   3418: ldc_w ': '
    //   3421: invokevirtual append : (Ljava/lang/String;)Ljava/lang/StringBuilder;
    //   3424: pop
    //   3425: aload #12
    //   3427: iload_2
    //   3428: invokevirtual append : (I)Ljava/lang/StringBuilder;
    //   3431: pop
    //   3432: aload #21
    //   3434: aload #12
    //   3436: invokevirtual toString : ()Ljava/lang/String;
    //   3439: invokevirtual setText : (Ljava/lang/CharSequence;)V
    //   3442: iload_2
    //   3443: iload_3
    //   3444: if_icmpeq -> 3509
    //   3447: new java/lang/StringBuilder
    //   3450: dup
    //   3451: invokespecial <init> : ()V
    //   3454: astore #12
    //   3456: aload #12
    //   3458: getstatic in/krosbits/musicolet/MyApplication.i : Lin/krosbits/musicolet/MyApplication;
    //   3461: invokevirtual getApplicationContext : ()Landroid/content/Context;
    //   3464: ldc_w 2131887515
    //   3467: invokevirtual getString : (I)Ljava/lang/String;
    //   3470: invokevirtual append : (Ljava/lang/String;)Ljava/lang/StringBuilder;
    //   3473: pop
    //   3474: aload #12
    //   3476: ldc_w ': '
    //   3479: invokevirtual append : (Ljava/lang/String;)Ljava/lang/StringBuilder;
    //   3482: pop
    //   3483: aload #12
    //   3485: iload_3
    //   3486: invokevirtual append : (I)Ljava/lang/StringBuilder;
    //   3489: pop
    //   3490: aload #20
    //   3492: aload #12
    //   3494: invokevirtual toString : ()Ljava/lang/String;
    //   3497: invokevirtual setText : (Ljava/lang/CharSequence;)V
    //   3500: aload #20
    //   3502: iconst_0
    //   3503: invokevirtual setVisibility : (I)V
    //   3506: goto -> 3516
    //   3509: aload #20
    //   3511: bipush #8
    //   3513: invokevirtual setVisibility : (I)V
    //   3516: getstatic in/krosbits/musicolet/MyApplication.j : Lwn1;
    //   3519: getfield c : Llm0;
    //   3522: getfield z : I
    //   3525: ifle -> 3612
    //   3528: new java/lang/StringBuilder
    //   3531: dup
    //   3532: ldc_w '<u>'
    //   3535: invokespecial <init> : (Ljava/lang/String;)V
    //   3538: astore #12
    //   3540: aload #12
    //   3542: getstatic in/krosbits/musicolet/MyApplication.i : Lin/krosbits/musicolet/MyApplication;
    //   3545: invokevirtual getApplicationContext : ()Landroid/content/Context;
    //   3548: ldc_w 2131886520
    //   3551: invokevirtual getString : (I)Ljava/lang/String;
    //   3554: invokevirtual append : (Ljava/lang/String;)Ljava/lang/StringBuilder;
    //   3557: pop
    //   3558: aload #12
    //   3560: ldc_w ': '
    //   3563: invokevirtual append : (Ljava/lang/String;)Ljava/lang/StringBuilder;
    //   3566: pop
    //   3567: aload #12
    //   3569: getstatic in/krosbits/musicolet/MyApplication.j : Lwn1;
    //   3572: getfield c : Llm0;
    //   3575: getfield z : I
    //   3578: invokevirtual append : (I)Ljava/lang/StringBuilder;
    //   3581: pop
    //   3582: aload #12
    //   3584: aload #14
    //   3586: invokevirtual append : (Ljava/lang/String;)Ljava/lang/StringBuilder;
    //   3589: pop
    //   3590: aload #19
    //   3592: aload #12
    //   3594: invokevirtual toString : ()Ljava/lang/String;
    //   3597: invokestatic fromHtml : (Ljava/lang/String;)Landroid/text/Spanned;
    //   3600: invokevirtual setText : (Ljava/lang/CharSequence;)V
    //   3603: aload #19
    //   3605: iconst_0
    //   3606: invokevirtual setVisibility : (I)V
    //   3609: goto -> 3619
    //   3612: aload #19
    //   3614: bipush #8
    //   3616: invokevirtual setVisibility : (I)V
    //   3619: getstatic in/krosbits/musicolet/MyApplication.F : Lyp1;
    //   3622: invokevirtual p : ()Z
    //   3625: ifeq -> 3653
    //   3628: invokestatic o : ()Landroid/content/SharedPreferences;
    //   3631: ldc_w 'b_icdalfl'
    //   3634: iconst_1
    //   3635: invokeinterface getBoolean : (Ljava/lang/String;Z)Z
    //   3640: ifne -> 3684
    //   3643: invokestatic A : ()Ljava/util/ArrayList;
    //   3646: invokevirtual size : ()I
    //   3649: istore_2
    //   3650: goto -> 3686
    //   3653: getstatic android/os/Build$VERSION.SDK_INT : I
    //   3656: bipush #30
    //   3658: if_icmplt -> 3684
    //   3661: getstatic in/krosbits/musicolet/MyApplication.G : Lv90;
    //   3664: invokevirtual b : ()Ljava/util/ArrayList;
    //   3667: invokevirtual size : ()I
    //   3670: getstatic in/krosbits/musicolet/MyApplication.G : Lv90;
    //   3673: invokevirtual d : ()Ljava/util/ArrayList;
    //   3676: invokevirtual size : ()I
    //   3679: iadd
    //   3680: istore_2
    //   3681: goto -> 3686
    //   3684: iconst_0
    //   3685: istore_2
    //   3686: iload_2
    //   3687: ifle -> 3766
    //   3690: new java/lang/StringBuilder
    //   3693: dup
    //   3694: ldc_w '<u>'
    //   3697: invokespecial <init> : (Ljava/lang/String;)V
    //   3700: astore #12
    //   3702: aload #12
    //   3704: getstatic in/krosbits/musicolet/MyApplication.i : Lin/krosbits/musicolet/MyApplication;
    //   3707: invokevirtual getApplicationContext : ()Landroid/content/Context;
    //   3710: ldc_w 2131886605
    //   3713: invokevirtual getString : (I)Ljava/lang/String;
    //   3716: invokevirtual append : (Ljava/lang/String;)Ljava/lang/StringBuilder;
    //   3719: pop
    //   3720: aload #12
    //   3722: ldc_w ': '
    //   3725: invokevirtual append : (Ljava/lang/String;)Ljava/lang/StringBuilder;
    //   3728: pop
    //   3729: aload #12
    //   3731: iload_2
    //   3732: invokevirtual append : (I)Ljava/lang/StringBuilder;
    //   3735: pop
    //   3736: aload #12
    //   3738: aload #14
    //   3740: invokevirtual append : (Ljava/lang/String;)Ljava/lang/StringBuilder;
    //   3743: pop
    //   3744: aload #18
    //   3746: aload #12
    //   3748: invokevirtual toString : ()Ljava/lang/String;
    //   3751: invokestatic fromHtml : (Ljava/lang/String;)Landroid/text/Spanned;
    //   3754: invokevirtual setText : (Ljava/lang/CharSequence;)V
    //   3757: aload #18
    //   3759: iconst_0
    //   3760: invokevirtual setVisibility : (I)V
    //   3763: goto -> 3773
    //   3766: aload #18
    //   3768: bipush #8
    //   3770: invokevirtual setVisibility : (I)V
    //   3773: invokestatic z : ()Ljava/util/ArrayList;
    //   3776: astore #12
    //   3778: aload #12
    //   3780: invokevirtual size : ()I
    //   3783: ifle -> 3866
    //   3786: new java/lang/StringBuilder
    //   3789: dup
    //   3790: ldc_w '<u>'
    //   3793: invokespecial <init> : (Ljava/lang/String;)V
    //   3796: astore #18
    //   3798: aload #18
    //   3800: getstatic in/krosbits/musicolet/MyApplication.i : Lin/krosbits/musicolet/MyApplication;
    //   3803: invokevirtual getApplicationContext : ()Landroid/content/Context;
    //   3806: ldc_w 2131886523
    //   3809: invokevirtual getString : (I)Ljava/lang/String;
    //   3812: invokevirtual append : (Ljava/lang/String;)Ljava/lang/StringBuilder;
    //   3815: pop
    //   3816: aload #18
    //   3818: ldc_w ': '
    //   3821: invokevirtual append : (Ljava/lang/String;)Ljava/lang/StringBuilder;
    //   3824: pop
    //   3825: aload #18
    //   3827: aload #12
    //   3829: invokevirtual size : ()I
    //   3832: invokevirtual append : (I)Ljava/lang/StringBuilder;
    //   3835: pop
    //   3836: aload #18
    //   3838: aload #14
    //   3840: invokevirtual append : (Ljava/lang/String;)Ljava/lang/StringBuilder;
    //   3843: pop
    //   3844: aload #17
    //   3846: aload #18
    //   3848: invokevirtual toString : ()Ljava/lang/String;
    //   3851: invokestatic fromHtml : (Ljava/lang/String;)Landroid/text/Spanned;
    //   3854: invokevirtual setText : (Ljava/lang/CharSequence;)V
    //   3857: aload #17
    //   3859: iconst_0
    //   3860: invokevirtual setVisibility : (I)V
    //   3863: goto -> 3873
    //   3866: aload #17
    //   3868: bipush #8
    //   3870: invokevirtual setVisibility : (I)V
    //   3873: getstatic in/krosbits/musicolet/MyApplication.j : Lwn1;
    //   3876: getfield c : Llm0;
    //   3879: getfield A : I
    //   3882: ifle -> 3969
    //   3885: new java/lang/StringBuilder
    //   3888: dup
    //   3889: ldc_w '<u>'
    //   3892: invokespecial <init> : (Ljava/lang/String;)V
    //   3895: astore #12
    //   3897: aload #12
    //   3899: getstatic in/krosbits/musicolet/MyApplication.i : Lin/krosbits/musicolet/MyApplication;
    //   3902: invokevirtual getApplicationContext : ()Landroid/content/Context;
    //   3905: ldc_w 2131886532
    //   3908: invokevirtual getString : (I)Ljava/lang/String;
    //   3911: invokevirtual append : (Ljava/lang/String;)Ljava/lang/StringBuilder;
    //   3914: pop
    //   3915: aload #12
    //   3917: ldc_w ': '
    //   3920: invokevirtual append : (Ljava/lang/String;)Ljava/lang/StringBuilder;
    //   3923: pop
    //   3924: aload #12
    //   3926: getstatic in/krosbits/musicolet/MyApplication.j : Lwn1;
    //   3929: getfield c : Llm0;
    //   3932: getfield A : I
    //   3935: invokevirtual append : (I)Ljava/lang/StringBuilder;
    //   3938: pop
    //   3939: aload #12
    //   3941: aload #14
    //   3943: invokevirtual append : (Ljava/lang/String;)Ljava/lang/StringBuilder;
    //   3946: pop
    //   3947: aload #16
    //   3949: aload #12
    //   3951: invokevirtual toString : ()Ljava/lang/String;
    //   3954: invokestatic fromHtml : (Ljava/lang/String;)Landroid/text/Spanned;
    //   3957: invokevirtual setText : (Ljava/lang/CharSequence;)V
    //   3960: aload #16
    //   3962: iconst_0
    //   3963: invokevirtual setVisibility : (I)V
    //   3966: goto -> 3976
    //   3969: aload #16
    //   3971: bipush #8
    //   3973: invokevirtual setVisibility : (I)V
    //   3976: getstatic in/krosbits/musicolet/MyApplication.F : Lyp1;
    //   3979: invokevirtual k : ()Ljava/util/ArrayList;
    //   3982: astore #16
    //   3984: new java/util/ArrayList
    //   3987: dup
    //   3988: aload #16
    //   3990: invokevirtual size : ()I
    //   3993: invokespecial <init> : (I)V
    //   3996: astore #12
    //   3998: aload #16
    //   4000: invokevirtual size : ()I
    //   4003: istore_3
    //   4004: iconst_0
    //   4005: istore_2
    //   4006: iload_2
    //   4007: iload_3
    //   4008: if_icmpge -> 4039
    //   4011: aload #16
    //   4013: iload_2
    //   4014: invokevirtual get : (I)Ljava/lang/Object;
    //   4017: astore #17
    //   4019: iinc #2, 1
    //   4022: aload #12
    //   4024: aload #17
    //   4026: checkcast xp1
    //   4029: invokestatic l : (Lxp1;)Ljava/lang/String;
    //   4032: invokevirtual add : (Ljava/lang/Object;)Z
    //   4035: pop
    //   4036: goto -> 4006
    //   4039: aload #16
    //   4041: invokevirtual size : ()I
    //   4044: ifle -> 4160
    //   4047: new java/lang/StringBuilder
    //   4050: dup
    //   4051: invokespecial <init> : ()V
    //   4054: astore #17
    //   4056: aload #17
    //   4058: aload #13
    //   4060: getfield w : Lin/krosbits/musicolet/GhostSearchActivity;
    //   4063: invokevirtual getResources : ()Landroid/content/res/Resources;
    //   4066: ldc_w 2131755024
    //   4069: aload #16
    //   4071: invokevirtual size : ()I
    //   4074: invokevirtual getQuantityString : (II)Ljava/lang/String;
    //   4077: invokevirtual append : (Ljava/lang/String;)Ljava/lang/StringBuilder;
    //   4080: pop
    //   4081: aload #17
    //   4083: ldc_w ' <b>'
    //   4086: invokevirtual append : (Ljava/lang/String;)Ljava/lang/StringBuilder;
    //   4089: pop
    //   4090: aload #17
    //   4092: ldc_w ', '
    //   4095: aload #12
    //   4097: invokestatic join : (Ljava/lang/CharSequence;Ljava/lang/Iterable;)Ljava/lang/String;
    //   4100: invokevirtual append : (Ljava/lang/String;)Ljava/lang/StringBuilder;
    //   4103: pop
    //   4104: aload #17
    //   4106: ldc_w '</b><br/><u>'
    //   4109: invokevirtual append : (Ljava/lang/String;)Ljava/lang/StringBuilder;
    //   4112: pop
    //   4113: aload #17
    //   4115: aload #13
    //   4117: getfield w : Lin/krosbits/musicolet/GhostSearchActivity;
    //   4120: ldc_w 2131886164
    //   4123: invokevirtual getString : (I)Ljava/lang/String;
    //   4126: invokevirtual append : (Ljava/lang/String;)Ljava/lang/StringBuilder;
    //   4129: pop
    //   4130: aload #17
    //   4132: aload #14
    //   4134: invokevirtual append : (Ljava/lang/String;)Ljava/lang/StringBuilder;
    //   4137: pop
    //   4138: aload #15
    //   4140: aload #17
    //   4142: invokevirtual toString : ()Ljava/lang/String;
    //   4145: invokestatic fromHtml : (Ljava/lang/String;)Landroid/text/Spanned;
    //   4148: invokevirtual setText : (Ljava/lang/CharSequence;)V
    //   4151: aload #15
    //   4153: iconst_0
    //   4154: invokevirtual setVisibility : (I)V
    //   4157: goto -> 4167
    //   4160: aload #15
    //   4162: bipush #8
    //   4164: invokevirtual setVisibility : (I)V
    //   4167: aload #13
    //   4169: getfield b : Lss0;
    //   4172: iconst_1
    //   4173: invokevirtual setCancelable : (Z)V
    //   4176: aload #13
    //   4178: getfield y : Z
    //   4181: ifeq -> 4229
    //   4184: aload #13
    //   4186: iconst_0
    //   4187: putfield y : Z
    //   4190: aload #13
    //   4192: getfield b : Lss0;
    //   4195: invokevirtual dismiss : ()V
    //   4198: goto -> 4229
    //   4201: aload #13
    //   4203: getfield b : Lss0;
    //   4206: astore #12
    //   4208: aload #12
    //   4210: ifnull -> 4229
    //   4213: aload #12
    //   4215: invokevirtual isShowing : ()Z
    //   4218: ifeq -> 4229
    //   4221: aload #13
    //   4223: getfield b : Lss0;
    //   4226: invokevirtual dismiss : ()V
    //   4229: return
    //   4230: astore #12
    //   4232: goto -> 2244
    //   4235: astore #12
    //   4237: goto -> 2268
    //   4240: astore #12
    //   4242: goto -> 2714
    //   4245: astore #12
    //   4247: goto -> 2799
    // Exception table:
    //   from	to	target	type
    //   132	145	148	java/lang/Exception
    //   661	671	696	java/lang/SecurityException
    //   671	682	688	finally
    //   682	685	696	java/lang/SecurityException
    //   690	693	688	finally
    //   693	696	696	java/lang/SecurityException
    //   786	799	844	finally
    //   846	849	844	finally
    //   978	990	993	finally
    //   995	1007	1010	java/lang/Exception
    //   995	1007	1010	java/lang/Error
    //   1067	1080	1323	finally
    //   1098	1113	1186	finally
    //   1130	1135	1186	finally
    //   1139	1147	1186	finally
    //   1151	1159	1186	finally
    //   1163	1172	1186	finally
    //   1176	1183	1186	finally
    //   1195	1202	1186	finally
    //   1206	1211	1186	finally
    //   1215	1220	1186	finally
    //   1224	1232	1186	finally
    //   1236	1245	1186	finally
    //   1249	1257	1186	finally
    //   1261	1268	1186	finally
    //   1268	1311	1323	finally
    //   1328	1371	1323	finally
    //   1371	1374	1323	finally
    //   1479	1490	1493	finally
    //   1498	1509	1493	finally
    //   1510	1513	1493	finally
    //   2226	2244	4230	finally
    //   2245	2268	4235	finally
    //   2318	2344	2447	finally
    //   2349	2379	2447	finally
    //   2384	2423	2447	finally
    //   2426	2434	2447	finally
    //   2434	2444	2447	finally
    //   2509	2543	2546	finally
    //   2551	2558	2546	finally
    //   2630	2638	4240	finally
    //   2641	2648	4240	finally
    //   2653	2695	4240	finally
    //   2695	2714	4240	finally
    //   2742	2772	4245	finally
    //   2778	2784	4245	finally
    //   2784	2799	4245	finally
  }
}


/* Location:              C:\Users\Kevin\Downloads\dex-tools-v2.4\dex-tools-v2.4\musicolet-dex2jar.jar!\yi1.class
 * Java compiler version: 6 (50.0)
 * JD-Core Version:       1.1.3
 */